Workbook
Name \P: #REF!
Name \P: #REF!
Name \PP: #REF!
Name \Q: #REF!
Name ___pg1: #REF!
Name ___pg1: #REF!
Name ___pg1: #REF!
Name ___pg1: #REF!
Name ___pg1: #REF!
Name __DTL1: #REF!
Name __DTL1: #REF!
Name __DTL1: #REF!
Name __DTL1: #REF!
Name __DTL1: #REF!
Name __pg1: #REF!
Name __pg1: #REF!
Name __pg1: #REF!
Name __pg1: #REF!
Name __pg1: #REF!
Name _DTL1: #REF!
Name _DTL1: #REF!
Name _DTL1: #REF!
Name _DTL1: #REF!
Name _DTL1: #REF!
Name _pg1: #REF!
Name _pg1: #REF!
Name _pg1: #REF!
Name _pg1: #REF!
Name _pg1: #REF!
Name _Q: #REF!
Name ASRFY: Input!$F$49
Name BExGrid1: #REF!
Name BExItemGrid: #REF!
Name bs: #REF!
Name bs: #REF!
Name bs: #REF!
Name bs: #REF!
Name bs: #REF!
Name bss: #REF!
Name bss: #REF!
Name bss: #REF!
Name bss: #REF!
Name bss: #REF!
Name BU: [1]Drop_Downs!$A$5:$A$22
Name BudgetOwner: #REF!
Name BudgetOwner: #REF!
Name BudgetOwner: #REF!
Name BUTable: [1]Drop_Downs!$A$37:$B$50
Name CASHFLOWS: #REF!
Name Cat: [1]Drop_Downs!$O$32:$O$39
Name Comp: Input!$D$51
Name COMPARISON: #REF!
Name COMPARISON: #REF!
Name CurrentFY: Input!$F$48
Name CurrentFYPriorSub: Current_Prior!$BQ$33
Name DefExitFY: Input!$N$59
Name DefExitFYOrig: HistInfo!$AB$44
Name DEMAND: #REF!
Name DEMAND: #REF!
Name DEMAND: #REF!

Sheet Inst
B2: Instructions
B4: Steps to incorporate Financial Template to your current R&D Business Cases
C5: 1 | H5: Create and Move a copy of all green tabs from this file ("Inst", "Input", "Calc", "Current_Prior", "HistInfo" "PPT" and "PPD_DD") to your current business case (BC) models.
C6: =C5+1 -> 2 | H6: Populate and Link information at "Input", "Calc", "Current_Prior" and "HistInfo". "PPT" tab is a summary of recommended information to be used in R&D BC discussions.
C7: =C6+1 -> 3 | H7: Save new BC package (BC model + Financial Template) at R&D BC Sharepoint. Access is segregated by BU folder. Keep a "live" file, which should be updated any time that project has a significant change, exits any GPDS phase, goes through ASR and budget review cycles. However, before updating BC at Sharepoint, make sure that you create a copy of previous version and save it at Repositorium/Historical folder (it is important to keep previous BC versions to assuring continuity and to avoid information loss, mainly when associates rotate to new positions).
B9: Tab: Basic Input (Input)
C10: # | D10: Columns | F10: Rows
C11: 1 | D11: =HLOOKUP(COLUMN(Input!A2),FT_PPD_DD!$A$116:$DZ$117,2,0) -> A | E11: =HLOOKUP(COLUMN(Input!R2),FT_PPD_DD!$A$116:$DZ$117,2,0) -> R | F11: =ROW(Input!A2) -> 2 | G11: =ROW(Input!R112) -> 112 | H11: Required Input: fileds in this session will load formulas on following tabs
C12: =C11+1 -> 2 | F12: =ROW(Input!D4) -> 4 | H12: Segment: Input Segment name
C13: =C12+1 -> 3 | F13: =ROW(Input!D5) -> 5 | H13: Business Unit: Input BU name
C14: =C13+1 -> 4 | F14: =ROW(Input!D7) -> 7 | H14: Update Date: Input last update date (calendar year)
C15: =C14+1 -> 5 | F15: =ROW(Input!D8) -> 8 | H15: PDT (Portfolio Decision Team): Input date of last PDT (calendar year)
C16: =C15+1 -> 6 | F16: =ROW(Input!D10) -> 10 | H16: Business Case (BC) Name: Input Business Case Name
C17: =C16+1 -> 7 | F17: =ROW(Input!D11) -> 11 | H17: Business Case Identification (BCID): Input Business Case ID number
C18: =C17+1 -> 8 | F18: =ROW(Input!D12) -> 12 | H18: 15 Yr Business Case?: Using drop down list, select whether project is a 10 or 15 yr time horizon. NOTE: standard guide is to projects be under 10 yr time horizon - 15 yr projects should be approved on an exception base
C19: =C17+1 -> 8 | F19: =ROW(Input!D15) -> 15 | H19: BPC Number: Input BPC project number and names associated to business case. It might be the case that multiple BPC projects refer to a single business case (BC)
C20: =C19+1 -> 9 | F20: =ROW(Input!D32) -> 32 | G20: =ROW(Input!D36) -> 36 | H20: Input product name. If business case is compounded by multiple products, list product names on following columns, starting on column D with most representative product in sales
C21: =C20+1 -> 10 | F21: =ROW(Input!D47) -> 47 | H21: Project Start FY: Input project start fiscal year
C22: =C21+1 -> 11 | F22: =ROW(Input!D48) -> 48 | H22: Current FY: Input current fiscal year
C23: =C22+1 -> 12 | F23: =ROW(Input!D49) -> 49 | H23: ASR FY: Input first year of ASR period
C24: =C23+1 -> 13 | F24: =ROW(Input!D51) -> 51 | H24: Comparison Scenario: Use drop down list to select compariosn bases. The default comparison base is the Def Exit scenario, but there are cases that a new rebaseline was approved and set as comparison scenario
C25: =C24+1 -> 14 | F25: =ROW(Input!D52) -> 52 | H25: If Rebaseline, input switch date: provide date of rebaseline, if a new scenario other than the Def Exit is been used
C26: =C25+1 -> 15 | F26: =ROW(Input!D55) -> 55 | H26: Current GPDS Phase: Input current GPDS phase (Concept, Definition, Development, Qualification, Launch). If project has multiple phase, input phase related to the most relevant product
C27: =C26+1 -> 16 | F27: =ROW(Input!D57) -> 57 | H27: Project Start: Input month and year of project start (calendar year)
C28: =C27+1 -> 17 | D28: =HLOOKUP(COLUMN(Input!D58),FT_PPD_DD!$A$116:$DZ$117,2,0) -> D | E28: =HLOOKUP(COLUMN(Input!H63),FT_PPD_DD!$A$116:$DZ$117,2,0) -> H | F28: =ROW(Input!D58) -> 58 | G28: =ROW(Input!E63) -> 63 | H28: Date of Exit GPDS Phase (Mth/Year): for each GPDS phase listed (Concept, Definition, Development, Qualification, Launch), input month and year (calendar year) of exiting. Use Commitment column to input dates expected to project exit each phase by the time that Project Exited Definition phase. Use "Current" column to input actual and/or most updated dates. Definition and Launch Current and Exit fileds will be used to adjust formulas at "Calculation" and "Presentation" tabs
C29: =C28+1 -> 18 | F29: =ROW(Input!D66) -> 66 | H29: Tax Rate: Input tax rate used for modeling
C30: =C29+1 -> 19 | F30: =ROW(Input!D67) -> 67 | H30: Tax Rate: Input tax rate used in Definition Exit or Rebaseline scenario. If there is no distinction, please input same number on both fields
C31: =C30+1 -> 20 | F31: =ROW(Input!D68) -> 68 | H31: Discount Rate: Input discount rate used for modeling. Discount rate will also be considered as project hurdle rate
C32: =C31+1 -> 21 | F32: =ROW(Input!D69) -> 69 | H32: Discount Rate @ Def Exit: If project had a different discount rate by the time that it exited Definition GPDS phase, insert its rate at this row
C33: =C32+1 -> 22 | F33: =ROW(Input!D70) -> 70 | H33: Commercial Risk: Input Commercail risk of project; use drop down list (low, medium, high)
C34: =C33+1 -> 23 | F34: =ROW(Input!D71) -> 71 | H34: Technical Risk: Input Technical risk of project; use drop down list (low, medium, high)
C35: =C34+1 -> 24 | F35: =ROW(Input!D72) -> 72 | H35: Finance Rate (for MIRR calc): Input finance rate (used to calculate MIRR); this is the cost of capital that is funding the project. BD WACC is a resonable rate, if project is funded internally (no debt is required to fund it). Please, double check most updated BD WACC rate (we are currently using 8%)
C36: =C35+1 -> 25 | F36: =ROW(Input!D73) -> 73 | H36: Reinvestment Rate (for MIRR calc): Input reinvestment rate (used to calculate MIRR); it represents the rate at which project cash flow is reinvested. Per capital recommendation, rate should be 12.5%
C37: =C36+1 -> 26 | F37: =ROW(Input!D74) -> 74 | H37: Growth Rate (for Terminal Value calc): Input growth rate used for modeling terminal value, if applicable
C38: =C37+1 -> 27 | F38: =ROW(Input!D76) -> 76 | G38: =ROW(Input!E78) -> 78 | H38: Number of Days (for Working Capital calculation): Input number of days to be considered in each of those 3 metrics: DSO (Receivables), DPO (Payables), DIO (Inventories). Columns J and K show BDX days related to FY16 actual figures. If needed, as reference, "PPD_DD" tab, rows 101 to 113 show a more detailed breakdown by BU (for DIO) and by region (for DSO and DPO) as FY16 actuals. Figures provide by Treasury.
C39: =C38+1 -> 28 | D39: =HLOOKUP(COLUMN(Input!B81),FT_PPD_DD!$A$116:$DZ$117,2,0) -> B | F39: =ROW(Input!D81) -> 81 | H39: SMS Name: Input SMS (Strategic Market Space) name, using drop down list. Based on the SMS name, table will automatically load remaining information. If you have a new SMS, override formula and fill information accordingly
C40: =C39+1 -> 29 | F40: =ROW(Input!D82) -> 82 | H40: Quadrant: Populated automatically; Input SMS quadrant, if formula does not work
C41: =C40+1 -> 30 | F41: =ROW(Input!D83) -> 83 | H41: SMS FY17 Rev ($ M): Populated automatically; Input revenues related to SMS as FY current year or most updated revenue expectation on SMS category, if formula does not work
C42: =C41+1 -> 31 | F42: =ROW(Input!D84) -> 84 | H42: FY17 Share: Populated automatically; Input share defined by SMS FY 15 Revenues divided by Size Addressable FY 17 WW Mkt ($ M), if formula does not work
C43: =C42+1 -> 32 | F43: =ROW(Input!D85) -> 85 | H43: Size Addressable FY 17 WW Mkt ($ M): Populated automatically; Input size in dollar amount of addressabale worldwide SMS market as FY17, if formula does not work
C44: =C43+1 -> 33 | F44: =ROW(Input!D86) -> 86 | H44: Addressable FY17-FY22 WW Mkt growth (%): Populated automatically; Input growth CAGR %, defined by the worldwide SMS market size in FY22 over FY17, if formula does not work
C45: =C44+1 -> 34 | F45: =ROW(Input!D87) -> 87 | H45: FY22 Std Gross Margin %: Populated automatically; Input expected gross margin % of SMS in FY22, if formula does not work
C46: =C45+1 -> 35 | D46: =HLOOKUP(COLUMN(Input!D88),FT_PPD_DD!$A$116:$DZ$117,2,0) -> D | F46: =ROW(Input!D88) -> 88 | H46: Technology Innovation Quadrant: Select quadrant that refers to your project (Disruptive, Architectural, Routine, Radical)
C47: =C46+1 -> 36 | F47: =ROW(Input!D89) -> 89 | H47: Standard Discount Rate (Hurdle Rate): This cell shows the recommended discount rate to be used by business case, as an output of combination of SMS and Technology Innovation Quadrants
C48: =C47+1 -> 37 | F48: =ROW(Input!D92) -> 92 | H48: # Years to Reach Target Conversion (aft launch): Input number of years to reach target conversion
C49: =C48+1 -> 38 | F49: =ROW(Input!D93) -> 93 | H49: Peak Category Share: Input peak category share, based on dollar amount
C50: =C49+1 -> 39 | F50: =ROW(Input!D94) -> 94 | H50: Product Life Cycle (Yrs after launch): Input expected product life cycle, counting on launch year
C51: =C50+1 -> 40 | D51: =HLOOKUP(COLUMN(Input!B99),FT_PPD_DD!$A$116:$DZ$117,2,0) -> B | E51: =HLOOKUP(COLUMN(Input!E105),FT_PPD_DD!$A$116:$DZ$117,2,0) -> E | F51: =ROW(Input!D99) -> 99 | G51: =ROW(Input!E105) -> 105 | H51: BC Owners: provide Finance, Marketing, R&D and Operations associates that were responsible for developing BC and last time that they reviewed BC figures (calendar year). By inputing name and date of last review, they acknoledge that they believe and commit to assumptions, timelines out outcomes.
C52: =C51+1 -> 41 | F52: =ROW(Input!D96) -> 96 | H52: Attestation Statement: please, read it before signing project
C53: =C52+1 -> 42 | D53: =HLOOKUP(COLUMN(Input!B39),FT_PPD_DD!$A$116:$DZ$117,2,0) -> B | E53: =HLOOKUP(COLUMN(Input!E44),FT_PPD_DD!$A$116:$DZ$117,2,0) -> E | F53: =ROW(Input!D39) -> 39 | G53: =ROW(Input!E44) -> 44 | H53: Project Description: Input a high level project description
B55: Tab: Calculation (Calc)
C57: General Rules
H58: Link cells to business case tabs or hard code figures (past as values)
H59: Input from Marketing - if available
H60: Manual Input
H61: Sub-totals or/and automated formulas based on dates (calculations should automatically roll for FY change) or links to "Input & Assumptions" tab
C63: Revenue and Profitability Input
C64: # | D64: Columns | F64: Rows
C65: 1 | F65: =ROW(Calc!G10) -> 10 | H65: New Product Volume: link new product volumes to your financial model in green cells. Volumes to be provide in thousands
C66: =+C65+1 -> 2 | F66: =ROW(Calc!G11) -> 11 | H66: New Product ASP: link new product Average Selling Price (ASP) to your financial model
C67: =+C66+1 -> 3 | F67: =ROW(Calc!G13) -> 13 | H67: Cannibalization $: link cannibalization as a negative number; Definition: sales reduction on current portfolio due to introduction of this new product
C68: =+C67+1 -> 4 | F68: =ROW(Calc!G14) -> 14 | H68: Pull-Through $: link pull-through as a positive number; Definition: additional sales of other products due to introduction of this new product, also named as indirect revenues
C69: =+C68+1 -> 5 | F69: =ROW(Calc!G15) -> 15 | H69: Loss Avoidance $: link avoidance as a positive number ; Definition: revenues that would be lost, if new product is not launched
C70: =+C69+1 -> 6 | F70: =ROW(Calc!G16) -> 16 | H70: Total Incremental Revenue: formula; this line should tie to your incremental revenue in the business case model
C71: =+C70+1 -> 7 | F71: =ROW(Calc!G17) -> 17 | H71: Volume Category Share (%): provide category share based on volumes, excluding pull-through revenues. Total Addressable Market (TAM) should be basis for calculation.
C72: =+C71+1 -> 8 | F72: =ROW(Calc!G18) -> 18 | H72: $ Category Share (%): provide category share based on dollar amount, excluding pull-through revenues. Total Addressable Market (TAM) should be basis for calculation.
C73: =+C72+1 -> 9 | F73: =ROW(Calc!G19) -> 19 | H73: True Incremental Revenue (exc. Loss Avoid): formula; this line should source and tie to PPD file. It basically subtract Cannibalization and adds Pull Through to Revenues
C74: =+C73+1 -> 10 | F74: =ROW(Calc!G20) -> 20 | H74: New Product ASR Rev (Hyperion): Input the New Product Revenue submitted in Hyperion for the most recent ASR submission. Leave revenues related to years not covered in ASR in blank; Leave in blank, if not applicable.
C75: =+C74+1 -> 11 | F75: =ROW(Calc!G21) -> 21 | H75: New Product Revenue vs ASR Revenue: Difference between New Product Revenue and ASR Revenue
C76: =+C75+1 -> 12 | F76: =ROW(Calc!G22) -> 22 | H76: Std Cost w/ Depr ($): Standard cost per unit for the new product with depreciation (should not consider variances)
C77: =+C76+1 -> 13 | F77: =ROW(Calc!G23) -> 23 | H77: Std Cost w/o Depr ($): Standard cost per unit for the new product without depreciation (should not consider variances)
C78: =+C77+1 -> 14 | F78: =ROW(Calc!G24) -> 24 | G78: =ROW(Calc!G25) -> 25 | H78: Gross Profit Information. New Product Gross Profit and Gross Profit % are formulas
C79: =+C78+1 -> 15 | F79: =ROW(Calc!G26) -> 26 | G79: =ROW(Calc!G27) -> 27 | H79: Gross Profit Information. Provide GP % information of BD's Product Family (line 26) and Competitor's GP (Market GP%, line 27)
C80: =+C79+1 -> 16 | F80: =ROW(Calc!G30) -> 30 | G80: =ROW(Calc!G111) -> 111 | H80: Multiple revenue source: For projects with multiple revenue source, uncollapse aggregate button (or unhide lines) on row 30 in order to input detailed information by product. In total, Financial Template can capture 5 products. As guideline, use this functionality for distinct product lines, e.g. reagents and instruments
C81: =+C80+1 -> 17 | D81: =HLOOKUP(COLUMN(Calc!G10),FT_PPD_DD!$A$116:$DZ$117,2,0) -> G | E81: =HLOOKUP(COLUMN(Calc!AI10),FT_PPD_DD!$A$116:$DZ$117,2,0) -> AI | H81: Revenue and Profitability Input (K): Latest Update: Information to be provided based on latest Business Case update. FY counter starts on project start year.
C82: =+C81+1 -> 18 | D82: =HLOOKUP(COLUMN(Calc!AQ11),FT_PPD_DD!$A$116:$DZ$117,2,0) -> AQ | E82: =HLOOKUP(COLUMN(Calc!BS11),FT_PPD_DD!$A$116:$DZ$117,2,0) -> BS | H82: Revenue and Profitability Input (K): Definition Exit: Information to be provided based on Definition Exit GPDS phase. Although FY counter starts on project start year, figures related to years before the Def Exit phase should be blank.
C83: =+C82+1 -> 19 | D83: =HLOOKUP(COLUMN(Calc!CA12),FT_PPD_DD!$A$116:$DZ$117,2,0) -> CA | E83: =HLOOKUP(COLUMN(Calc!DF12),FT_PPD_DD!$A$116:$DZ$117,2,0) -> DF | H83: H / (L) vs. Definition Exit: columns to calculate high and lows; they are the difference between Current info and Def Exit (no need to take any action, formulas are automated)
C85: P&L and Free Cash Flow
C86: # | D86: Columns | F86: Rows
C87: 1 | F87: =ROW(Calc!G127) -> 127 | G87: =ROW(Calc!G130) -> 130 | H87: Revenue, Growth, Category Share, True Inc Rev (exc. Loss Avoidance): automatically pull information from Revenue and Profitability session
C88: =+C87+1 -> 2 | F88: =ROW(Calc!G129) -> 129 | H88: Category Share: Formula is linked to category Share provided on Revenue Build Up at 1st product based on drop down list available at cell "C129" (Dollar ($) or Volume (units)). Formula can be overwritten, if needed; i.e. multiple product revenues are considered on business case - please calculate a new category share (dollar seems to be more applicable) including the whole category as basis
C89: =+C88+1 -> 3 | F89: =ROW(Calc!G131) -> 131 | H89: Cost of Sales: Link Cost of Sales (excluding depreciation) from business case (positive number). This line should consider all product related costs, including variances
C90: =+C89+1 -> 4 | F90: =ROW(Calc!G132) -> 132 | H90: Depreciation: Link Depreciation from business case (positive number)
C91: =+C90+1 -> 5 | F91: =ROW(Calc!G133) -> 133 | H91: Gross Profit: Calculates GP = Revenues - Cost of Sales - Depreciation
C92: =+C91+1 -> 6 | F92: =ROW(Calc!G135) -> 135 | H92: SSG&A: Link SSG&A from business case. All SSG&A expenses related to BC should be considered in this line
C93: =+C92+1 -> 7 | F93: =ROW(Calc!G136) -> 136 | H93: R&D: Link R&D from business case. All R&D expenses related to BC should be considered in this line
C94: =+C93+1 -> 8 | F94: =ROW(Calc!G137) -> 137 | H94: OIBT: Operating Income Before Taxes; OIBT = GP - SSG&A - R&D
C95: =+C94+1 -> 9 | F95: =ROW(Calc!G139) -> 139 | H95: Other (Inc) / Exp: Include any Other Income or Expenses that should be considererd in project
C96: =+C95+1 -> 10 | F96: =ROW(Calc!G140) -> 140 | H96: Tax Exp / Ben: Calculates taxes automatically based on tax rate
C97: =+C96+1 -> 11 | F97: =ROW(Calc!G141) -> 141 | H97: Net Income: Automatically calculated: NI = OIBT - OIE -Tax
C98: =+C97+1 -> 12 | F98: =ROW(Calc!G143) -> 143 | H98: Capital Expenses: Link Capital from business case (positive number)
C99: =+C98+1 -> 13 | F99: =ROW(Calc!G144) -> 144 | H99: Increase in Working Capital: ield is automatically populated based on COGS, Revenues and number of days provided for DPO, DSO, DIO at Input tab. Formulas are available at rows 244 to 255.
C100: =+C99+1 -> 14 | F100: =ROW(Calc!G145) -> 145 | H100: Free Cash Flow: Calculates FCF = NI - Capital - Inc in WC + Depreciation
C101: =+C100+1 -> 15 | D101: =HLOOKUP(COLUMN(Calc!G147),FT_PPD_DD!$A$116:$DZ$117,2,0) -> G | E101: =HLOOKUP(COLUMN(Calc!AI147),FT_PPD_DD!$A$116:$DZ$117,2,0) -> AI | F101: =ROW(Calc!G147) -> 147 | H101: Discounted Free Cash Flow: This row shows the FCF discounted to Current FY (as set at Input tab). It does not consider: TV nor Undepreciated Capital
C102: =+C101+1 -> 16 | D102: =HLOOKUP(COLUMN(Calc!AQ147),FT_PPD_DD!$A$116:$DZ$117,2,0) -> AQ | E102: =HLOOKUP(COLUMN(Calc!BS147),FT_PPD_DD!$A$116:$DZ$117,2,0) -> BS | F102: =ROW(Calc!G147) -> 147 | H102: Discounted Free Cash Flow: This row shows the FCF discounted to Def Exit FY (as set at Input tab). It does not consider: TV nor Undepreciated Capital
C103: =+C102+1 -> 17 | D103: =HLOOKUP(COLUMN(Calc!F124),FT_PPD_DD!$A$116:$DZ$117,2,0) -> F | H103: All Sunk Costs in Column F are automatically calculated based on the dates you provided in the "Basic Input & Assumptions" Tab
C104: =+C103+1 -> 18 | D104: =HLOOKUP(COLUMN(Calc!G124),FT_PPD_DD!$A$116:$DZ$117,2,0) -> G | E104: =HLOOKUP(COLUMN(Calc!AI147),FT_PPD_DD!$A$116:$DZ$117,2,0) -> AI | H104: P&L and FCF Input (K): Latest Update: Information to be provided based on latest Business Case update. FY counter starts on project start year; as a result, previous FYs (before the current update) should be populated with actual figures and will be treated as sunk costs
C105: =+C104+1 -> 19 | D105: =HLOOKUP(COLUMN(Calc!AQ124),FT_PPD_DD!$A$116:$DZ$117,2,0) -> AQ | E105: =HLOOKUP(COLUMN(Calc!BS147),FT_PPD_DD!$A$116:$DZ$117,2,0) -> BS | H105: P&L and FCF Input (K): Definition Exit: Information to be provided based on Definition Exit GPDS phase. As Definition Exit FY occurs later than project start, fields related to years before the Def Exit phase may be left blank, if info is not available. Moreover, Definition Exit figures are static and should not be changed throughout project evolution, unless there is a Rebaseline in place.
C106: =+C105+1 -> 20 | D106: =HLOOKUP(COLUMN(Calc!CA124),FT_PPD_DD!$A$116:$DZ$117,2,0) -> CA | E106: =HLOOKUP(COLUMN(Calc!DF147),FT_PPD_DD!$A$116:$DZ$117,2,0) -> DF | H106: H / (L) vs. Definition Exit: columns to calculate high and lows; they are the difference between Current info and Def Exit (no need to take any action, formulas are automated)
C107: =+C106+1 -> 21 | D107: =HLOOKUP(COLUMN(Calc!U176),FT_PPD_DD!$A$116:$DZ$117,2,0) -> U | F107: =ROW(Calc!U176) -> 176 | G107: =ROW(Calc!U179) -> 179 | H107: Terminal Value (TV): It is strongly recommended not to use TV. The reason is that products will probably require future capital investments by the end of life cycle and revenues will probably not be in the level indefinitely, what raises the point that the use of a Terminal Value may not be appropriate. If your BC requires a Terminal Value Calculation, spreadsheet is built with perpetuity formula "LastFCF*(1+g)/(r-g)", which is linked to last Free Cash Flow, discount rate and growth rate (the last two were defined on Input tab). If your BC requires a different way to calculate the Terminal Value, you may overhide the formula. As Terminal Value should be considered on the last year of project, you will notice that there are four lines related to Terminal Value, deppending on the last period of the scenarios considered on return metrics calculation session at BC template. Instead of using TV, you may extend your FCF calculations for the next years (extended time horizon - 15 years) as an exception. The standard time horizon for project life is 10 years and 15 year projects are treated as exception
...

Sheet Input
B2: Required Inputs (feed template fornulas) | U2: Additional Inputs (provide extra contextect to project - not linked to formulas)
B4: Segment | D4: Life Sciences
B5: Business Unit | D5: BDB
B7: Latest Update on (calendar year): | D7: N/A | E7: N/A | F7: N/A
B8: Latest Portfolio Decision Team - PDT on (calendar year): | D8: N/A | E8: N/A | F8: N/A
B10: Business Case Name
B11: Business Case Identification (BCID)
B12: 15 Yr Business Case? (Y/N) | D12: Yes (exception)
B14: BPC Projects Associated to Business Case: | D14: Code | J14: Name
B31: New Product (NP) Revenue Build Up | D31: Name
B32: NP - Main | D32: A
B33: NP 2 | D33: B
B34: NP 3 | D34: C
B35: NP 4 | D35: D
B36: NP 5 | D36: E
B38: Project Description
B39: <<Please provide a brief and high level project / product description; no need to be a technical explanation>>
B46: Dates and Terms - Fiscal Year Input
B47: Project Start FY | D47: FY18 | F47: =RIGHT(D47,2)*1 -> 18
B48: Current FY | D48: FY18 | F48: =RIGHT(D48,2)*1 -> 18
B49: ASR FY (start yr) | D49: N/A | F49: =RIGHT(D49,2)*1 -> #VALUE!
B51: Comparison Scenario | D51: Def Exit | U51: Information provided in this session is not physically linked to template formulas (further tabs or left side of this tab). However, you may prefer to link them, if applicable to your model.
B52: If Rebaseline, input switch date (Calendar Year) | D52: N/A | E52: N/A | U52: Dates of Exit GPDS Phase: Month / Calendar Year
B54: GPDS Phase and Terms | U54: Product or Region | V54: <Name> | AA54: <Name> | AF54: <Name> | AK54: <Name> | AP54: <Name>
B55: Current GPDS Phase | D55: N/A | J55: Fiscal Year Equivalent | U55: Current GPDS Phase | V55: N/A | AA55: N/A | AF55: N/A | AK55: N/A | AP55: N/A
B56: Dates of Exit GPDS Phase: Month / Calendar Year | D56: Current | F56: Commitment | J56: Current | L56: Commit | U56: Month / Calendar Year | V56: Current | X56: Commitment | AA56: Current | AC56: Commitment | AF56: Current | AH56: Commitment | AK56: Current | AM56: Commitment | AP56: Current | AR56: Commitment
B57: Project Start | D57: N/A | E57: N/A | F57: N/A | G57: 16 | H57: N/A | J57: ="FY"&IF(OR(D57="Oct",D57="Nov",D57="Dec"),E57+1,E57) -> FYN/A | L57: ="FY"&IF(OR(F57="Oct",F57="Nov",F57="Dec"),H57+1,H57) -> FYN/A
B58: Concept | D58: N/A | E58: N/A | F58: N/A | G58: 16 | H58: N/A | J58: ="FY"&IF(OR(D58="Oct",D58="Nov",D58="Dec"),E58+1,E58) -> FYN/A | L58: ="FY"&IF(OR(F58="Oct",F58="Nov",F58="Dec"),H58+1,H58) -> FYN/A | U58: Concept | V58: N/A | W58: N/A | X58: N/A | Y58: N/A | AA58: N/A | AB58: N/A | AC58: N/A | AD58: N/A | AF58: N/A | AG58: N/A | AH58: N/A | AI58: N/A | AK58: N/A | AL58: N/A | AM58: N/A | AN58: N/A | AP58: N/A | AQ58: N/A | AR58: N/A | AS58: N/A
B59: Definition | D59: N/A | E59: N/A | F59: N/A | G59: 16 | H59: N/A | J59: ="FY"&IF(OR(D59="Oct",D59="Nov",D59="Dec"),E59+1,E59) -> FYN/A | L59: ="FY"&IF(OR(F59="Oct",F59="Nov",F59="Dec"),H59+1,H59) -> FYN/A | N59: =RIGHT(J59,2)*1 -> #VALUE! | U59: Definition | V59: N/A | W59: N/A | X59: N/A | Y59: N/A | AA59: N/A | AB59: N/A | AC59: N/A | AD59: N/A | AF59: N/A | AG59: N/A | AH59: N/A | AI59: N/A | AK59: N/A | AL59: N/A | AM59: N/A | AN59: N/A | AP59: N/A | AQ59: N/A | AR59: N/A | AS59: N/A
D60: Current | F60: =Comp&" Commit" -> Def Exit Commit | V60: Current | X60: =Comp&" Commit" -> Def Exit Commit | AA60: Current | AC60: =Comp&" Commit" -> Def Exit Commit | AF60: Current | AH60: =Comp&" Commit" -> Def Exit Commit | AK60: Current | AM60: =Comp&" Commit" -> Def Exit Commit | AP60: Current | AR60: =Comp&" Commit" -> Def Exit Commit
B61: Development | D61: N/A | E61: N/A | F61: N/A | G61: 16 | H61: N/A | J61: ="FY"&IF(OR(D61="Oct",D61="Nov",D61="Dec"),E61+1,E61) -> FYN/A | L61: ="FY"&IF(OR(F61="Oct",F61="Nov",F61="Dec"),H61+1,H61) -> FYN/A | U61: Development | V61: N/A | W61: N/A | X61: N/A | Y61: N/A | AA61: N/A | AB61: N/A | AC61: N/A | AD61: N/A | AF61: N/A | AG61: N/A | AH61: N/A | AI61: N/A | AK61: N/A | AL61: N/A | AM61: N/A | AN61: N/A | AP61: N/A | AQ61: N/A | AR61: N/A | AS61: N/A
B62: Qualification | D62: N/A | E62: N/A | F62: N/A | G62: 16 | H62: N/A | J62: ="FY"&IF(OR(D62="Oct",D62="Nov",D62="Dec"),E62+1,E62) -> FYN/A | L62: ="FY"&IF(OR(F62="Oct",F62="Nov",F62="Dec"),H62+1,H62) -> FYN/A | U62: Qualification | V62: N/A | W62: N/A | X62: N/A | Y62: N/A | AA62: N/A | AB62: N/A | AC62: N/A | AD62: N/A | AF62: N/A | AG62: N/A | AH62: N/A | AI62: N/A | AK62: N/A | AL62: N/A | AM62: N/A | AN62: N/A | AP62: N/A | AQ62: N/A | AR62: N/A | AS62: N/A
B63: Launch | D63: N/A | E63: N/A | F63: N/A | H63: N/A | J63: ="FY"&IF(OR(D63="Oct",D63="Nov",D63="Dec"),E63+1,E63) -> FYN/A | L63: ="FY"&IF(OR(F63="Oct",F63="Nov",F63="Dec"),H63+1,H63) -> FYN/A | N63: =RIGHT(J63,2)*1 -> #VALUE! | O63: =RIGHT(L63,2)*1 -> #VALUE! | U63: Launch | V63: N/A | W63: N/A | X63: N/A | Y63: N/A | AA63: N/A | AB63: N/A | AC63: N/A | AD63: N/A | AF63: N/A | AG63: N/A | AH63: N/A | AI63: N/A | AK63: N/A | AL63: N/A | AM63: N/A | AN63: N/A | AP63: N/A | AQ63: N/A | AR63: N/A | AS63: N/A
U64: ="Revenue Rep (DefExit 10 or 15yrs)" -> Revenue Rep (DefExit 10 or 15yrs) | X64: 0 | AC64: 0 | AH64: 0 | AM64: 0 | AR64: 0
B65: Financial Inputs
B66: Tax Rate @ Act/Projection Scenarios | D66: 0.28 | F66: =D66 -> 0.28
B67: ="Tax Rate @ "&Comp&" Scenario (if different)" -> Tax Rate @ Def Exit Scenario (if different) | D67: =D66 -> 0.28 | F67: =D67 -> 0.28
B68: Discount (Hurdle) Rate @ Act/Projection Scenarios | D68: 0.15 | F68: =D68 -> 0.15 | G68: =F68*100 -> 15 | U68: Regional Launches
B69: ="Disc (Hurdle) Rate @ "&Comp&" Scenario (if different)" -> Disc (Hurdle) Rate @ Def Exit Scenario (if different) | D69: =D68 -> 0.15 | F69: =D69 -> 0.15 | V69: Expected Launch at
B70: Commercial Risk | D70: N/A | V70: Actual | X70: =Comp&" Commit" -> Def Exit Commit
B71: Technical Risk | D71: N/A | U71: US | V71: N/A | W71: N/A | X71: N/A | Y71: N/A
B72: Finance Rate (for MIRR calc) | D72: 0.08 | F72: =D72 -> 0.08 | U72: WEU | V72: N/A | W72: N/A | X72: N/A | Y72: N/A
B73: Reinvestment Rate (for MIRR calc) | D73: 0.125 | F73: =D73 -> 0.125 | U73: EMA | V73: N/A | W73: N/A | X73: N/A | Y73: N/A
B74: Growth Rate (for Terminal Value calc) | D74: 0.02 | F74: =D74 -> 0.02 | J74: BDX Referece Figures | U74: China | V74: N/A | W74: N/A | X74: N/A | Y74: N/A
B75: Working Capital Calculation: # of Days | J75: (FY16 Actuals) | U75: AP ex China | V75: N/A | W75: N/A | X75: N/A | Y75: N/A
B76: Receivables (DSO) | D76: 55 | J76: DSO | L76: =FT_PPD_DD!K103 -> 51.121086 | U76: LA | V76: N/A | W76: N/A | X76: N/A | Y76: N/A
B77: Payables (DPO) | D77: 55 | J77: DPO | L77: =FT_PPD_DD!L103 -> 44.655347 | U77: Canada | V77: N/A | W77: N/A | X77: N/A | Y77: N/A
B78: Inventories (DIO) | D78: 100 | J78: DIO | L78: =FT_PPD_DD!O103 -> 117.22235
B80: SMS + Technology Innovation
B81: SMS Name
B82: =FT_PPD_DD!P39 -> Quadrant | D82: =VLOOKUP($B$81,PPD_DD_2!$L$46:$W$103,7,0) -> #N/A | F82: =D82 -> #N/A
B83: =FT_PPD_DD!Q39 -> SMS FY17 Rev ($ M) | D83: =VLOOKUP($B$81,PPD_DD_2!$L$46:$W$103,8,0) -> #N/A | F83: =D83 -> #N/A
B84: =FT_PPD_DD!T39 -> FY17 Share | D84: =VLOOKUP($B$81,PPD_DD_2!$L$46:$W$103,11,0) -> #N/A | F84: =D84 -> #N/A
B85: =FT_PPD_DD!R39 -> Size Address. FY 17 WW Mkt ($ M) | D85: =VLOOKUP($B$81,PPD_DD_2!$L$46:$W$103,9,0) -> #N/A | F85: =D85 -> #N/A
B86: =FT_PPD_DD!S39 -> Address. FY17-FY22 WW Mkt gwth (%) | D86: =VLOOKUP($B$81,PPD_DD_2!$L$46:$W$103,10,0) -> #N/A | F86: =D86 -> #N/A
B87: =FT_PPD_DD!U39 -> FY22 Std Gross Margin (%) | D87: =VLOOKUP($B$81,PPD_DD_2!$L$46:$W$103,12,0) -> #N/A | F87: =D87 -> #N/A
B88: =FT_PPD_DD!B90 -> Technology Innovation Quadrant | D88: N/A | F88: =D88 -> N/A
B89: Standard Discount Rate (Hurdle Rate) | D89: =VLOOKUP(D82,PPD_DD_2!$V$106:$W$109,2,0)+VLOOKUP(D88,PPD_DD_2!$V$112:$W$115,2,0) -> #N/A | E89: =D89 -> #N/A
B91: Marketing Asusmptions
B92: # Years to Reach Target Conversion (after launch) | F92: =D92 -> 0
B93: Peak Category Share | F93: =D93 -> 0
B94: Product Life Cycle (Yrs after launch) | F94: =D94 -> 0
B96: Business Case Owners
B97: Name and Last Review Date (Calendar Year) | D97: Month | E97: Year
B98: Finance
B99: AA | D99: N/A | E99: N/A
B100: Marketing
B101: BB | D101: N/A | E101: N/A
B102: R&D
B103: CC | D103: N/A | E103: N/A
B104: Operations
B105: DD | D105: N/A | E105: N/A
B107: Attestation Statement:
B108: By signing this business case, I (R&D, Finance, Marketing, Operations owner) attest that: 1. This business case is a realistic portrayal of the expected financials (i.e. potential for overachievement = potential for underachievement). 2. I have: a. Reviewed/pressure tested all major assumptions, confirming that they are reasonable and balanced b. Confirmed that the financials reflect the most recent project status/information as of this date (no material differences) 3. We, the business case owners, have recently: a. Challenged ourselves / each other on the completeness and reasonableness of our individual inputs and this collective output b. Reviewed and aligned the assumptions and outputs with BU Leadership
AY233: Launch
I288: =IF($L$262=1,SUM(G247)/SUM(G246),IF($L$262=2,SUM(G247:H247)/SUM(G246:H246),IF($L$262=3,SUM(G247:I247)/SUM(G246:I246),IF($L$262=4,SUM(G247:J247)/SUM(G246:J246),IF($L$262=5,SUM(G247:K247)/SUM(G246:K246),IF($L$262=6,SUM(G247:L247)/SUM(G246:L246),IF($L$262=7,SUM(G247:M247)/SUM(G246:M246),IF($L$262=8,SUM(G247:N247)/SUM(G246:N246),IF($L$262=9,SUM(G247:O247)/SUM(G246:O246),IF($L$262=10,SUM(G247:P247)/SUM(G246:P246),IF($L$262=11,SUM(G247:Q247)/SUM(G246:Q246),IF($L$262=12,SUM(G247:R247)/SUM(G246:R246),IF($L$262=13,SUM(G245:S245)/SUM(G244:S244),IF($L$262=14,SUM(G245:T245)/SUM(G244:T244),IF($L$262=15,SUM(G245:U245)/SUM(G244:U244),IF($L$262=16,SUM(G245:V245)/SUM(G244:V244),IF($L$262=17,SUM(G245:W245)/SUM(G244:W244),0))))))))))))))))) -> 0
E611: Concept | H611: Low
E612: Definition | H612: Medium
E613: Development | H613: High
E614: Qualification
E615: Launch

Sheet Current_Prior
B2: Current vs. Prios Submission Comparison
B4: Please, paste values refereing to Prior Submission on light green highlighted cells (AP14 to BW 47)
B6: Current Submission | AP6: Prior Submission
AJ8: 10 Yrs | AM8: 15 Yrs
F9: Sunk | G9: =Calc!G125 -> FY18 | H9: =Calc!H125 -> FY19 | I9: =Calc!I125 -> FY20 | J9: =Calc!J125 -> FY21 | K9: =Calc!K125 -> FY22 | L9: =Calc!L125 -> FY23 | M9: =Calc!M125 -> FY24 | N9: =Calc!N125 -> FY25 | ... AI9: =Calc!AI125 -> FY46 | AJ9: =Calc!AJ9 -> FY18-27 | AK9: % Rev | AM9: =Calc!AM9 -> FY18-32 | AP9: Sunk | AQ9: =G9 -> FY18 | AR9: =H9 -> FY19 | AS9: =I9 -> FY20 | AT9: =J9 -> FY21 | AU9: =K9 -> FY22 | AV9: =L9 -> FY23 | AW9: =M9 -> FY24 | AX9: =N9 -> FY25 | ... BS9: =AI9 -> FY46 | BT9: FYAA-FYBB | BU9: % Rev | BW9: FYAA-FYBB
B11: Incremental Revenue | F11: =Calc!F127 -> 0 | G11: =Calc!G127 -> 0 | H11: =Calc!H127 -> 0 | I11: =Calc!I127 -> 0 | J11: =Calc!J127 -> 0 | K11: =Calc!K127 -> 0 | L11: =Calc!L127 -> 16667.204 | M11: =Calc!M127 -> 38568.729 | ... AJ11: =Calc!AJ127 -> 376419.95 | AM11: =Calc!AM127 -> 1323354.4
B12: Growth % | G12: =Calc!G128 -> 0 | H12: =Calc!H128 -> 0 | I12: =Calc!I128 -> 0 | J12: =Calc!J128 -> 0 | K12: =Calc!K128 -> 0 | L12: =Calc!L128 -> 0 | M12: =Calc!M128 -> 1.3140492 | N12: =Calc!N128 -> 0.90631038 | ... AJ12: =Calc!AJ128 -> 0.69427697 | AK12: 5 Yr CAGR
B13: Category Share | C13: =Calc!C129 -> Dollar ($) | G13: =Calc!G129 -> 0 | H13: =Calc!H129 -> 0 | I13: =Calc!I129 -> 0 | J13: =Calc!J129 -> 0 | K13: =Calc!K129 -> 0 | L13: =Calc!L129 -> 0 | M13: =Calc!M129 -> 0 | N13: =Calc!N129 -> 0 | ... AJ13: =Calc!AJ129 -> 0
B14: True Inc Rev (exc. Loss Avoid): PPD | G14: =Calc!G130 -> 0 | H14: =Calc!H130 -> 0 | I14: =Calc!I130 -> 0 | J14: =Calc!J130 -> 0 | K14: =Calc!K130 -> 0 | L14: =Calc!L130 -> 16667.204 | M14: =Calc!M130 -> 38568.729 | N14: =Calc!N130 -> 73523.969 | ... AJ14: =Calc!AJ130 -> 376419.95 | AM14: =Calc!AM130 -> 1323354.4
B15: Cost of Sales | F15: =Calc!F131 -> 0 | G15: =Calc!G131 -> 0 | H15: =Calc!H131 -> 0 | I15: =Calc!I131 -> 0 | J15: =Calc!J131 -> 0 | K15: =Calc!K131 -> 0 | L15: =Calc!L131 -> 4910.0681 | M15: =Calc!M131 -> 11698.893 | ... AK15: =Calc!AK131 -> 0.30506292 | AM15: =Calc!AM131 -> 413753.52
B16: Depreciation | F16: =Calc!F132 -> 0 | G16: =Calc!G132 -> 0 | H16: =Calc!H132 -> 0 | I16: =Calc!I132 -> 0 | J16: =Calc!J132 -> 0 | K16: =Calc!K132 -> 0 | L16: =Calc!L132 -> 0 | M16: =Calc!M132 -> 0 | ... AK16: =Calc!AK132 -> 0 | AM16: =Calc!AM132 -> 0
B17: Gross Profit | F17: =+F11-F15-F16 -> 0 | G17: =+G11-G15-G16 -> 0 | H17: =+H11-H15-H16 -> 0 | I17: =+I11-I15-I16 -> 0 | J17: =+J11-J15-J16 -> 0 | K17: =+K11-K15-K16 -> 0 | L17: =+L11-L15-L16 -> 11757.136 | M17: =+M11-M15-M16 -> 26869.837 | ... AI17: =+AI11-AI15-AI16 -> 0 | AJ17: =Calc!AJ133 -> 261588.18 | AM17: =Calc!AM133 -> 909600.9
C18: % of Revenue | G18: =IFERROR(IF(ABS(G17/G$11)>100%,0,G17/G$11),0) -> 0 | H18: =IFERROR(IF(ABS(H17/H$11)>100%,0,H17/H$11),0) -> 0 | I18: =IFERROR(IF(ABS(I17/I$11)>100%,0,I17/I$11),0) -> 0 | J18: =IFERROR(IF(ABS(J17/J$11)>100%,0,J17/J$11),0) -> 0 | K18: =IFERROR(IF(ABS(K17/K$11)>100%,0,K17/K$11),0) -> 0 | L18: =IFERROR(IF(ABS(L17/L$11)>100%,0,L17/L$11),0) -> 0.70540541 | M18: =IFERROR(IF(ABS(M17/M$11)>100%,0,M17/M$11),0) -> 0.69667415 | N18: =IFERROR(IF(ABS(N17/N$11)>100%,0,N17/N$11),0) -> 0.69576747 | ... AJ18: =IFERROR(IF(ABS(AJ17/AJ$11)>100%,0,AJ17/AJ$11),0) -> 0.69493708
B19: SSG&A | F19: =Calc!F135 -> 0 | G19: =Calc!G135 -> 200 | H19: =Calc!H135 -> 1000 | I19: =Calc!I135 -> 2500 | J19: =Calc!J135 -> 3500 | K19: =Calc!K135 -> 4500 | L19: =Calc!L135 -> 3300.0097 | M19: =Calc!M135 -> 3694.2371 | ... AK19: =Calc!AK135 -> 0.078304986 | AM19: =Calc!AM135 -> 52020.379
B20: R&D | F20: =Calc!F136 -> 0 | G20: =Calc!G136 -> 4828.4207 | H20: =Calc!H136 -> 3450.6323 | I20: =Calc!I136 -> 8338.5411 | J20: =Calc!J136 -> 7736.0277 | K20: =Calc!K136 -> 2362.6099 | L20: =Calc!L136 -> 1451.8026 | M20: =Calc!M136 -> 205.83869 | ... AK20: =Calc!AK136 -> 0.077085236 | AM20: =Calc!AM136 -> 29239.227
B21: OIBT | F21: =+F17-F19-F20 -> 0 | G21: =+G17-G19-G20 -> -5028.4207 | H21: =+H17-H19-H20 -> -4450.6323 | I21: =+I17-I19-I20 -> -10838.541 | J21: =+J17-J19-J20 -> -11236.028 | K21: =+K17-K19-K20 -> -6862.6099 | L21: =+L17-L19-L20 -> 7005.3234 | M21: =+M17-M19-M20 -> 22969.761 | ... AI21: =+AI17-AI19-AI20 -> 0 | AJ21: =Calc!AJ137 -> 203096.2 | AM21: =Calc!AM137 -> 828341.29
C22: % of Revenue | F22: =IFERROR(IF(ABS(F21/F$11)>100%,0,F21/F$11),0) -> 0 | G22: =IFERROR(IF(ABS(G21/G$11)>100%,0,G21/G$11),0) -> 0 | H22: =IFERROR(IF(ABS(H21/H$11)>100%,0,H21/H$11),0) -> 0 | I22: =IFERROR(IF(ABS(I21/I$11)>100%,0,I21/I$11),0) -> 0 | J22: =IFERROR(IF(ABS(J21/J$11)>100%,0,J21/J$11),0) -> 0 | K22: =IFERROR(IF(ABS(K21/K$11)>100%,0,K21/K$11),0) -> 0 | L22: =IFERROR(IF(ABS(L21/L$11)>100%,0,L21/L$11),0) -> 0.42030586 | M22: =IFERROR(IF(ABS(M21/M$11)>100%,0,M21/M$11),0) -> 0.595554 | ... AJ22: =IFERROR(IF(ABS(AJ21/AJ$11)>100%,0,AJ21/AJ$11),0) -> 0.53954685
B23: Other (Inc) / Exp | F23: =Calc!F139 -> 0 | G23: =Calc!G139 -> 0 | H23: =Calc!H139 -> 0 | I23: =Calc!I139 -> 0 | J23: =Calc!J139 -> 0 | K23: =Calc!K139 -> 0 | L23: =Calc!L139 -> 933.33333 | M23: =Calc!M139 -> 933.33333 | ... AJ23: =Calc!AJ139 -> 4666.6667 | AK23: Tax Rate | AM23: =Calc!AM139 -> 9333.3333
B24: Tax Exp / (Ben) | F24: =Calc!F140 -> 0 | G24: =Calc!G140 -> -1407.9578 | H24: =Calc!H140 -> -1246.1771 | I24: =Calc!I140 -> -3034.7915 | J24: =Calc!J140 -> -3146.0877 | K24: =Calc!K140 -> -1921.5308 | L24: =Calc!L140 -> 1700.1572 | M24: =Calc!M140 -> 6170.1998 | ... AK24: =Calc!AK140 -> 0.27356627 | AM24: =Calc!AM140 -> 229322.23
B25: Net Income | F25: =F21-F23-F24 -> 0 | G25: =G21-G23-G24 -> -3620.4629 | H25: =H21-H23-H24 -> -3204.4553 | I25: =I21-I23-I24 -> -7803.7496 | J25: =J21-J23-J24 -> -8089.9399 | K25: =K21-K23-K24 -> -4941.0791 | L25: =L21-L23-L24 -> 4371.8328 | M25: =M21-M23-M24 -> 15866.228 | ... AI25: =AI21-AI23-AI24 -> 0 | AJ25: =Calc!AJ141 -> 142869.26 | AM25: =Calc!AM141 -> 589685.73
C26: % of Revenue | G26: =IFERROR(IF(ABS(G25/G$11)>100%,0,G25/G$11),0) -> 0 | H26: =IFERROR(IF(ABS(H25/H$11)>100%,0,H25/H$11),0) -> 0 | I26: =IFERROR(IF(ABS(I25/I$11)>100%,0,I25/I$11),0) -> 0 | J26: =IFERROR(IF(ABS(J25/J$11)>100%,0,J25/J$11),0) -> 0 | K26: =IFERROR(IF(ABS(K25/K$11)>100%,0,K25/K$11),0) -> 0 | L26: =IFERROR(IF(ABS(L25/L$11)>100%,0,L25/L$11),0) -> 0.26230152 | M26: =IFERROR(IF(ABS(M25/M$11)>100%,0,M25/M$11),0) -> 0.41137544 | N26: =IFERROR(IF(ABS(N25/N$11)>100%,0,N25/N$11),0) -> 0.45721121 | ... AJ26: =IFERROR(IF(ABS(AJ25/AJ$11)>100%,0,AJ25/AJ$11),0) -> 0.37954753
B27: Capital | F27: =Calc!F143 -> 0 | G27: =Calc!G143 -> 0 | H27: =Calc!H143 -> 0 | I27: =Calc!I143 -> 0 | J27: =Calc!J143 -> 0 | K27: =Calc!K143 -> 0 | L27: =Calc!L143 -> 13066.667 | M27: =Calc!M143 -> -933.33333 | ... AK27: =Calc!AK143 -> 0.024795002 | AM27: =Calc!AM143 -> 4666.6667
B28: Increase in Working Capital | F28: =Calc!F144 -> 0 | G28: =Calc!G144 -> 0 | H28: =Calc!H144 -> 0 | I28: =Calc!I144 -> 0 | J28: =Calc!J144 -> 0 | K28: =Calc!K144 -> 0 | L28: =Calc!L144 -> 3160.1369 | M28: =Calc!M144 -> 4194.6695 | ... AK28: =Calc!AK144 -> 0.069754615 | AM28: =Calc!AM144 -> 45804.169
B29: Free Cash Flow | F29: =F25+F16-F27-F28 -> 0 | G29: =G25+G16-G27-G28 -> -3620.4629 | H29: =H25+H16-H27-H28 -> -3204.4553 | I29: =I25+I16-I27-I28 -> -7803.7496 | J29: =J25+J16-J27-J28 -> -8089.9399 | K29: =K25+K16-K27-K28 -> -4941.0791 | L29: =L25+L16-L27-L28 -> -11854.971 | M29: =M25+M16-M27-M28 -> 12604.892 | ... AI29: =AI25+AI16-AI27-AI28 -> 0 | AJ29: =Calc!AJ145 -> 107278.9 | AM29: =Calc!AM145 -> 539214.89
C30: % of Revenue | G30: =IFERROR(IF(ABS(G29/G$11)>100%,0,G29/G$11),0) -> 0 | H30: =IFERROR(IF(ABS(H29/H$11)>100%,0,H29/H$11),0) -> 0 | I30: =IFERROR(IF(ABS(I29/I$11)>100%,0,I29/I$11),0) -> 0 | J30: =IFERROR(IF(ABS(J29/J$11)>100%,0,J29/J$11),0) -> 0 | K30: =IFERROR(IF(ABS(K29/K$11)>100%,0,K29/K$11),0) -> 0 | L30: =IFERROR(IF(ABS(L29/L$11)>100%,0,L29/L$11),0) -> -0.71127532 | M30: =IFERROR(IF(ABS(M29/M$11)>100%,0,M29/M$11),0) -> 0.32681636 | N30: =IFERROR(IF(ABS(N29/N$11)>100%,0,N29/N$11),0) -> 0.37913141 | ... AJ30: =IFERROR(IF(ABS(AJ29/AJ$11)>100%,0,AJ29/AJ$11),0) -> 0.28499792
B31: ="Discounted FCF to Current FY (FY"&CurrentFY&")*" -> Discounted FCF to Current FY (FY18)* | G31: =Calc!G147 -> -3620.4629 | H31: =Calc!H147 -> -2786.4829 | I31: =Calc!I147 -> -5900.7558 | J31: =Calc!J147 -> -5319.2668 | K31: =Calc!K147 -> -2825.078 | L31: =Calc!L147 -> -5894.0156 | M31: =Calc!M147 -> 5449.4426 | N31: =Calc!N147 -> 10479.338 | ... AJ31: =Calc!AJ147 -> 21754.78 | AM31: =Calc!AM147 -> 101683.22
B32: * No Undepreciated Captital and/or Terminal Value Adjustment
BL33: Current FY (Prior Submission) | BO33: N/A | BP33: Fiscal Year | BQ33: =RIGHT(BO33,2)*1 -> #VALUE!
Q34: 10 Yrs | U34: 15 Yrs | BA34: 10 Yrs | BF34: 15 Yrs | BL34: Disc Rate (Prior Submission)
H35: Business Case Owners (Current) | Q35: =Comp&" Act/Proj" -> Def Exit Act/Proj | R35: Fwd Look | S35: Fwd Look ASR | U35: =Comp&" Act/Proj" -> Def Exit Act/Proj | V35: Fwd Look | W35: Fwd Look ASR | AR35: Business Case Owners (Prior Submission) | BA35: Proj Start | BB35: =Comp&" Commit" -> Def Exit Commit | BC35: =Comp&" Act/Proj" -> Def Exit Act/Proj | BD35: Fwd Look | BE35: Fwd Look ASR | BF35: Proj Start | BG35: =Comp&" Commit" -> Def Exit Commit | BH35: =Comp&" Act/Proj" -> Def Exit Act/Proj | BI35: Fwd Look | BJ35: Fwd Look ASR | BN35: Calendar Year
H36: Name and Last Review Date (Calendar Year) | Q36: ="FY "&DefExitFY&"-"&DefExitFY+9 -> #VALUE! | R36: ="FY "&CurrentFY&"-"&CurrentFY+9 -> FY 18-27 | S36: ="FY "&ASRFY&"-"&ASRFY+9 -> #VALUE! | U36: ="FY "&DefExitFY&"-"&DefExitFY+14 -> #VALUE! | V36: ="FY "&CurrentFY&"-"&CurrentFY+14 -> FY 18-32 | W36: ="FY "&ASRFY&"-"&ASRFY+14 -> #VALUE! | AA36: Date of Exit GPDS Phase (Calendar Year) | AR36: Name and Last Review Date (Calendar Based) | BC36: FY XX - ZZ | BD36: FY XX - ZZ | BE36: FY XX - ZZ | BH36: FY XX - ZZ | BI36: FY XX - ZZ | BJ36: FY XX - ZZ | BL36: Date of Exit GPDS Phase | BN36: Month | BO36: Year
H37: Finance | K37: (MM) | L37: (YY) | O37: MIRR | Q37: =Calc!H176 -> #VALUE! | R37: =Calc!I176 -> 0.20264461 | S37: =Calc!J176 -> NA | U37: =Calc!M176 -> #VALUE! | V37: =Calc!N176 -> 0.26443581 | W37: =Calc!O176 -> NA | AA37: Concept | AC37: =Input!D58 -> N/A | AD37: =Input!E58 -> N/A | AR37: Finance | AU37: (MM) | AV37: (YY) | AY37: MIRR | BL37: Concept | BN37: N/A | BO37: N/A
H38: =Input!B99 -> AA | K38: =Input!D99 -> N/A | L38: =Input!E99 -> N/A | O38: NPV | Q38: =Calc!H177 -> #VALUE! | R38: =Calc!I177 -> 21754.78 | S38: =Calc!J177 -> NA | U38: =Calc!M177 -> #VALUE! | V38: =Calc!N177 -> 101683.22 | W38: =Calc!O177 -> NA | AA38: Definition | AC38: =Input!D59 -> N/A | AD38: =Input!E59 -> N/A | AY38: NPV | BL38: Definition | BN38: N/A | BO38: N/A
H39: Marketing | AR39: Marketing | BN39: Def Exit (FY)
H40: =Input!B101 -> BB | K40: =Input!D101 -> N/A | L40: =Input!E101 -> N/A | O40: Metrics with TV | AA40: Development | AC40: =Input!D61 -> N/A | AD40: =Input!E61 -> N/A | AY40: Metrics with TV | BL40: Development | BN40: N/A | BO40: N/A
H41: R&D | O41: MIRR (with TV) | Q41: =Calc!H185 -> #VALUE! | R41: =Calc!I185 -> 0.39797793 | S41: =Calc!J185 -> NA | AA41: Qualification | AC41: =Input!D62 -> N/A | AD41: =Input!E62 -> N/A | AR41: R&D | AY41: MIRR (with TV) | BL41: Qualification | BN41: N/A | BO41: N/A
H42: =Input!B103 -> CC | K42: =Input!D103 -> N/A | L42: =Input!E103 -> N/A | O42: NPV (with TV) | Q42: =Calc!H186 -> #VALUE! | R42: =Calc!I186 -> 156812.43 | S42: =Calc!J186 -> NA | AA42: Launch | AC42: =Input!D63 -> N/A | AD42: =Input!E63 -> N/A | AY42: NPV (with TV) | BL42: Launch | BN42: N/A | BO42: N/A | BP42: =IF(OR(BN42="Oct",BN42="Nov",BN42="Dec"),BO42+1,BO42) -> N/A
H43: Operations | AR43: Operations | BA43: >> No need to populate
H44: =Input!B105 -> DD | K44: =Input!D105 -> N/A | L44: =Input!E105 -> N/A
B49: Return Metric Calculations SubTotals
B50: Current Submission | G50: =Calc!G231 -> 18 | H50: =Calc!H231 -> 19 | I50: =Calc!I231 -> 20 | J50: =Calc!J231 -> 21 | K50: =Calc!K231 -> 22 | L50: =Calc!L231 -> 23 | M50: =Calc!M231 -> 24 | N50: =Calc!N231 -> 25 | ... AI50: =Calc!AI231 -> 46 | AO50: Prior Submission | AQ50: =Calc!AQ231 -> 18 | AR50: =Calc!AR231 -> 19 | AS50: =Calc!AS231 -> 20 | AT50: =Calc!AT231 -> 21 | AU50: =Calc!AU231 -> 22 | AV50: =Calc!AV231 -> 23 | AW50: =Calc!AW231 -> 24 | AX50: =Calc!AX231 -> 25 | ... BS50: =Calc!BS231 -> 46
AO51: Data available at "Calc" tab, cells G233 to AI240
B52: Free Cash Flow (FCF) | G52: =Calc!G233 -> -3620.4629 | H52: =Calc!H233 -> -3204.4553 | I52: =Calc!I233 -> -7803.7496 | J52: =Calc!J233 -> -8089.9399 | K52: =Calc!K233 -> -4941.0791 | L52: =Calc!L233 -> -11854.971 | M52: =Calc!M233 -> 12604.892 | N52: =Calc!N233 -> 27875.246 | ... AI52: =Calc!AI233 -> 0
B53: R&D Exp (used for ROI calculation) | G53: =Calc!G234 -> 4828.4207 | H53: =Calc!H234 -> 3450.6323 | I53: =Calc!I234 -> 8338.5411 | J53: =Calc!J234 -> 7736.0277 | K53: =Calc!K234 -> 2362.6099 | L53: =Calc!L234 -> 1451.8026 | M53: =Calc!M234 -> 205.83869 | N53: =Calc!N234 -> 209.95546 | ... AI53: =Calc!AI234 -> 0
B54: R&D, SGA & Cap Exp (used for ROI calculation) | G54: =Calc!G235 -> 5028.4207 | H54: =Calc!H235 -> 4450.6323 | I54: =Calc!I235 -> 10838.541 | J54: =Calc!J235 -> 11236.028 | K54: =Calc!K235 -> 6862.6099 | L54: =Calc!L235 -> 17818.479 | M54: =Calc!M235 -> 2966.7425 | N54: =Calc!N235 -> 2600.0536 | ... AI54: =Calc!AI235 -> 0
B55: OIBT (used for ROI calculation) | G55: =Calc!G236 -> -5028.4207 | H55: =Calc!H236 -> -4450.6323 | I55: =Calc!I236 -> -10838.541 | J55: =Calc!J236 -> -11236.028 | K55: =Calc!K236 -> -6862.6099 | L55: =Calc!L236 -> 7005.3234 | M55: =Calc!M236 -> 22969.761 | N55: =Calc!N236 -> 47622.199 | ... AI55: =Calc!AI236 -> 0
B56: Undepreciated (Undp) Capital | G56: =Calc!G237 -> 0 | H56: =Calc!H237 -> 0 | I56: =Calc!I237 -> 0 | J56: =Calc!J237 -> 0 | K56: =Calc!K237 -> 0 | L56: =Calc!L237 -> 0 | M56: =Calc!M237 -> 0 | N56: =Calc!N237 -> 0 | ... AI56: =Calc!AI237 -> 0
B57: Free Cash Flow (FCF) + Undp Capital | G57: =Calc!G238 -> -3620.4629 | H57: =Calc!H238 -> -3204.4553 | I57: =Calc!I238 -> -7803.7496 | J57: =Calc!J238 -> -8089.9399 | K57: =Calc!K238 -> -4941.0791 | L57: =Calc!L238 -> -11854.971 | M57: =Calc!M238 -> 12604.892 | N57: =Calc!N238 -> 27875.246 | ... AI57: =Calc!AI238 -> 0
B58: Terminal Value | G58: =Calc!G239 -> -28406.709 | H58: =Calc!H239 -> -25142.649 | I58: =Calc!I239 -> -61229.42 | J58: =Calc!J239 -> -63474.913 | K58: =Calc!K239 -> -38768.467 | L58: =Calc!L239 -> -93015.924 | M58: =Calc!M239 -> 98899.921 | N58: =Calc!N239 -> 218713.47 | ... AI58: =Calc!AI239 -> 0
B59: Free Cash Flow (FCF) + Undp Capital + TV | G59: =Calc!G240 -> -32027.172 | H59: =Calc!H240 -> -28347.104 | I59: =Calc!I240 -> -69033.169 | J59: =Calc!J240 -> -71564.853 | K59: =Calc!K240 -> -43709.546 | L59: =Calc!L240 -> -104870.89 | M59: =Calc!M240 -> 111504.81 | N59: =Calc!N240 -> 246588.72 | ... AI59: =Calc!AI240 -> 0
B63: NPV Change Drivers: To be used on ASR Collection (May timeframe)
B65: Discounted FCFs (Present Value at Current FY) | G65: Loss: (neg) | H65: Gain: pos | AQ65: Discounted FCFs (Present Value to Current FY)
G66: =G50 -> 18 | H66: =H50 -> 19 | I66: =I50 -> 20 | J66: =J50 -> 21 | K66: =K50 -> 22 | L66: =L50 -> 23 | M66: =M50 -> 24 | N66: =N50 -> 25 | ... AI66: =AI50 -> 46 | AJ66: ="FY"&CurrentFY&"-"&CurrentFY+9 -> FY18-27 | AQ66: =AQ50 -> 18 | AR66: =AR50 -> 19 | AS66: =AS50 -> 20 | AT66: =AT50 -> 21 | AU66: =AU50 -> 22 | AV66: =AV50 -> 23 | AW66: =AW50 -> 24 | AX66: =AX50 -> 25 | ... BS66: =BS50 -> 46 | BT66: ="FY"&CurrentFY&"-"&CurrentFY+14 -> FY18-32
B67: SSG&A | G67: =-IF(AND(G79=1,G80=1),(G87/(1+DiscR)^G$82)-(G88/(1+DiscR)^G$82),0) -> #VALUE! | H67: =-IF(AND(H79=1,H80=1),(H87/(1+DiscR)^H$82)-(H88/(1+DiscR)^H$82),0) -> #VALUE! | I67: =-IF(AND(I79=1,I80=1),(I87/(1+DiscR)^I$82)-(I88/(1+DiscR)^I$82),0) -> #VALUE! | J67: =-IF(AND(J79=1,J80=1),(J87/(1+DiscR)^J$82)-(J88/(1+DiscR)^J$82),0) -> #VALUE! | K67: =-IF(AND(K79=1,K80=1),(K87/(1+DiscR)^K$82)-(K88/(1+DiscR)^K$82),0) -> #VALUE! | L67: =-IF(AND(L79=1,L80=1),(L87/(1+DiscR)^L$82)-(L88/(1+DiscR)^L$82),0) -> #VALUE! | M67: =-IF(AND(M79=1,M80=1),(M87/(1+DiscR)^M$82)-(M88/(1+DiscR)^M$82),0) -> #VALUE! | N67: =-IF(AND(N79=1,N80=1),(N87/(1+DiscR)^N$82)-(N88/(1+DiscR)^N$82),0) -> #VALUE! | ... AI67: =-IF(AND(AI79=1,AI80=1),(AI87/(1+DiscR)^AI$82)-(AI88/(1+DiscR)^AI$82),0) -> #VALUE! | AJ67: =SUMIF($G$81:$AI$81,TRUE,G67:AI67) -> 0 | AQ67: =-IF(AND(G79=1,G80=1),(G87/(1+DiscR)^G$82)-(G88/(1+DiscR)^G$82),0) -> #VALUE! | AR67: =-IF(AND(H79=1,H80=1),(H87/(1+DiscR)^H$82)-(H88/(1+DiscR)^H$82),0) -> #VALUE! | AS67: =-IF(AND(I79=1,I80=1),(I87/(1+DiscR)^I$82)-(I88/(1+DiscR)^I$82),0) -> #VALUE! | AT67: =-IF(AND(J79=1,J80=1),(J87/(1+DiscR)^J$82)-(J88/(1+DiscR)^J$82),0) -> #VALUE! | AU67: =-IF(AND(K79=1,K80=1),(K87/(1+DiscR)^K$82)-(K88/(1+DiscR)^K$82),0) -> #VALUE! | AV67: =-IF(AND(L79=1,L80=1),(L87/(1+DiscR)^L$82)-(L88/(1+DiscR)^L$82),0) -> #VALUE! | AW67: =-IF(AND(M79=1,M80=1),(M87/(1+DiscR)^M$82)-(M88/(1+DiscR)^M$82),0) -> #VALUE! | AX67: =-IF(AND(N79=1,N80=1),(N87/(1+DiscR)^N$82)-(N88/(1+DiscR)^N$82),0) -> #VALUE! | ... BS67: =-IF(AND(AI79=1,AI80=1),(AI87/(1+DiscR)^AI$82)-(AI88/(1+DiscR)^AI$82),0) -> #VALUE! | BT67: =SUMIF($AQ$81:$BS$81,TRUE,AQ67:BS67) -> 0
B68: R&D | G68: =-IF(AND(G79=1,G80=1),(G89/(1+DiscR)^G$82)-(G90/(1+DiscR)^G$82),0) -> #VALUE! | H68: =-IF(AND(H79=1,H80=1),(H89/(1+DiscR)^H$82)-(H90/(1+DiscR)^H$82),0) -> #VALUE! | I68: =-IF(AND(I79=1,I80=1),(I89/(1+DiscR)^I$82)-(I90/(1+DiscR)^I$82),0) -> #VALUE! | J68: =-IF(AND(J79=1,J80=1),(J89/(1+DiscR)^J$82)-(J90/(1+DiscR)^J$82),0) -> #VALUE! | K68: =-IF(AND(K79=1,K80=1),(K89/(1+DiscR)^K$82)-(K90/(1+DiscR)^K$82),0) -> #VALUE! | L68: =-IF(AND(L79=1,L80=1),(L89/(1+DiscR)^L$82)-(L90/(1+DiscR)^L$82),0) -> #VALUE! | M68: =-IF(AND(M79=1,M80=1),(M89/(1+DiscR)^M$82)-(M90/(1+DiscR)^M$82),0) -> #VALUE! | N68: =-IF(AND(N79=1,N80=1),(N89/(1+DiscR)^N$82)-(N90/(1+DiscR)^N$82),0) -> #VALUE! | ... AI68: =-IF(AND(AI79=1,AI80=1),(AI89/(1+DiscR)^AI$82)-(AI90/(1+DiscR)^AI$82),0) -> #VALUE! | AJ68: =SUMIF($G$81:$AI$81,TRUE,G68:AI68) -> 0 | AQ68: =-IF(AND(G79=1,G80=1),(G89/(1+DiscR)^G$82)-(G90/(1+DiscR)^G$82),0) -> #VALUE! | AR68: =-IF(AND(H79=1,H80=1),(H89/(1+DiscR)^H$82)-(H90/(1+DiscR)^H$82),0) -> #VALUE! | AS68: =-IF(AND(I79=1,I80=1),(I89/(1+DiscR)^I$82)-(I90/(1+DiscR)^I$82),0) -> #VALUE! | AT68: =-IF(AND(J79=1,J80=1),(J89/(1+DiscR)^J$82)-(J90/(1+DiscR)^J$82),0) -> #VALUE! | AU68: =-IF(AND(K79=1,K80=1),(K89/(1+DiscR)^K$82)-(K90/(1+DiscR)^K$82),0) -> #VALUE! | AV68: =-IF(AND(L79=1,L80=1),(L89/(1+DiscR)^L$82)-(L90/(1+DiscR)^L$82),0) -> #VALUE! | AW68: =-IF(AND(M79=1,M80=1),(M89/(1+DiscR)^M$82)-(M90/(1+DiscR)^M$82),0) -> #VALUE! | AX68: =-IF(AND(N79=1,N80=1),(N89/(1+DiscR)^N$82)-(N90/(1+DiscR)^N$82),0) -> #VALUE! | ... BS68: =-IF(AND(AI79=1,AI80=1),(AI89/(1+DiscR)^AI$82)-(AI90/(1+DiscR)^AI$82),0) -> #VALUE! | BT68: =SUMIF($AQ$81:$BS$81,TRUE,AQ68:BS68) -> 0
B69: Capital | G69: =-IF(AND(G79=1,G80=1),(G91/(1+DiscR)^G$82)-(G92/(1+DiscR)^G$82),0) -> #VALUE! | H69: =-IF(AND(H79=1,H80=1),(H91/(1+DiscR)^H$82)-(H92/(1+DiscR)^H$82),0) -> #VALUE! | I69: =-IF(AND(I79=1,I80=1),(I91/(1+DiscR)^I$82)-(I92/(1+DiscR)^I$82),0) -> #VALUE! | J69: =-IF(AND(J79=1,J80=1),(J91/(1+DiscR)^J$82)-(J92/(1+DiscR)^J$82),0) -> #VALUE! | K69: =-IF(AND(K79=1,K80=1),(K91/(1+DiscR)^K$82)-(K92/(1+DiscR)^K$82),0) -> #VALUE! | L69: =-IF(AND(L79=1,L80=1),(L91/(1+DiscR)^L$82)-(L92/(1+DiscR)^L$82),0) -> #VALUE! | M69: =-IF(AND(M79=1,M80=1),(M91/(1+DiscR)^M$82)-(M92/(1+DiscR)^M$82),0) -> #VALUE! | N69: =-IF(AND(N79=1,N80=1),(N91/(1+DiscR)^N$82)-(N92/(1+DiscR)^N$82),0) -> #VALUE! | ... AI69: =-IF(AND(AI79=1,AI80=1),(AI91/(1+DiscR)^AI$82)-(AI92/(1+DiscR)^AI$82),0) -> #VALUE! | AJ69: =SUMIF($G$81:$AI$81,TRUE,G69:AI69) -> 0 | AQ69: =-IF(AND(G79=1,G80=1),(G91/(1+DiscR)^G$82)-(G92/(1+DiscR)^G$82),0) -> #VALUE! | AR69: =-IF(AND(H79=1,H80=1),(H91/(1+DiscR)^H$82)-(H92/(1+DiscR)^H$82),0) -> #VALUE! | AS69: =-IF(AND(I79=1,I80=1),(I91/(1+DiscR)^I$82)-(I92/(1+DiscR)^I$82),0) -> #VALUE! | AT69: =-IF(AND(J79=1,J80=1),(J91/(1+DiscR)^J$82)-(J92/(1+DiscR)^J$82),0) -> #VALUE! | AU69: =-IF(AND(K79=1,K80=1),(K91/(1+DiscR)^K$82)-(K92/(1+DiscR)^K$82),0) -> #VALUE! | AV69: =-IF(AND(L79=1,L80=1),(L91/(1+DiscR)^L$82)-(L92/(1+DiscR)^L$82),0) -> #VALUE! | AW69: =-IF(AND(M79=1,M80=1),(M91/(1+DiscR)^M$82)-(M92/(1+DiscR)^M$82),0) -> #VALUE! | AX69: =-IF(AND(N79=1,N80=1),(N91/(1+DiscR)^N$82)-(N92/(1+DiscR)^N$82),0) -> #VALUE! | ... BS69: =-IF(AND(AI79=1,AI80=1),(AI91/(1+DiscR)^AI$82)-(AI92/(1+DiscR)^AI$82),0) -> #VALUE! | BT69: =SUMIF($AQ$81:$BS$81,TRUE,AQ69:BS69) -> 0
B70: Investment Launch+2Yrs (SSG&A+R&D+Capital) | G70: =SUM(G67:G69) -> #VALUE! | H70: =SUM(H67:H69) -> #VALUE! | I70: =SUM(I67:I69) -> #VALUE! | J70: =SUM(J67:J69) -> #VALUE! | K70: =SUM(K67:K69) -> #VALUE! | L70: =SUM(L67:L69) -> #VALUE! | M70: =SUM(M67:M69) -> #VALUE! | N70: =SUM(N67:N69) -> #VALUE! | ... AI70: =SUM(AI67:AI69) -> #VALUE! | AJ70: =SUMIF($G$81:$AI$81,TRUE,G70:AI70) -> 0 | AQ70: =SUM(AQ67:AQ69) -> #VALUE! | AR70: =SUM(AR67:AR69) -> #VALUE! | AS70: =SUM(AS67:AS69) -> #VALUE! | AT70: =SUM(AT67:AT69) -> #VALUE! | AU70: =SUM(AU67:AU69) -> #VALUE! | AV70: =SUM(AV67:AV69) -> #VALUE! | AW70: =SUM(AW67:AW69) -> #VALUE! | AX70: =SUM(AX67:AX69) -> #VALUE! | ... BS70: =SUM(BS67:BS69) -> #VALUE! | BT70: =SUMIF($AQ$81:$BS$81,TRUE,AQ70:BS70) -> 0
B71: Launch Delay | G71: =IF($P$96="Delay",G107-G106,G116-G115) -> #VALUE! | H71: =IF($P$96="Delay",H107-H106,H116-H115) -> #VALUE! | I71: =IF($P$96="Delay",I107-I106,I116-I115) -> #VALUE! | J71: =IF($P$96="Delay",J107-J106,J116-J115) -> #VALUE! | K71: =IF($P$96="Delay",K107-K106,K116-K115) -> #VALUE! | L71: =IF($P$96="Delay",L107-L106,L116-L115) -> #VALUE! | M71: =IF($P$96="Delay",M107-M106,M116-M115) -> #VALUE! | N71: =IF($P$96="Delay",N107-N106,N116-N115) -> #VALUE! | ... AI71: =IF($P$96="Delay",AI107-AI106,AI116-AI115) -> #VALUE! | AJ71: =SUMIF($G$81:$AI$81,TRUE,G71:AI71) -> 0 | AQ71: =IF($AZ$96="Delay",AQ107-AQ106,AQ116-AQ115) -> #VALUE! | AR71: =IF($AZ$96="Delay",AR107-AR106,AR116-AR115) -> #VALUE! | AS71: =IF($AZ$96="Delay",AS107-AS106,AS116-AS115) -> #VALUE! | AT71: =IF($AZ$96="Delay",AT107-AT106,AT116-AT115) -> #VALUE! | AU71: =IF($AZ$96="Delay",AU107-AU106,AU116-AU115) -> #VALUE! | AV71: =IF($AZ$96="Delay",AV107-AV106,AV116-AV115) -> #VALUE! | AW71: =IF($AZ$96="Delay",AW107-AW106,AW116-AW115) -> #VALUE! | AX71: =IF($AZ$96="Delay",AX107-AX106,AX116-AX115) -> #VALUE! | ... BS71: =IF($AZ$96="Delay",BS107-BS106,BS116-BS115) -> #VALUE! | BT71: =SUMIF($AQ$81:$BS$81,TRUE,AQ71:BS71) -> 0
B72: Revenue Change | G72: =(G121/(1+DiscR)^G$82)-(G122/(1+DiscR)^G$82)-G71 -> #VALUE! | H72: =(H121/(1+DiscR)^H$82)-(H122/(1+DiscR)^H$82)-H71 -> #VALUE! | I72: =(I121/(1+DiscR)^I$82)-(I122/(1+DiscR)^I$82)-I71 -> #VALUE! | J72: =(J121/(1+DiscR)^J$82)-(J122/(1+DiscR)^J$82)-J71 -> #VALUE! | K72: =(K121/(1+DiscR)^K$82)-(K122/(1+DiscR)^K$82)-K71 -> #VALUE! | L72: =(L121/(1+DiscR)^L$82)-(L122/(1+DiscR)^L$82)-L71 -> #VALUE! | M72: =(M121/(1+DiscR)^M$82)-(M122/(1+DiscR)^M$82)-M71 -> #VALUE! | N72: =(N121/(1+DiscR)^N$82)-(N122/(1+DiscR)^N$82)-N71 -> #VALUE! | ... AI72: =(AI121/(1+DiscR)^AI$82)-(AI122/(1+DiscR)^AI$82)-AI71 -> #VALUE! | AJ72: =SUMIF($G$81:$AI$81,TRUE,G72:AI72) -> 0 | AQ72: =(AQ121/(1+DiscR)^AQ$82)-(AQ122/(1+DiscR)^AQ$82)-AQ71 -> #VALUE! | AR72: =(AR121/(1+DiscR)^AR$82)-(AR122/(1+DiscR)^AR$82)-AR71 -> #VALUE! | AS72: =(AS121/(1+DiscR)^AS$82)-(AS122/(1+DiscR)^AS$82)-AS71 -> #VALUE! | AT72: =(AT121/(1+DiscR)^AT$82)-(AT122/(1+DiscR)^AT$82)-AT71 -> #VALUE! | AU72: =(AU121/(1+DiscR)^AU$82)-(AU122/(1+DiscR)^AU$82)-AU71 -> #VALUE! | AV72: =(AV121/(1+DiscR)^AV$82)-(AV122/(1+DiscR)^AV$82)-AV71 -> #VALUE! | AW72: =(AW121/(1+DiscR)^AW$82)-(AW122/(1+DiscR)^AW$82)-AW71 -> #VALUE! | AX72: =(AX121/(1+DiscR)^AX$82)-(AX122/(1+DiscR)^AX$82)-AX71 -> #VALUE! | ... BS72: =(BS121/(1+DiscR)^BS$82)-(BS122/(1+DiscR)^BS$82)-BS71 -> #VALUE! | BT72: =SUMIF($AQ$81:$BS$81,TRUE,AQ72:BS72) -> 0
B73: Std Cost Change | G73: =(G125/(1+DiscR)^G$82)-(G126/(1+DiscR)^G$82) -> #VALUE! | H73: =(H125/(1+DiscR)^H$82)-(H126/(1+DiscR)^H$82) -> #VALUE! | I73: =(I125/(1+DiscR)^I$82)-(I126/(1+DiscR)^I$82) -> #VALUE! | J73: =(J125/(1+DiscR)^J$82)-(J126/(1+DiscR)^J$82) -> #VALUE! | K73: =(K125/(1+DiscR)^K$82)-(K126/(1+DiscR)^K$82) -> #VALUE! | L73: =(L125/(1+DiscR)^L$82)-(L126/(1+DiscR)^L$82) -> #VALUE! | M73: =(M125/(1+DiscR)^M$82)-(M126/(1+DiscR)^M$82) -> #VALUE! | N73: =(N125/(1+DiscR)^N$82)-(N126/(1+DiscR)^N$82) -> #VALUE! | ... AI73: =(AI125/(1+DiscR)^AI$82)-(AI126/(1+DiscR)^AI$82) -> #VALUE! | AJ73: =SUMIF($G$81:$AI$81,TRUE,G73:AI73) -> 0 | AQ73: =(AQ125/(1+DiscR)^AQ$82)-(AQ126/(1+DiscR)^AQ$82) -> #VALUE! | AR73: =(AR125/(1+DiscR)^AR$82)-(AR126/(1+DiscR)^AR$82) -> #VALUE! | AS73: =(AS125/(1+DiscR)^AS$82)-(AS126/(1+DiscR)^AS$82) -> #VALUE! | AT73: =(AT125/(1+DiscR)^AT$82)-(AT126/(1+DiscR)^AT$82) -> #VALUE! | AU73: =(AU125/(1+DiscR)^AU$82)-(AU126/(1+DiscR)^AU$82) -> #VALUE! | AV73: =(AV125/(1+DiscR)^AV$82)-(AV126/(1+DiscR)^AV$82) -> #VALUE! | AW73: =(AW125/(1+DiscR)^AW$82)-(AW126/(1+DiscR)^AW$82) -> #VALUE! | AX73: =(AX125/(1+DiscR)^AX$82)-(AX126/(1+DiscR)^AX$82) -> #VALUE! | ... BS73: =(BS125/(1+DiscR)^BS$82)-(BS126/(1+DiscR)^BS$82) -> #VALUE! | BT73: =SUMIF($AQ$81:$BS$81,TRUE,AQ73:BS73) -> 0
B74: Hurdle Rate Change | AJ74: =AJ77-AJ76 -> -85524.123 | BT74: =BT77-BT76 -> -437531.67
B75: Other | AJ75: =(R38-BD38)-(SUM(AJ70:AJ73)+AJ74) -> 107278.9 | BT75: =(V38-BI38)-(SUM(BT70:BT73)+BT74) -> 539214.89
B76: Fwd Look at Previous Disc Rate | AJ76: =VLOOKUP(CurrentFY,$AK$83:$AM$95,2,0) -> 107278.9 | BT76: =VLOOKUP(CurrentFY,$AK$83:$AM$95,3,0) -> 539214.89
AJ77: =VLOOKUP(CurrentFY,Calc!$N$196:$P$208,2,0) -> 21754.78 | BT77: =VLOOKUP(CurrentFY,Calc!$N$196:$P$208,3,0) -> 101683.22
B78: Counters and Markers | AQ78: Counters and Markers
B79: Investment +2 (2 Yr Marker) | G79: =IF(LaunchFY="NA",2,IF((LaunchFY+3)>G66,1,0)) -> #VALUE! | H79: =IF(LaunchFY="NA",2,IF((LaunchFY+3)>H66,1,0)) -> #VALUE! | I79: =IF(LaunchFY="NA",2,IF((LaunchFY+3)>I66,1,0)) -> #VALUE! | J79: =IF(LaunchFY="NA",2,IF((LaunchFY+3)>J66,1,0)) -> #VALUE! | K79: =IF(LaunchFY="NA",2,IF((LaunchFY+3)>K66,1,0)) -> #VALUE! | L79: =IF(LaunchFY="NA",2,IF((LaunchFY+3)>L66,1,0)) -> #VALUE! | M79: =IF(LaunchFY="NA",2,IF((LaunchFY+3)>M66,1,0)) -> #VALUE! | N79: =IF(LaunchFY="NA",2,IF((LaunchFY+3)>N66,1,0)) -> #VALUE! | ... AI79: =IF(LaunchFY="NA",2,IF((LaunchFY+3)>AI66,1,0)) -> #VALUE!
B80: Current Year (Prior Sub) Start Marker | G80: =IF(CurrentFYPriorSub="NA",2,IF(Calc!G288>=CurrentFYPriorSub,1,0)) -> #VALUE! | H80: =IF(CurrentFYPriorSub="NA",2,IF(Calc!H288>=CurrentFYPriorSub,1,0)) -> #VALUE! | I80: =IF(CurrentFYPriorSub="NA",2,IF(Calc!I288>=CurrentFYPriorSub,1,0)) -> #VALUE! | J80: =IF(CurrentFYPriorSub="NA",2,IF(Calc!J288>=CurrentFYPriorSub,1,0)) -> #VALUE! | K80: =IF(CurrentFYPriorSub="NA",2,IF(Calc!K288>=CurrentFYPriorSub,1,0)) -> #VALUE! | L80: =IF(CurrentFYPriorSub="NA",2,IF(Calc!L288>=CurrentFYPriorSub,1,0)) -> #VALUE! | M80: =IF(CurrentFYPriorSub="NA",2,IF(Calc!M288>=CurrentFYPriorSub,1,0)) -> #VALUE! | N80: =IF(CurrentFYPriorSub="NA",2,IF(Calc!N288>=CurrentFYPriorSub,1,0)) -> #VALUE! | ... AI80: =IF(CurrentFYPriorSub="NA",2,IF(Calc!AI288>=CurrentFYPriorSub,1,0)) -> #VALUE! | AK80: @ Prior Disc Rate
B81: 10 Yrs Marker | G81: =AND(G66>=CurrentFYPriorSub,G66<=CurrentFYPriorSub+9) -> #VALUE! | H81: =AND(H66>=CurrentFYPriorSub,H66<=CurrentFYPriorSub+9) -> #VALUE! | I81: =AND(I66>=CurrentFYPriorSub,I66<=CurrentFYPriorSub+9) -> #VALUE! | J81: =AND(J66>=CurrentFYPriorSub,J66<=CurrentFYPriorSub+9) -> #VALUE! | K81: =AND(K66>=CurrentFYPriorSub,K66<=CurrentFYPriorSub+9) -> #VALUE! | L81: =AND(L66>=CurrentFYPriorSub,L66<=CurrentFYPriorSub+9) -> #VALUE! | M81: =AND(M66>=CurrentFYPriorSub,M66<=CurrentFYPriorSub+9) -> #VALUE! | N81: =AND(N66>=CurrentFYPriorSub,N66<=CurrentFYPriorSub+9) -> #VALUE! | ... AI81: =AND(AI66>=CurrentFYPriorSub,AI66<=CurrentFYPriorSub+9) -> #VALUE! | AK81: NPV + Undp Capital | AO81: 15 Yrs Marker | AQ81: =AND(AQ66>=CurrentFYPriorSub,AQ66<=CurrentFYPriorSub+14) -> #VALUE! | AR81: =AND(AR66>=CurrentFYPriorSub,AR66<=CurrentFYPriorSub+14) -> #VALUE! | AS81: =AND(AS66>=CurrentFYPriorSub,AS66<=CurrentFYPriorSub+14) -> #VALUE! | AT81: =AND(AT66>=CurrentFYPriorSub,AT66<=CurrentFYPriorSub+14) -> #VALUE! | AU81: =AND(AU66>=CurrentFYPriorSub,AU66<=CurrentFYPriorSub+14) -> #VALUE! | AV81: =AND(AV66>=CurrentFYPriorSub,AV66<=CurrentFYPriorSub+14) -> #VALUE! | AW81: =AND(AW66>=CurrentFYPriorSub,AW66<=CurrentFYPriorSub+14) -> #VALUE! | AX81: =AND(AX66>=CurrentFYPriorSub,AX66<=CurrentFYPriorSub+14) -> #VALUE! | ... BS81: =AND(BS66>=CurrentFYPriorSub,BS66<=CurrentFYPriorSub+14) -> #VALUE!
B82: Year counter | G82: =IF(G66=CurrentFYPriorSub,0,IF(G66>CurrentFYPriorSub,F82+1,)) -> #VALUE! | H82: =IF(H66=CurrentFYPriorSub,0,IF(H66>CurrentFYPriorSub,G82+1,)) -> #VALUE! | I82: =IF(I66=CurrentFYPriorSub,0,IF(I66>CurrentFYPriorSub,H82+1,)) -> #VALUE! | J82: =IF(J66=CurrentFYPriorSub,0,IF(J66>CurrentFYPriorSub,I82+1,)) -> #VALUE! | K82: =IF(K66=CurrentFYPriorSub,0,IF(K66>CurrentFYPriorSub,J82+1,)) -> #VALUE! | L82: =IF(L66=CurrentFYPriorSub,0,IF(L66>CurrentFYPriorSub,K82+1,)) -> #VALUE! | M82: =IF(M66=CurrentFYPriorSub,0,IF(M66>CurrentFYPriorSub,L82+1,)) -> #VALUE! | N82: =IF(N66=CurrentFYPriorSub,0,IF(N66>CurrentFYPriorSub,M82+1,)) -> #VALUE! | ... AI82: =IF(AI66=CurrentFYPriorSub,0,IF(AI66>CurrentFYPriorSub,AH82+1,)) -> #VALUE! | AK82: FY \ Window | AL82: 10 | AM82: 15 | AQ82: =IF(AQ66=CurrentFYPriorSub,0,IF(AQ66>CurrentFYPriorSub,AP82+1,)) -> #VALUE! | AR82: =IF(AR66=CurrentFYPriorSub,0,IF(AR66>CurrentFYPriorSub,AQ82+1,)) -> #VALUE! | AS82: =IF(AS66=CurrentFYPriorSub,0,IF(AS66>CurrentFYPriorSub,AR82+1,)) -> #VALUE! | AT82: =IF(AT66=CurrentFYPriorSub,0,IF(AT66>CurrentFYPriorSub,AS82+1,)) -> #VALUE! | AU82: =IF(AU66=CurrentFYPriorSub,0,IF(AU66>CurrentFYPriorSub,AT82+1,)) -> #VALUE! | AV82: =IF(AV66=CurrentFYPriorSub,0,IF(AV66>CurrentFYPriorSub,AU82+1,)) -> #VALUE! | AW82: =IF(AW66=CurrentFYPriorSub,0,IF(AW66>CurrentFYPriorSub,AV82+1,)) -> #VALUE! | AX82: =IF(AX66=CurrentFYPriorSub,0,IF(AX66>CurrentFYPriorSub,AW82+1,)) -> #VALUE! | ... BS82: =IF(BS66=CurrentFYPriorSub,0,IF(BS66>CurrentFYPriorSub,BR82+1,)) -> #VALUE!
B83: Current Year (Prior Sub) Time Horizon Marker (10yrs) | G83: =IF(AND(G66>=CurrentFYPriorSub,G66<=CurrentFYPriorSub+9),1,0) -> #VALUE! | H83: =IF(AND(H66>=CurrentFYPriorSub,H66<=CurrentFYPriorSub+9),1,0) -> #VALUE! | I83: =IF(AND(I66>=CurrentFYPriorSub,I66<=CurrentFYPriorSub+9),1,0) -> #VALUE! | J83: =IF(AND(J66>=CurrentFYPriorSub,J66<=CurrentFYPriorSub+9),1,0) -> #VALUE! | K83: =IF(AND(K66>=CurrentFYPriorSub,K66<=CurrentFYPriorSub+9),1,0) -> #VALUE! | L83: =IF(AND(L66>=CurrentFYPriorSub,L66<=CurrentFYPriorSub+9),1,0) -> #VALUE! | M83: =IF(AND(M66>=CurrentFYPriorSub,M66<=CurrentFYPriorSub+9),1,0) -> #VALUE! | N83: =IF(AND(N66>=CurrentFYPriorSub,N66<=CurrentFYPriorSub+9),1,0) -> #VALUE! | ... AI83: =IF(AND(AI66>=CurrentFYPriorSub,AI66<=CurrentFYPriorSub+9),1,0) -> #VALUE! | AK83: =Calc!$G$113 -> 18 | AL83: =IF($AK83=Calc!$G$113,Calc!G233+NPV(DiscRPriorSub,(Calc!H233:O233,Calc!P238)),0) -> 107278.9 | AM83: =IF($AK83=Calc!$G$113,Calc!G233+NPV(DiscRPriorSub,(Calc!H233:T233,Calc!U238)),0) -> 539214.89 | AO83: Current FY (Prior Sub) Time Horizon Marker (15yrs) | AQ83: =IF(AND(G66>=CurrentFYPriorSub,G66<=CurrentFYPriorSub+14),1,0) -> #VALUE! | AR83: =IF(AND(H66>=CurrentFYPriorSub,H66<=CurrentFYPriorSub+14),1,0) -> #VALUE! | AS83: =IF(AND(I66>=CurrentFYPriorSub,I66<=CurrentFYPriorSub+14),1,0) -> #VALUE! | AT83: =IF(AND(J66>=CurrentFYPriorSub,J66<=CurrentFYPriorSub+14),1,0) -> #VALUE! | AU83: =IF(AND(K66>=CurrentFYPriorSub,K66<=CurrentFYPriorSub+14),1,0) -> #VALUE! | AV83: =IF(AND(L66>=CurrentFYPriorSub,L66<=CurrentFYPriorSub+14),1,0) -> #VALUE! | AW83: =IF(AND(M66>=CurrentFYPriorSub,M66<=CurrentFYPriorSub+14),1,0) -> #VALUE! | AX83: =IF(AND(N66>=CurrentFYPriorSub,N66<=CurrentFYPriorSub+14),1,0) -> #VALUE! | ... BS83: =IF(AND(AI66>=CurrentFYPriorSub,AI66<=CurrentFYPriorSub+14),1,0) -> #VALUE!
AK84: =AK83+1 -> 19 | AL84: =IF($AK84=Calc!$H$113,Calc!H233+NPV(DiscRPriorSub,(Calc!I233:P233,Calc!Q238)),0) -> 181080.9 | AM84: =IF($AK84=Calc!$H$113,Calc!H233+NPV(DiscRPriorSub,(Calc!I233:U233,Calc!V238)),0) -> 664306.81
B85: Effect in FCF level due to: | AK85: =AK84+1 -> 20 | AL85: =IF($AK85=Calc!$I$113,Calc!I233+NPV(DiscRPriorSub,(Calc!J233:Q233,Calc!R238)),0) -> 260136.57 | AM85: =IF($AK85=Calc!$I$113,Calc!I233+NPV(DiscRPriorSub,(Calc!J233:V233,Calc!W238)),0) -> 806132.86
B86: Investment Change: | AK86: =AK85+1 -> 21 | AL86: =IF($AK86=Calc!$J$113,Calc!J233+NPV(DiscRPriorSub,(Calc!K233:R233,Calc!S238)),0) -> 354207.36 | AM86: =IF($AK86=Calc!$J$113,Calc!J233+NPV(DiscRPriorSub,(Calc!K233:W233,Calc!X238)),0) -> 1017144.5
B87: SSG&A | C87: Fwd Look (Current Submission) | G87: =((G19)*(1-$BU$24)) -> 200 | H87: =((H19)*(1-$BU$24)) -> 1000 | I87: =((I19)*(1-$BU$24)) -> 2500 | J87: =((J19)*(1-$BU$24)) -> 3500 | K87: =((K19)*(1-$BU$24)) -> 4500 | L87: =((L19)*(1-$BU$24)) -> 3300.0097 | M87: =((M19)*(1-$BU$24)) -> 3694.2371 | N87: =((N19)*(1-$BU$24)) -> 3323.4315 | ... AI87: =((AI19)*(1-$BU$24)) -> 0 | AK87: =AK86+1 -> 22 | AL87: =IF($AK87=Calc!$K$113,Calc!K233+NPV(DiscRPriorSub,(Calc!L233:S233,Calc!T238)),0) -> 453748.09 | AM87: =IF($AK87=Calc!$K$113,Calc!K233+NPV(DiscRPriorSub,(Calc!L233:X233,Calc!Y238)),0) -> 1064116.1
C88: Fwd Look (Prior Submission) | G88: =((AQ19)*(1-$BU$24)) -> 0 | H88: =((AR19)*(1-$BU$24)) -> 0 | I88: =((AS19)*(1-$BU$24)) -> 0 | J88: =((AT19)*(1-$BU$24)) -> 0 | K88: =((AU19)*(1-$BU$24)) -> 0 | L88: =((AV19)*(1-$BU$24)) -> 0 | M88: =((AW19)*(1-$BU$24)) -> 0 | N88: =((AX19)*(1-$BU$24)) -> 0 | ... AI88: =((BS19)*(1-$BU$24)) -> 0 | AK88: =AK87+1 -> 23 | AL88: =IF($AK88=Calc!$L$113,Calc!L233+NPV(DiscRPriorSub,(Calc!M233:T233,Calc!U238)),0) -> 566874.58 | AM88: =IF($AK88=Calc!$L$113,Calc!L233+NPV(DiscRPriorSub,(Calc!M233:Y233,Calc!Z238)),0) -> 1069318.5
B89: R&D | C89: Fwd Look (Current Submission) | G89: =((G20)*(1-$BU$24)) -> 4828.4207 | H89: =((H20)*(1-$BU$24)) -> 3450.6323 | I89: =((I20)*(1-$BU$24)) -> 8338.5411 | J89: =((J20)*(1-$BU$24)) -> 7736.0277 | K89: =((K20)*(1-$BU$24)) -> 2362.6099 | L89: =((L20)*(1-$BU$24)) -> 1451.8026 | M89: =((M20)*(1-$BU$24)) -> 205.83869 | N89: =((N20)*(1-$BU$24)) -> 209.95546 | ... AI89: =((AI20)*(1-$BU$24)) -> 0 | AK89: =AK88+1 -> 24 | AL89: =IF($AK89=Calc!$M$113,Calc!M233+NPV(DiscRPriorSub,(Calc!N233:U233,Calc!V238)),0) -> 700201.01 | AM89: =IF($AK89=Calc!$M$113,Calc!M233+NPV(DiscRPriorSub,(Calc!N233:Z233,Calc!AA238)),0) -> 1081173.4
C90: Fwd Look (Prior Submission) | G90: =((AQ20)*(1-$BU$24)) -> 0 | H90: =((AR20)*(1-$BU$24)) -> 0 | I90: =((AS20)*(1-$BU$24)) -> 0 | J90: =((AT20)*(1-$BU$24)) -> 0 | K90: =((AU20)*(1-$BU$24)) -> 0 | L90: =((AV20)*(1-$BU$24)) -> 0 | M90: =((AW20)*(1-$BU$24)) -> 0 | N90: =((AX20)*(1-$BU$24)) -> 0 | ... AI90: =((BS20)*(1-$BU$24)) -> 0 | AK90: =AK89+1 -> 25 | AL90: =IF($AK90=Calc!$N$113,Calc!N233+NPV(DiscRPriorSub,(Calc!O233:V233,Calc!W238)),0) -> 826217.7 | AM90: =IF($AK90=Calc!$N$113,Calc!N233+NPV(DiscRPriorSub,(Calc!O233:AA233,Calc!AB238)),0) -> 1068568.5
B91: Capital | C91: Fwd Look (Current Submission) | G91: =G27 -> 0 | H91: =H27 -> 0 | I91: =I27 -> 0 | J91: =J27 -> 0 | K91: =K27 -> 0 | L91: =L27 -> 13066.667 | M91: =M27 -> -933.33333 | N91: =N27 -> -933.33333 | ... AI91: =AI27 -> 0 | AK91: =AK90+1 -> 26 | AL91: =IF($AK91=Calc!$O$113,Calc!O233+NPV(DiscRPriorSub,(Calc!P233:W233,Calc!X238)),0) -> 1001550.4 | AM91: =IF($AK91=Calc!$O$113,Calc!O233+NPV(DiscRPriorSub,(Calc!P233:AB233,Calc!AC238)),0) -> 1040693.3
C92: Fwd Look (Prior Submission) | G92: =AQ27 -> 0 | H92: =AR27 -> 0 | I92: =AS27 -> 0 | J92: =AT27 -> 0 | K92: =AU27 -> 0 | L92: =AV27 -> 0 | M92: =AW27 -> 0 | N92: =AX27 -> 0 | ... AI92: =BS27 -> 0 | AK92: =AK91+1 -> 27 | AL92: =IF($AK92=Calc!$P$113,Calc!P233+NPV(DiscRPriorSub,(Calc!Q233:X233,Calc!Y238)),0) -> 994672.56 | AM92: =IF($AK92=Calc!$P$113,Calc!P233+NPV(DiscRPriorSub,(Calc!Q233:AC233,Calc!AD238)),0) -> 994933.89
AK93: =AK92+1 -> 28 | AL93: =IF($AK93=Calc!$Q$113,Calc!Q233+NPV(DiscRPriorSub,(Calc!R233:Y233,Calc!Z238)),0) -> 934379.87 | AM93: =IF($AK93=Calc!$Q$113,Calc!Q233+NPV(DiscRPriorSub,(Calc!R233:AD233,Calc!AE238)),0) -> 934379.87
B94: Launch Delay: (Based on Prior Submission Scenario - 10yrs) | AK94: =AK93+1 -> 29 | AL94: =IF($AK94=Calc!$R$113,Calc!R233+NPV(DiscRPriorSub,(Calc!S233:Z233,Calc!AA238)),0) -> 864198.34 | AM94: =IF($AK94=Calc!$R$113,Calc!R233+NPV(DiscRPriorSub,(Calc!S233:AE233,Calc!AF238)),0) -> 864198.34 | AO94: Launch Delay: (Based on Prior Submission Scenario - 15yrs)
G95: Current Sub | H95: Prior Sub | J95: Slippage | K95: Deferred Yrs | L95: Deferred Mths | O95: Slippage | AK95: =AK94+1 -> 30 | AL95: =IF($AK95=Calc!$S$113,Calc!S233+NPV(DiscRPriorSub,(Calc!T233:AA233,Calc!AB238)),0) -> 788347.13 | AM95: =IF($AK95=Calc!$S$113,Calc!S233+NPV(DiscRPriorSub,(Calc!T233:AF233,Calc!AG238)),0) -> 788347.13 | AQ95: Current Sub | AR95: Prior Sub | AT95: Slippage | AU95: Deferred Yrs | AV95: Deferred Mths | AY95: Slippage
C96: Launch Date | G96: =IFERROR(IF(Input!$D$63="Feb",DATE("20"&Input!$E$63,VLOOKUP(Input!$D$63,FT_PPD_DD!$Y$84:$Z$97,2,0),28),DATE("20"&Input!$E$63,VLOOKUP(Input!$D$63,FT_PPD_DD!$Y$84:$Z$97,2,0),30)),"No") -> No | H96: =IFERROR(IF(BN42="Feb",DATE("20"&BO42,VLOOKUP(BN42,FT_PPD_DD!$Y$84:$Z$97,2,0),28),DATE("20"&BO42,VLOOKUP(BN42,FT_PPD_DD!$Y$84:$Z$97,2,0),30)),"No") -> No | J96: =ABS(ROUND((G96-H96)/365,2)) -> #VALUE! | K96: =ROUNDDOWN(J96,0) -> #VALUE! | L96: =J96-ROUNDDOWN(J96,0) -> #VALUE! | O96: =ROUND((G96-H96)/365,2) -> #VALUE! | P96: =IF(O96>=0,"Delay","Earlier") -> #VALUE! | AQ96: =IFERROR(IF(Input!$D$63="Feb",DATE("20"&Input!$E$63,VLOOKUP(Input!$D$63,FT_PPD_DD!$Y$84:$Z$97,2,0),28),DATE("20"&Input!$E$63,VLOOKUP(Input!$D$63,FT_PPD_DD!$Y$84:$Z$97,2,0),30)),"No") -> No | AR96: =IFERROR(IF(BN42="Feb",DATE("20"&BO42,VLOOKUP(BN42,FT_PPD_DD!$Y$84:$Z$97,2,0),28),DATE("20"&BO42,VLOOKUP(BN42,FT_PPD_DD!$Y$84:$Z$97,2,0),30)),"No") -> No | AT96: =ABS(ROUND((AQ96-AR96)/365,2)) -> #VALUE! | AU96: =ROUNDDOWN(AT96,0) -> #VALUE! | AV96: =AT96-ROUNDDOWN(AT96,0) -> #VALUE! | AY96: =ROUND((AQ96-AR96)/365,2) -> #VALUE! | AZ96: =IF(AY96>=0,"Delay","Earlier") -> #VALUE!
C97: Post Launch FCF | G97: =IF(G83=1,IF(LaunchFYPriorSub<=AQ66,IF(AQ66=CurrentFYPriorSub+9,AQ57,AQ52),0),0) -> #VALUE! | H97: =IF(H83=1,IF(LaunchFYPriorSub<=AR66,IF(AR66=CurrentFYPriorSub+9,AR57,AR52),0),0) -> #VALUE! | I97: =IF(I83=1,IF(LaunchFYPriorSub<=AS66,IF(AS66=CurrentFYPriorSub+9,AS57,AS52),0),0) -> #VALUE! | J97: =IF(J83=1,IF(LaunchFYPriorSub<=AT66,IF(AT66=CurrentFYPriorSub+9,AT57,AT52),0),0) -> #VALUE! | K97: =IF(K83=1,IF(LaunchFYPriorSub<=AU66,IF(AU66=CurrentFYPriorSub+9,AU57,AU52),0),0) -> #VALUE! | L97: =IF(L83=1,IF(LaunchFYPriorSub<=AV66,IF(AV66=CurrentFYPriorSub+9,AV57,AV52),0),0) -> #VALUE! | M97: =IF(M83=1,IF(LaunchFYPriorSub<=AW66,IF(AW66=CurrentFYPriorSub+9,AW57,AW52),0),0) -> #VALUE! | N97: =IF(N83=1,IF(LaunchFYPriorSub<=AX66,IF(AX66=CurrentFYPriorSub+9,AX57,AX52),0),0) -> #VALUE! | ... AI97: =IF(AI83=1,IF(LaunchFYPriorSub<=BS66,IF(BS66=CurrentFYPriorSub+9,BS57,BS52),0),0) -> #VALUE! | AQ97: =IF(AQ83=1,IF(LaunchFYPriorSub<=AQ66,IF(AQ66=CurrentFYPriorSub+14,AQ57,AQ52),0),0) -> #VALUE! | AR97: =IF(AR83=1,IF(LaunchFYPriorSub<=AR66,IF(AR66=CurrentFYPriorSub+14,AR57,AR52),0),0) -> #VALUE! | AS97: =IF(AS83=1,IF(LaunchFYPriorSub<=AS66,IF(AS66=CurrentFYPriorSub+14,AS57,AS52),0),0) -> #VALUE! | AT97: =IF(AT83=1,IF(LaunchFYPriorSub<=AT66,IF(AT66=CurrentFYPriorSub+14,AT57,AT52),0),0) -> #VALUE! | AU97: =IF(AU83=1,IF(LaunchFYPriorSub<=AU66,IF(AU66=CurrentFYPriorSub+14,AU57,AU52),0),0) -> #VALUE! | AV97: =IF(AV83=1,IF(LaunchFYPriorSub<=AV66,IF(AV66=CurrentFYPriorSub+14,AV57,AV52),0),0) -> #VALUE! | AW97: =IF(AW83=1,IF(LaunchFYPriorSub<=AW66,IF(AW66=CurrentFYPriorSub+14,AW57,AW52),0),0) -> #VALUE! | AX97: =IF(AX83=1,IF(LaunchFYPriorSub<=AX66,IF(AX66=CurrentFYPriorSub+14,AX57,AX52),0),0) -> #VALUE! | ... BS97: =IF(BS83=1,IF(LaunchFYPriorSub<=BS66,IF(BS66=CurrentFYPriorSub+14,BS57,BS52),0),0) -> #VALUE!
C98: To be deferred | G98: =$L$96*G97 -> #VALUE! | H98: =$L$96*H97 -> #VALUE! | I98: =$L$96*I97 -> #VALUE! | J98: =$L$96*J97 -> #VALUE! | K98: =$L$96*K97 -> #VALUE! | L98: =$L$96*L97 -> #VALUE! | M98: =$L$96*M97 -> #VALUE! | N98: =$L$96*N97 -> #VALUE! | ... AI98: =$L$96*AI97 -> #VALUE! | AQ98: =$AV$96*AQ97 -> #VALUE! | AR98: =$AV$96*AR97 -> #VALUE! | AS98: =$AV$96*AS97 -> #VALUE! | AT98: =$AV$96*AT97 -> #VALUE! | AU98: =$AV$96*AU97 -> #VALUE! | AV98: =$AV$96*AV97 -> #VALUE! | AW98: =$AV$96*AW97 -> #VALUE! | AX98: =$AV$96*AX97 -> #VALUE! | ... BS98: =$AV$96*BS97 -> #VALUE!
C100: Delay | F100: Delay | G100: New post-launch FCF (shifted by time difference) | AP100: Delay | AQ100: New post-launch FCF (shifted by time difference)
C101: 0 - 0.99 | F101: 0 | G101: =IF(G97=0,0,G$97-G$98+F$98) -> #VALUE! | H101: =IF(H97=0,0,H$97-H$98+G98) -> #VALUE! | I101: =IF(I97=0,0,I$97-I$98+H98) -> #VALUE! | J101: =IF(J97=0,0,J$97-J$98+I98) -> #VALUE! | K101: =IF(K97=0,0,K$97-K$98+J98) -> #VALUE! | L101: =IF(L97=0,0,L$97-L$98+K98) -> #VALUE! | M101: =IF(M97=0,0,M$97-M$98+L98) -> #VALUE! | N101: =IF(N97=0,0,N$97-N$98+M98) -> #VALUE! | O101: =IF(O97=0,0,O$97-O$98+N98) -> #VALUE! | ... AI101: =IF(AI97=0,0,AI$97-AI$98+AH98) -> #VALUE! | AP101: 0 | AQ101: =IF(AQ97=0,0,AQ$97-AQ$98+#REF!) -> #VALUE! | AR101: =IF(AR97=0,0,AR$97-AR$98+AQ98) -> #VALUE! | AS101: =IF(AS97=0,0,AS$97-AS$98+AR98) -> #VALUE! | AT101: =IF(AT97=0,0,AT$97-AT$98+AS98) -> #VALUE! | AU101: =IF(AU97=0,0,AU$97-AU$98+AT98) -> #VALUE! | AV101: =IF(AV97=0,0,AV$97-AV$98+AU98) -> #VALUE! | AW101: =IF(AW97=0,0,AW$97-AW$98+AV98) -> #VALUE! | AX101: =IF(AX97=0,0,AX$97-AX$98+AW98) -> #VALUE! | AY101: =IF(AY97=0,0,AY$97-AY$98+AX98) -> #VALUE! | ... BS101: =IF(BS97=0,0,BS$97-BS$98+BR98) -> #VALUE!
C102: 1 - 1.99 | F102: 1 | G102: =IF(G$97=0,0,IF($J$96=1,0,0)) -> #VALUE! | H102: =IF(H$97=0,0,IF($J$96=1,G$97,G$97-G$98)) -> #VALUE! | I102: =IF(I$97=0,0,IF($J$96=1,H$97,H$97-H$98+G$98)) -> #VALUE! | J102: =IF(J$97=0,0,IF($J$96=1,I$97,I$97-I$98+H$98)) -> #VALUE! | K102: =IF(K$97=0,0,IF($J$96=1,J$97,J$97-J$98+I$98)) -> #VALUE! | L102: =IF(L$97=0,0,IF($J$96=1,K$97,K$97-K$98+J$98)) -> #VALUE! | M102: =IF(M$97=0,0,IF($J$96=1,L$97,L$97-L$98+K$98)) -> #VALUE! | N102: =IF(N$97=0,0,IF($J$96=1,M$97,M$97-M$98+L$98)) -> #VALUE! | O102: =IF(O$97=0,0,IF($J$96=1,N$97,N$97-N$98+M$98)) -> #VALUE! | P102: =IF(P$97=0,0,IF($J$96=1,O$97,O$97-O$98+N$98)) -> #VALUE! | ... AI102: =IF(AI$97=0,0,IF($J$96=1,AH$97,AH$97-AH$98+AG$98)) -> #VALUE! | AP102: 1 | AQ102: =IF(AQ$97=0,0,IF($AT$96=1,0,0)) -> #VALUE! | AR102: =IF(AR$97=0,0,IF($AT$96=1,AQ$97,AQ$97-AQ$98)) -> #VALUE! | AS102: =IF(AS$97=0,0,IF($AT$96=1,AR$97,AR$97-AR$98+AQ$98)) -> #VALUE! | AT102: =IF(AT$97=0,0,IF($AT$96=1,AS$97,AS$97-AS$98+AR$98)) -> #VALUE! | AU102: =IF(AU$97=0,0,IF($AT$96=1,AT$97,AT$97-AT$98+AS$98)) -> #VALUE! | AV102: =IF(AV$97=0,0,IF($AT$96=1,AU$97,AU$97-AU$98+AT$98)) -> #VALUE! | AW102: =IF(AW$97=0,0,IF($AT$96=1,AV$97,AV$97-AV$98+AU$98)) -> #VALUE! | AX102: =IF(AX$97=0,0,IF($AT$96=1,AW$97,AW$97-AW$98+AV$98)) -> #VALUE! | AY102: =IF(AY$97=0,0,IF($AT$96=1,AX$97,AX$97-AX$98+AW$98)) -> #VALUE! | AZ102: =IF(AZ$97=0,0,IF($AT$96=1,AY$97,AY$97-AY$98+AX$98)) -> #VALUE! | ... BS102: =IF(BS$97=0,0,IF($AT$96=1,BR$97,BR$97-BR$98+BQ$98)) -> #VALUE!
C103: 2 - 2.99 | F103: 2 | G103: =IF(G$97=0,0,IF($J$96=2,0,0)) -> #VALUE! | H103: =IF(H$97=0,0,IF($J$96=2,0,0)) -> #VALUE! | I103: =IF(I$97=0,0,IF($J$96=2,G$97,G$97-G$98)) -> #VALUE! | J103: =IF(J$97=0,0,IF($J$96=2,H$97,H$97-H$98+G$98)) -> #VALUE! | K103: =IF(K$97=0,0,IF($J$96=2,I$97,I$97-I$98+H$98)) -> #VALUE! | L103: =IF(L$97=0,0,IF($J$96=2,J$97,J$97-J$98+I$98)) -> #VALUE! | M103: =IF(M$97=0,0,IF($J$96=2,K$97,K$97-K$98+J$98)) -> #VALUE! | N103: =IF(N$97=0,0,IF($J$96=2,L$97,L$97-L$98+K$98)) -> #VALUE! | O103: =IF(O$97=0,0,IF($J$96=2,M$97,M$97-M$98+L$98)) -> #VALUE! | P103: =IF(P$97=0,0,IF($J$96=2,N$97,N$97-N$98+M$98)) -> #VALUE! | Q103: =IF(Q$97=0,0,IF($J$96=2,O$97,O$97-O$98+N$98)) -> #VALUE! | ... AI103: =IF(AI$97=0,0,IF($J$96=2,AG$97,AG$97-AG$98+AF$98)) -> #VALUE! | AP103: 2 | AQ103: =IF(AQ$97=0,0,IF($AT$96=2,0,0)) -> #VALUE! | AR103: =IF(AR$97=0,0,IF($AT$96=2,0,0)) -> #VALUE! | AS103: =IF(AS$97=0,0,IF($AT$96=2,AQ$97,AQ$97-AQ$98)) -> #VALUE! | AT103: =IF(AT$97=0,0,IF($AT$96=2,AR$97,AR$97-AR$98+AQ$98)) -> #VALUE! | AU103: =IF(AU$97=0,0,IF($AT$96=2,AS$97,AS$97-AS$98+AR$98)) -> #VALUE! | AV103: =IF(AV$97=0,0,IF($AT$96=2,AT$97,AT$97-AT$98+AS$98)) -> #VALUE! | AW103: =IF(AW$97=0,0,IF($AT$96=2,AU$97,AU$97-AU$98+AT$98)) -> #VALUE! | AX103: =IF(AX$97=0,0,IF($AT$96=2,AV$97,AV$97-AV$98+AU$98)) -> #VALUE! | AY103: =IF(AY$97=0,0,IF($AT$96=2,AW$97,AW$97-AW$98+AV$98)) -> #VALUE! | AZ103: =IF(AZ$97=0,0,IF($AT$96=2,AX$97,AX$97-AX$98+AW$98)) -> #VALUE! | BA103: =IF(BA$97=0,0,IF($AT$96=2,AY$97,AY$97-AY$98+AX$98)) -> #VALUE! | ... BS103: =IF(BS$97=0,0,IF($AT$96=2,BQ$97,BQ$97-BQ$98+BP$98)) -> #VALUE!
C104: 3 - 3.99 | F104: 3 | G104: =IF(G$97=0,0,IF($J$96=3,0,0)) -> #VALUE! | H104: =IF(H$97=0,0,IF($J$96=3,0,0)) -> #VALUE! | I104: =IF(I$97=0,0,IF($J$96=3,0,0)) -> #VALUE! | J104: =IF(J$97=0,0,IF($J$96=3,G$97,G$97-G$98)) -> #VALUE! | K104: =IF(K$97=0,0,IF($J$96=3,H$97,H$97-H$98+G$98)) -> #VALUE! | L104: =IF(L$97=0,0,IF($J$96=3,I$97,I$97-I$98+H$98)) -> #VALUE! | M104: =IF(M$97=0,0,IF($J$96=3,J$97,J$97-J$98+I$98)) -> #VALUE! | N104: =IF(N$97=0,0,IF($J$96=3,K$97,K$97-K$98+J$98)) -> #VALUE! | O104: =IF(O$97=0,0,IF($J$96=3,L$97,L$97-L$98+K$98)) -> #VALUE! | P104: =IF(P$97=0,0,IF($J$96=3,M$97,M$97-M$98+L$98)) -> #VALUE! | Q104: =IF(Q$97=0,0,IF($J$96=3,N$97,N$97-N$98+M$98)) -> #VALUE! | R104: =IF(R$97=0,0,IF($J$96=3,O$97,O$97-O$98+N$98)) -> #VALUE! | ... AI104: =IF(AI$97=0,0,IF($J$96=3,AF$97,AF$97-AF$98+AE$98)) -> #VALUE! | AP104: 3 | AQ104: =IF(AQ$97=0,0,IF($AT$96=3,0,0)) -> #VALUE! | AR104: =IF(AR$97=0,0,IF($AT$96=3,0,0)) -> #VALUE! | AS104: =IF(AS$97=0,0,IF($AT$96=3,0,0)) -> #VALUE! | AT104: =IF(AT$97=0,0,IF($AT$96=3,AQ$97,AQ$97-AQ$98)) -> #VALUE! | AU104: =IF(AU$97=0,0,IF($AT$96=3,AR$97,AR$97-AR$98+AQ$98)) -> #VALUE! | AV104: =IF(AV$97=0,0,IF($AT$96=3,AS$97,AS$97-AS$98+AR$98)) -> #VALUE! | AW104: =IF(AW$97=0,0,IF($AT$96=3,AT$97,AT$97-AT$98+AS$98)) -> #VALUE! | AX104: =IF(AX$97=0,0,IF($AT$96=3,AU$97,AU$97-AU$98+AT$98)) -> #VALUE! | AY104: =IF(AY$97=0,0,IF($AT$96=3,AV$97,AV$97-AV$98+AU$98)) -> #VALUE! | AZ104: =IF(AZ$97=0,0,IF($AT$96=3,AW$97,AW$97-AW$98+AV$98)) -> #VALUE! | BA104: =IF(BA$97=0,0,IF($AT$96=3,AX$97,AX$97-AX$98+AW$98)) -> #VALUE! | BB104: =IF(BB$97=0,0,IF($AT$96=3,AY$97,AY$97-AY$98+AX$98)) -> #VALUE! | ... BS104: =IF(BS$97=0,0,IF($AT$96=3,BP$97,BP$97-BP$98+BO$98)) -> #VALUE!
C105: 4 - 4.99 | F105: 4 | G105: =IF(G$97=0,0,IF($J$96=4,0,0)) -> #VALUE! | H105: =IF(H$97=0,0,IF($J$96=4,0,0)) -> #VALUE! | I105: =IF(I$97=0,0,IF($J$96=4,0,0)) -> #VALUE! | J105: =IF(J$97=0,0,IF($J$96=4,0,0)) -> #VALUE! | K105: =IF(K$97=0,0,IF($J$96=4,G$97,G$97-G$98)) -> #VALUE! | L105: =IF(L$97=0,0,IF($J$96=4,H$97,H$97-H$98+G$98)) -> #VALUE! | M105: =IF(M$97=0,0,IF($J$96=4,I$97,I$97-I$98+H$98)) -> #VALUE! | N105: =IF(N$97=0,0,IF($J$96=4,J$97,J$97-J$98+I$98)) -> #VALUE! | O105: =IF(O$97=0,0,IF($J$96=4,K$97,K$97-K$98+J$98)) -> #VALUE! | P105: =IF(P$97=0,0,IF($J$96=4,L$97,L$97-L$98+K$98)) -> #VALUE! | Q105: =IF(Q$97=0,0,IF($J$96=4,M$97,M$97-M$98+L$98)) -> #VALUE! | R105: =IF(R$97=0,0,IF($J$96=4,N$97,N$97-N$98+M$98)) -> #VALUE! | S105: =IF(S$97=0,0,IF($J$96=4,O$97,O$97-O$98+N$98)) -> #VALUE! | ... AI105: =IF(AI$97=0,0,IF($J$96=4,AE$97,AE$97-AE$98+AD$98)) -> #VALUE! | AP105: 4 | AQ105: =IF(AQ$97=0,0,IF($AT$96=4,0,0)) -> #VALUE! | AR105: =IF(AR$97=0,0,IF($AT$96=4,0,0)) -> #VALUE! | AS105: =IF(AS$97=0,0,IF($AT$96=4,0,0)) -> #VALUE! | AT105: =IF(AT$97=0,0,IF($AT$96=4,0,0)) -> #VALUE! | AU105: =IF(AU$97=0,0,IF($AT$96=4,AQ$97,AQ$97-AQ$98)) -> #VALUE! | AV105: =IF(AV$97=0,0,IF($AT$96=4,AR$97,AR$97-AR$98+AQ$98)) -> #VALUE! | AW105: =IF(AW$97=0,0,IF($AT$96=4,AS$97,AS$97-AS$98+AR$98)) -> #VALUE! | AX105: =IF(AX$97=0,0,IF($AT$96=4,AT$97,AT$97-AT$98+AS$98)) -> #VALUE! | AY105: =IF(AY$97=0,0,IF($AT$96=4,AU$97,AU$97-AU$98+AT$98)) -> #VALUE! | AZ105: =IF(AZ$97=0,0,IF($AT$96=4,AV$97,AV$97-AV$98+AU$98)) -> #VALUE! | BA105: =IF(BA$97=0,0,IF($AT$96=4,AW$97,AW$97-AW$98+AV$98)) -> #VALUE! | BB105: =IF(BB$97=0,0,IF($AT$96=4,AX$97,AX$97-AX$98+AW$98)) -> #VALUE! | BC105: =IF(BC$97=0,0,IF($AT$96=4,AY$97,AY$97-AY$98+AX$98)) -> #VALUE! | ... BS105: =IF(BS$97=0,0,IF($AT$96=4,BO$97,BO$97-BO$98+BN$98)) -> #VALUE!
C106: Discted FCF Post Launch | G106: =IF(G82="x",0,G97/(1+DiscR)^G82) -> #VALUE! | H106: =H97/(1+DiscR)^H82 -> #VALUE! | I106: =I97/(1+DiscR)^I82 -> #VALUE! | J106: =J97/(1+DiscR)^J82 -> #VALUE! | K106: =K97/(1+DiscR)^K82 -> #VALUE! | L106: =L97/(1+DiscR)^L82 -> #VALUE! | M106: =M97/(1+DiscR)^M82 -> #VALUE! | N106: =N97/(1+DiscR)^N82 -> #VALUE! | O106: =O97/(1+DiscR)^O82 -> #VALUE! | ... AI106: =AI97/(1+DiscR)^AI82 -> #VALUE! | AQ106: =IF(AQ82="x",0,AQ97/(1+DiscR)^AQ82) -> #VALUE! | AR106: =AR97/(1+DiscR)^AR82 -> #VALUE! | AS106: =AS97/(1+DiscR)^AS82 -> #VALUE! | AT106: =AT97/(1+DiscR)^AT82 -> #VALUE! | AU106: =AU97/(1+DiscR)^AU82 -> #VALUE! | AV106: =AV97/(1+DiscR)^AV82 -> #VALUE! | AW106: =AW97/(1+DiscR)^AW82 -> #VALUE! | AX106: =AX97/(1+DiscR)^AX82 -> #VALUE! | AY106: =AY97/(1+DiscR)^AY82 -> #VALUE! | ... BS106: =BS97/(1+DiscR)^BS82 -> #VALUE!
C107: Discted FCF Post Launch Deferred | G107: =VLOOKUP(ABS($K$96),$F$101:$AI$105,2,0)/(1+DiscR)^G82 -> #VALUE! | H107: =VLOOKUP(ABS($K$96),$F$101:$AI$105,3,0)/(1+DiscR)^H82 -> #VALUE! | I107: =VLOOKUP(ABS($K$96),$F$101:$AI$105,4,0)/(1+DiscR)^I82 -> #VALUE! | J107: =VLOOKUP(ABS($K$96),$F$101:$AI$105,5,0)/(1+DiscR)^J82 -> #VALUE! | K107: =VLOOKUP(ABS($K$96),$F$101:$AI$105,6,0)/(1+DiscR)^K82 -> #VALUE! | L107: =VLOOKUP(ABS($K$96),$F$101:$AI$105,7,0)/(1+DiscR)^L82 -> #VALUE! | M107: =VLOOKUP(ABS($K$96),$F$101:$AI$105,8,0)/(1+DiscR)^M82 -> #VALUE! | N107: =VLOOKUP(ABS($K$96),$F$101:$AI$105,9,0)/(1+DiscR)^N82 -> #VALUE! | O107: =VLOOKUP(ABS($K$96),$F$101:$AI$105,10,0)/(1+DiscR)^O82 -> #VALUE! | P107: =VLOOKUP(ABS($K$96),$F$101:$AI$105,11,0)/(1+DiscR)^P82 -> #VALUE! | Q107: =VLOOKUP(ABS($K$96),$F$101:$AI$105,12,0)/(1+DiscR)^Q82 -> #VALUE! | R107: =VLOOKUP(ABS($K$96),$F$101:$AI$105,13,0)/(1+DiscR)^R82 -> #VALUE! | S107: =VLOOKUP(ABS($K$96),$F$101:$AI$105,14,0)/(1+DiscR)^S82 -> #VALUE! | T107: =VLOOKUP(ABS($K$96),$F$101:$AI$105,15,0)/(1+DiscR)^T82 -> #VALUE! | U107: =VLOOKUP(ABS($K$96),$F$101:$AI$105,16,0)/(1+DiscR)^U82 -> #VALUE! | V107: =VLOOKUP(ABS($K$96),$F$101:$AI$105,17,0)/(1+DiscR)^V82 -> #VALUE! | W107: =VLOOKUP(ABS($K$96),$F$101:$AI$105,18,0)/(1+DiscR)^W82 -> #VALUE! | X107: =VLOOKUP(ABS($K$96),$F$101:$AI$105,19,0)/(1+DiscR)^X82 -> #VALUE! | Y107: =VLOOKUP(ABS($K$96),$F$101:$AI$105,20,0)/(1+DiscR)^Y82 -> #VALUE! | Z107: =VLOOKUP(ABS($K$96),$F$101:$AI$105,21,0)/(1+DiscR)^Z82 -> #VALUE! | AA107: =VLOOKUP(ABS($K$96),$F$101:$AI$105,22,0)/(1+DiscR)^AA82 -> #VALUE! | AB107: =VLOOKUP(ABS($K$96),$F$101:$AI$105,23,0)/(1+DiscR)^AB82 -> #VALUE! | AC107: =VLOOKUP(ABS($K$96),$F$101:$AI$105,24,0)/(1+DiscR)^AC82 -> #VALUE! | AD107: =VLOOKUP(ABS($K$96),$F$101:$AI$105,25,0)/(1+DiscR)^AD82 -> #VALUE! | AE107: =VLOOKUP(ABS($K$96),$F$101:$AI$105,26,0)/(1+DiscR)^AE82 -> #VALUE! | AF107: =VLOOKUP(ABS($K$96),$F$101:$AI$105,27,0)/(1+DiscR)^AF82 -> #VALUE! | AG107: =VLOOKUP(ABS($K$96),$F$101:$AI$105,28,0)/(1+DiscR)^AG82 -> #VALUE! | AH107: =VLOOKUP(ABS($K$96),$F$101:$AI$105,29,0)/(1+DiscR)^AH82 -> #VALUE! | AI107: =VLOOKUP(ABS($K$96),$F$101:$AI$105,30,0)/(1+DiscR)^AI82 -> #VALUE! | AQ107: =VLOOKUP(ABS($AU$96),$AP$101:$BS$105,2,0)/(1+DiscR)^AQ82 -> #VALUE! | AR107: =VLOOKUP(ABS($AU$96),$AP$101:$BS$105,3,0)/(1+DiscR)^AR82 -> #VALUE! | AS107: =VLOOKUP(ABS($AU$96),$AP$101:$BS$105,4,0)/(1+DiscR)^AS82 -> #VALUE! | AT107: =VLOOKUP(ABS($AU$96),$AP$101:$BS$105,5,0)/(1+DiscR)^AT82 -> #VALUE! | AU107: =VLOOKUP(ABS($AU$96),$AP$101:$BS$105,6,0)/(1+DiscR)^AU82 -> #VALUE! | AV107: =VLOOKUP(ABS($AU$96),$AP$101:$BS$105,7,0)/(1+DiscR)^AV82 -> #VALUE! | AW107: =VLOOKUP(ABS($AU$96),$AP$101:$BS$105,8,0)/(1+DiscR)^AW82 -> #VALUE! | AX107: =VLOOKUP(ABS($AU$96),$AP$101:$BS$105,9,0)/(1+DiscR)^AX82 -> #VALUE! | AY107: =VLOOKUP(ABS($AU$96),$AP$101:$BS$105,10,0)/(1+DiscR)^AY82 -> #VALUE! | AZ107: =VLOOKUP(ABS($AU$96),$AP$101:$BS$105,11,0)/(1+DiscR)^AZ82 -> #VALUE! | BA107: =VLOOKUP(ABS($AU$96),$AP$101:$BS$105,12,0)/(1+DiscR)^BA82 -> #VALUE! | BB107: =VLOOKUP(ABS($AU$96),$AP$101:$BS$105,13,0)/(1+DiscR)^BB82 -> #VALUE! | BC107: =VLOOKUP(ABS($AU$96),$AP$101:$BS$105,14,0)/(1+DiscR)^BC82 -> #VALUE! | BD107: =VLOOKUP(ABS($AU$96),$AP$101:$BS$105,15,0)/(1+DiscR)^BD82 -> #VALUE! | BE107: =VLOOKUP(ABS($AU$96),$AP$101:$BS$105,16,0)/(1+DiscR)^BE82 -> #VALUE! | BF107: =VLOOKUP(ABS($AU$96),$AP$101:$BS$105,17,0)/(1+DiscR)^BF82 -> #VALUE! | BG107: =VLOOKUP(ABS($AU$96),$AP$101:$BS$105,18,0)/(1+DiscR)^BG82 -> #VALUE! | BH107: =VLOOKUP(ABS($AU$96),$AP$101:$BS$105,19,0)/(1+DiscR)^BH82 -> #VALUE! | BI107: =VLOOKUP(ABS($AU$96),$AP$101:$BS$105,20,0)/(1+DiscR)^BI82 -> #VALUE! | BJ107: =VLOOKUP(ABS($AU$96),$AP$101:$BS$105,21,0)/(1+DiscR)^BJ82 -> #VALUE! | BK107: =VLOOKUP(ABS($AU$96),$AP$101:$BS$105,22,0)/(1+DiscR)^BK82 -> #VALUE! | BL107: =VLOOKUP(ABS($AU$96),$AP$101:$BS$105,23,0)/(1+DiscR)^BL82 -> #VALUE! | BM107: =VLOOKUP(ABS($AU$96),$AP$101:$BS$105,24,0)/(1+DiscR)^BM82 -> #VALUE! | BN107: =VLOOKUP(ABS($AU$96),$AP$101:$BS$105,25,0)/(1+DiscR)^BN82 -> #VALUE! | BO107: =VLOOKUP(ABS($AU$96),$AP$101:$BS$105,26,0)/(1+DiscR)^BO82 -> #VALUE! | BP107: =VLOOKUP(ABS($AU$96),$AP$101:$BS$105,27,0)/(1+DiscR)^BP82 -> #VALUE! | BQ107: =VLOOKUP(ABS($AU$96),$AP$101:$BS$105,28,0)/(1+DiscR)^BQ82 -> #VALUE! | BR107: =VLOOKUP(ABS($AU$96),$AP$101:$BS$105,29,0)/(1+DiscR)^BR82 -> #VALUE! | BS107: =VLOOKUP(ABS($AU$96),$AP$101:$BS$105,30,0)/(1+DiscR)^BS82 -> #VALUE!
C109: Earlier Launch | F109: Earlier | G109: New post-launch FCF (shifted by time difference) | AP109: Earlier | AQ109: New post-launch FCF (shifted by time difference)
C110: 0 - 0.99 | F110: 0 | G110: =IF(G97=0,0,G$97-G$98+H98) -> #VALUE! | H110: =IF(H97=0,0,H$97-H$98+I98) -> #VALUE! | I110: =IF(I97=0,0,I$97-I$98+J98) -> #VALUE! | J110: =IF(J97=0,0,J$97-J$98+K98) -> #VALUE! | K110: =IF(K97=0,0,K$97-K$98+L98) -> #VALUE! | L110: =IF(L97=0,0,L$97-L$98+M98) -> #VALUE! | M110: =IF(M97=0,0,M$97-M$98+N98) -> #VALUE! | N110: =IF(N97=0,0,N$97-N$98+O98) -> #VALUE! | ... AI110: =IF(AI97=0,0,AI$97-AI$98+AJ98) -> #VALUE! | AP110: 0 | AQ110: =IF(AQ97=0,0,AQ$97-AQ$98+AR98) -> #VALUE! | AR110: =IF(AR97=0,0,AR$97-AR$98+AS98) -> #VALUE! | AS110: =IF(AS97=0,0,AS$97-AS$98+AT98) -> #VALUE! | AT110: =IF(AT97=0,0,AT$97-AT$98+AU98) -> #VALUE! | AU110: =IF(AU97=0,0,AU$97-AU$98+AV98) -> #VALUE! | AV110: =IF(AV97=0,0,AV$97-AV$98+AW98) -> #VALUE! | AW110: =IF(AW97=0,0,AW$97-AW$98+AX98) -> #VALUE! | AX110: =IF(AX97=0,0,AX$97-AX$98+AY98) -> #VALUE! | ... BS110: =IF(BS97=0,0,BS$97-BS$98+BT98) -> #VALUE!
C111: 1 - 1.99 | F111: 1 | G111: =IF(G$97=0,0,IF($J$96=1,H$97,H$97-H$98+I$98)) -> #VALUE! | H111: =IF(H$97=0,0,IF($J$96=1,I$97,I$97-I$98+J$98)) -> #VALUE! | I111: =IF(I$97=0,0,IF($J$96=1,J$97,J$97-J$98+K$98)) -> #VALUE! | J111: =IF(J$97=0,0,IF($J$96=1,K$97,K$97-K$98+L$98)) -> #VALUE! | K111: =IF(K$97=0,0,IF($J$96=1,L$97,L$97-L$98+M$98)) -> #VALUE! | L111: =IF(L$97=0,0,IF($J$96=1,M$97,M$97-M$98+N$98)) -> #VALUE! | M111: =IF(M$97=0,0,IF($J$96=1,N$97,N$97-N$98+O$98)) -> #VALUE! | N111: =IF(N$97=0,0,IF($J$96=1,O$97,O$97-O$98+P$98)) -> #VALUE! | ... W111: =IF(W$97=0,0,IF($J$96=1,X$97,X$97-X$98+Y$98)) -> #VALUE! | X111: =IF(X$97=0,0,IF($J$96=1,Y$97,Y$97-Y$98+AJ$98)) -> #VALUE! | Y111: =IF(Y$97=0,0,IF($J$96=1,Z$97,Z$97-Z$98+AK$98)) -> #VALUE! | Z111: =IF(Z$97=0,0,IF($J$96=1,AA$97,AA$97-AA$98+AL$98)) -> #VALUE! | AA111: =IF(AA$97=0,0,IF($J$96=1,AB$97,AB$97-AB$98+AM$98)) -> #VALUE! | AB111: =IF(AB$97=0,0,IF($J$96=1,AC$97,AC$97-AC$98+AN$98)) -> #VALUE! | AC111: =IF(AC$97=0,0,IF($J$96=1,AD$97,AD$97-AD$98+AO$98)) -> #VALUE! | AD111: =IF(AD$97=0,0,IF($J$96=1,AE$97,AE$97-AE$98+AP$98)) -> #VALUE! | AE111: =IF(AE$97=0,0,IF($J$96=1,AF$97,AF$97-AF$98+AQ$98)) -> #VALUE! | ... AI111: =IF(AI$97=0,0,IF($J$96=1,AJ$97,AJ$97-AJ$98+AU$98)) -> #VALUE! | AP111: 1 | AQ111: =IF(AQ$97=0,0,IF($AT$96=1,AR$97,AR$97-AR$98+AS$98)) -> #VALUE! | AR111: =IF(AR$97=0,0,IF($AT$96=1,AS$97,AS$97-AS$98+AT$98)) -> #VALUE! | AS111: =IF(AS$97=0,0,IF($AT$96=1,AT$97,AT$97-AT$98+AU$98)) -> #VALUE! | AT111: =IF(AT$97=0,0,IF($AT$96=1,AU$97,AU$97-AU$98+AV$98)) -> #VALUE! | AU111: =IF(AU$97=0,0,IF($AT$96=1,AV$97,AV$97-AV$98+AW$98)) -> #VALUE! | AV111: =IF(AV$97=0,0,IF($AT$96=1,AW$97,AW$97-AW$98+AX$98)) -> #VALUE! | AW111: =IF(AW$97=0,0,IF($AT$96=1,AX$97,AX$97-AX$98+AY$98)) -> #VALUE! | AX111: =IF(AX$97=0,0,IF($AT$96=1,AY$97,AY$97-AY$98+AZ$98)) -> #VALUE! | ... BG111: =IF(BG$97=0,0,IF($AT$96=1,BH$97,BH$97-BH$98+BI$98)) -> #VALUE! | BH111: =IF(BH$97=0,0,IF($AT$96=1,BI$97,BI$97-BI$98+BT$98)) -> #VALUE! | BI111: =IF(BI$97=0,0,IF($AT$96=1,BJ$97,BJ$97-BJ$98+BU$98)) -> #VALUE! | BJ111: =IF(BJ$97=0,0,IF($AT$96=1,BK$97,BK$97-BK$98+BV$98)) -> #VALUE! | BK111: =IF(BK$97=0,0,IF($AT$96=1,BL$97,BL$97-BL$98+BW$98)) -> #VALUE! | BL111: =IF(BL$97=0,0,IF($AT$96=1,BM$97,BM$97-BM$98+BX$98)) -> #VALUE! | BM111: =IF(BM$97=0,0,IF($AT$96=1,BN$97,BN$97-BN$98+BY$98)) -> #VALUE! | BN111: =IF(BN$97=0,0,IF($AT$96=1,BO$97,BO$97-BO$98+BZ$98)) -> #VALUE! | BO111: =IF(BO$97=0,0,IF($AT$96=1,BP$97,BP$97-BP$98+CA$98)) -> #VALUE! | ... BS111: =IF(BS$97=0,0,IF($AT$96=1,BT$97,BT$97-BT$98+CE$98)) -> #VALUE!
C112: 2 - 2.99 | F112: 2 | G112: =IF(G$97=0,0,IF($J$96=2,I$97,I$97-I$98+J$98)) -> #VALUE! | H112: =IF(H$97=0,0,IF($J$96=2,J$97,J$97-J$98+K$98)) -> #VALUE! | I112: =IF(I$97=0,0,IF($J$96=2,K$97,K$97-K$98+L$98)) -> #VALUE! | J112: =IF(J$97=0,0,IF($J$96=2,L$97,L$97-L$98+M$98)) -> #VALUE! | K112: =IF(K$97=0,0,IF($J$96=2,M$97,M$97-M$98+N$98)) -> #VALUE! | L112: =IF(L$97=0,0,IF($J$96=2,N$97,N$97-N$98+O$98)) -> #VALUE! | M112: =IF(M$97=0,0,IF($J$96=2,O$97,O$97-O$98+P$98)) -> #VALUE! | N112: =IF(N$97=0,0,IF($J$96=2,P$97,P$97-P$98+Q$98)) -> #VALUE! | ... V112: =IF(V$97=0,0,IF($J$96=2,X$97,X$97-X$98+Y$98)) -> #VALUE! | W112: =IF(W$97=0,0,IF($J$96=2,Y$97,Y$97-Y$98+AJ$98)) -> #VALUE! | X112: =IF(X$97=0,0,IF($J$96=2,AJ$97,AJ$97-AJ$98+AK$98)) -> #VALUE! | Y112: =IF(Y$97=0,0,IF($J$96=2,AK$97,AK$97-AK$98+AL$98)) -> #VALUE! | Z112: =IF(Z$97=0,0,IF($J$96=2,AL$97,AL$97-AL$98+AM$98)) -> #VALUE! | AA112: =IF(AA$97=0,0,IF($J$96=2,AM$97,AM$97-AM$98+AN$98)) -> #VALUE! | AB112: =IF(AB$97=0,0,IF($J$96=2,AN$97,AN$97-AN$98+AO$98)) -> #VALUE! | AC112: =IF(AC$97=0,0,IF($J$96=2,AO$97,AO$97-AO$98+AP$98)) -> #VALUE! | AD112: =IF(AD$97=0,0,IF($J$96=2,AP$97,AP$97-AP$98+AQ$98)) -> #VALUE! | AE112: =IF(AE$97=0,0,IF($J$96=2,AQ$97,AQ$97-AQ$98+AR$98)) -> #VALUE! | ... AI112: =IF(AI$97=0,0,IF($J$96=2,AU$97,AU$97-AU$98+AV$98)) -> #VALUE! | AP112: 2 | AQ112: =IF(AQ$97=0,0,IF($AT$96=2,AS$97,AS$97-AS$98+AT$98)) -> #VALUE! | AR112: =IF(AR$97=0,0,IF($AT$96=2,AT$97,AT$97-AT$98+AU$98)) -> #VALUE! | AS112: =IF(AS$97=0,0,IF($AT$96=2,AU$97,AU$97-AU$98+AV$98)) -> #VALUE! | AT112: =IF(AT$97=0,0,IF($AT$96=2,AV$97,AV$97-AV$98+AW$98)) -> #VALUE! | AU112: =IF(AU$97=0,0,IF($AT$96=2,AW$97,AW$97-AW$98+AX$98)) -> #VALUE! | AV112: =IF(AV$97=0,0,IF($AT$96=2,AX$97,AX$97-AX$98+AY$98)) -> #VALUE! | AW112: =IF(AW$97=0,0,IF($AT$96=2,AY$97,AY$97-AY$98+AZ$98)) -> #VALUE! | AX112: =IF(AX$97=0,0,IF($AT$96=2,AZ$97,AZ$97-AZ$98+BA$98)) -> #VALUE! | ... BF112: =IF(BF$97=0,0,IF($AT$96=2,BH$97,BH$97-BH$98+BI$98)) -> #VALUE! | BG112: =IF(BG$97=0,0,IF($AT$96=2,BI$97,BI$97-BI$98+BT$98)) -> #VALUE! | BH112: =IF(BH$97=0,0,IF($AT$96=2,BT$97,BT$97-BT$98+BU$98)) -> #VALUE! | BI112: =IF(BI$97=0,0,IF($AT$96=2,BU$97,BU$97-BU$98+BV$98)) -> #VALUE! | BJ112: =IF(BJ$97=0,0,IF($AT$96=2,BV$97,BV$97-BV$98+BW$98)) -> #VALUE! | BK112: =IF(BK$97=0,0,IF($AT$96=2,BW$97,BW$97-BW$98+BX$98)) -> #VALUE! | BL112: =IF(BL$97=0,0,IF($AT$96=2,BX$97,BX$97-BX$98+BY$98)) -> #VALUE! | BM112: =IF(BM$97=0,0,IF($AT$96=2,BY$97,BY$97-BY$98+BZ$98)) -> #VALUE! | BN112: =IF(BN$97=0,0,IF($AT$96=2,BZ$97,BZ$97-BZ$98+CA$98)) -> #VALUE! | BO112: =IF(BO$97=0,0,IF($AT$96=2,CA$97,CA$97-CA$98+CB$98)) -> #VALUE! | ... BS112: =IF(BS$97=0,0,IF($AT$96=2,CE$97,CE$97-CE$98+CF$98)) -> #VALUE!
C113: 3 - 3.99 | F113: 3 | G113: =IF(G$97=0,0,IF($J$96=3,J$97,J$97-J$98+K$98)) -> #VALUE! | H113: =IF(H$97=0,0,IF($J$96=3,K$97,K$97-K$98+L$98)) -> #VALUE! | I113: =IF(I$97=0,0,IF($J$96=3,L$97,L$97-L$98+M$98)) -> #VALUE! | J113: =IF(J$97=0,0,IF($J$96=3,M$97,M$97-M$98+N$98)) -> #VALUE! | K113: =IF(K$97=0,0,IF($J$96=3,N$97,N$97-N$98+O$98)) -> #VALUE! | L113: =IF(L$97=0,0,IF($J$96=3,O$97,O$97-O$98+P$98)) -> #VALUE! | M113: =IF(M$97=0,0,IF($J$96=3,P$97,P$97-P$98+Q$98)) -> #VALUE! | N113: =IF(N$97=0,0,IF($J$96=3,Q$97,Q$97-Q$98+R$98)) -> #VALUE! | ... U113: =IF(U$97=0,0,IF($J$96=3,X$97,X$97-X$98+Y$98)) -> #VALUE! | V113: =IF(V$97=0,0,IF($J$96=3,Y$97,Y$97-Y$98+AJ$98)) -> #VALUE! | W113: =IF(W$97=0,0,IF($J$96=3,AJ$97,AJ$97-AJ$98+AK$98)) -> #VALUE! | X113: =IF(X$97=0,0,IF($J$96=3,AK$97,AK$97-AK$98+AL$98)) -> #VALUE! | Y113: =IF(Y$97=0,0,IF($J$96=3,AL$97,AL$97-AL$98+AM$98)) -> #VALUE! | Z113: =IF(Z$97=0,0,IF($J$96=3,AM$97,AM$97-AM$98+AN$98)) -> #VALUE! | AA113: =IF(AA$97=0,0,IF($J$96=3,AN$97,AN$97-AN$98+AO$98)) -> #VALUE! | AB113: =IF(AB$97=0,0,IF($J$96=3,AO$97,AO$97-AO$98+AP$98)) -> #VALUE! | AC113: =IF(AC$97=0,0,IF($J$96=3,AP$97,AP$97-AP$98+AQ$98)) -> #VALUE! | AD113: =IF(AD$97=0,0,IF($J$96=3,AQ$97,AQ$97-AQ$98+AR$98)) -> #VALUE! | ... AI113: =IF(AI$97=0,0,IF($J$96=3,AV$97,AV$97-AV$98+AW$98)) -> #VALUE! | AP113: 3 | AQ113: =IF(AQ$97=0,0,IF($AT$96=3,AT$97,AT$97-AT$98+AU$98)) -> #VALUE! | AR113: =IF(AR$97=0,0,IF($AT$96=3,AU$97,AU$97-AU$98+AV$98)) -> #VALUE! | AS113: =IF(AS$97=0,0,IF($AT$96=3,AV$97,AV$97-AV$98+AW$98)) -> #VALUE! | AT113: =IF(AT$97=0,0,IF($AT$96=3,AW$97,AW$97-AW$98+AX$98)) -> #VALUE! | AU113: =IF(AU$97=0,0,IF($AT$96=3,AX$97,AX$97-AX$98+AY$98)) -> #VALUE! | AV113: =IF(AV$97=0,0,IF($AT$96=3,AY$97,AY$97-AY$98+AZ$98)) -> #VALUE! | AW113: =IF(AW$97=0,0,IF($AT$96=3,AZ$97,AZ$97-AZ$98+BA$98)) -> #VALUE! | AX113: =IF(AX$97=0,0,IF($AT$96=3,BA$97,BA$97-BA$98+BB$98)) -> #VALUE! | ... BE113: =IF(BE$97=0,0,IF($AT$96=3,BH$97,BH$97-BH$98+BI$98)) -> #VALUE! | BF113: =IF(BF$97=0,0,IF($AT$96=3,BI$97,BI$97-BI$98+BT$98)) -> #VALUE! | BG113: =IF(BG$97=0,0,IF($AT$96=3,BT$97,BT$97-BT$98+BU$98)) -> #VALUE! | BH113: =IF(BH$97=0,0,IF($AT$96=3,BU$97,BU$97-BU$98+BV$98)) -> #VALUE! | BI113: =IF(BI$97=0,0,IF($AT$96=3,BV$97,BV$97-BV$98+BW$98)) -> #VALUE! | BJ113: =IF(BJ$97=0,0,IF($AT$96=3,BW$97,BW$97-BW$98+BX$98)) -> #VALUE! | BK113: =IF(BK$97=0,0,IF($AT$96=3,BX$97,BX$97-BX$98+BY$98)) -> #VALUE! | BL113: =IF(BL$97=0,0,IF($AT$96=3,BY$97,BY$97-BY$98+BZ$98)) -> #VALUE! | BM113: =IF(BM$97=0,0,IF($AT$96=3,BZ$97,BZ$97-BZ$98+CA$98)) -> #VALUE! | BN113: =IF(BN$97=0,0,IF($AT$96=3,CA$97,CA$97-CA$98+CB$98)) -> #VALUE! | ... BS113: =IF(BS$97=0,0,IF($AT$96=3,CF$97,CF$97-CF$98+CG$98)) -> #VALUE!
C114: 4 - 4.99 | F114: 4 | G114: =IF(G$97=0,0,IF($J$96=4,K$97,K$97-K$98+L$98)) -> #VALUE! | H114: =IF(H$97=0,0,IF($J$96=4,L$97,L$97-L$98+M$98)) -> #VALUE! | I114: =IF(I$97=0,0,IF($J$96=4,M$97,M$97-M$98+N$98)) -> #VALUE! | J114: =IF(J$97=0,0,IF($J$96=4,N$97,N$97-N$98+O$98)) -> #VALUE! | K114: =IF(K$97=0,0,IF($J$96=4,O$97,O$97-O$98+P$98)) -> #VALUE! | L114: =IF(L$97=0,0,IF($J$96=4,P$97,P$97-P$98+Q$98)) -> #VALUE! | M114: =IF(M$97=0,0,IF($J$96=4,Q$97,Q$97-Q$98+R$98)) -> #VALUE! | N114: =IF(N$97=0,0,IF($J$96=4,R$97,R$97-R$98+S$98)) -> #VALUE! | ... T114: =IF(T$97=0,0,IF($J$96=4,X$97,X$97-X$98+Y$98)) -> #VALUE! | U114: =IF(U$97=0,0,IF($J$96=4,Y$97,Y$97-Y$98+AJ$98)) -> #VALUE! | V114: =IF(V$97=0,0,IF($J$96=4,AJ$97,AJ$97-AJ$98+AK$98)) -> #VALUE! | W114: =IF(W$97=0,0,IF($J$96=4,AK$97,AK$97-AK$98+AL$98)) -> #VALUE! | X114: =IF(X$97=0,0,IF($J$96=4,AL$97,AL$97-AL$98+AM$98)) -> #VALUE! | Y114: =IF(Y$97=0,0,IF($J$96=4,AM$97,AM$97-AM$98+AN$98)) -> #VALUE! | Z114: =IF(Z$97=0,0,IF($J$96=4,AN$97,AN$97-AN$98+AO$98)) -> #VALUE! | AA114: =IF(AA$97=0,0,IF($J$96=4,AO$97,AO$97-AO$98+AP$98)) -> #VALUE! | AB114: =IF(AB$97=0,0,IF($J$96=4,AP$97,AP$97-AP$98+AQ$98)) -> #VALUE! | AC114: =IF(AC$97=0,0,IF($J$96=4,AQ$97,AQ$97-AQ$98+AR$98)) -> #VALUE! | ... AI114: =IF(AI$97=0,0,IF($J$96=4,AW$97,AW$97-AW$98+AX$98)) -> #VALUE! | AP114: 4 | AQ114: =IF(AQ$97=0,0,IF($AT$96=4,AU$97,AU$97-AU$98+AV$98)) -> #VALUE! | AR114: =IF(AR$97=0,0,IF($AT$96=4,AV$97,AV$97-AV$98+AW$98)) -> #VALUE! | AS114: =IF(AS$97=0,0,IF($AT$96=4,AW$97,AW$97-AW$98+AX$98)) -> #VALUE! | AT114: =IF(AT$97=0,0,IF($AT$96=4,AX$97,AX$97-AX$98+AY$98)) -> #VALUE! | AU114: =IF(AU$97=0,0,IF($AT$96=4,AY$97,AY$97-AY$98+AZ$98)) -> #VALUE! | AV114: =IF(AV$97=0,0,IF($AT$96=4,AZ$97,AZ$97-AZ$98+BA$98)) -> #VALUE! | AW114: =IF(AW$97=0,0,IF($AT$96=4,BA$97,BA$97-BA$98+BB$98)) -> #VALUE! | AX114: =IF(AX$97=0,0,IF($AT$96=4,BB$97,BB$97-BB$98+BC$98)) -> #VALUE! | ... BD114: =IF(BD$97=0,0,IF($AT$96=4,BH$97,BH$97-BH$98+BI$98)) -> #VALUE! | BE114: =IF(BE$97=0,0,IF($AT$96=4,BI$97,BI$97-BI$98+BT$98)) -> #VALUE! | BF114: =IF(BF$97=0,0,IF($AT$96=4,BT$97,BT$97-BT$98+BU$98)) -> #VALUE! | BG114: =IF(BG$97=0,0,IF($AT$96=4,BU$97,BU$97-BU$98+BV$98)) -> #VALUE! | BH114: =IF(BH$97=0,0,IF($AT$96=4,BV$97,BV$97-BV$98+BW$98)) -> #VALUE! | BI114: =IF(BI$97=0,0,IF($AT$96=4,BW$97,BW$97-BW$98+BX$98)) -> #VALUE! | BJ114: =IF(BJ$97=0,0,IF($AT$96=4,BX$97,BX$97-BX$98+BY$98)) -> #VALUE! | BK114: =IF(BK$97=0,0,IF($AT$96=4,BY$97,BY$97-BY$98+BZ$98)) -> #VALUE! | BL114: =IF(BL$97=0,0,IF($AT$96=4,BZ$97,BZ$97-BZ$98+CA$98)) -> #VALUE! | BM114: =IF(BM$97=0,0,IF($AT$96=4,CA$97,CA$97-CA$98+CB$98)) -> #VALUE! | ... BS114: =IF(BS$97=0,0,IF($AT$96=4,CG$97,CG$97-CG$98+CH$98)) -> #VALUE!
C115: Discted FCF Post Launch | G115: =G97/(1+DiscR)^G82 -> #VALUE! | H115: =H97/(1+DiscR)^H82 -> #VALUE! | I115: =I97/(1+DiscR)^I82 -> #VALUE! | J115: =J97/(1+DiscR)^J82 -> #VALUE! | K115: =K97/(1+DiscR)^K82 -> #VALUE! | L115: =L97/(1+DiscR)^L82 -> #VALUE! | M115: =M97/(1+DiscR)^M82 -> #VALUE! | N115: =N97/(1+DiscR)^N82 -> #VALUE! | ... AI115: =AI97/(1+DiscR)^AI82 -> #VALUE! | AQ115: =AQ97/(1+DiscR)^AQ82 -> #VALUE! | AR115: =AR97/(1+DiscR)^AR82 -> #VALUE! | AS115: =AS97/(1+DiscR)^AS82 -> #VALUE! | AT115: =AT97/(1+DiscR)^AT82 -> #VALUE! | AU115: =AU97/(1+DiscR)^AU82 -> #VALUE! | AV115: =AV97/(1+DiscR)^AV82 -> #VALUE! | AW115: =AW97/(1+DiscR)^AW82 -> #VALUE! | AX115: =AX97/(1+DiscR)^AX82 -> #VALUE! | ... BS115: =BS97/(1+DiscR)^BS82 -> #VALUE!
...

Sheet HistInfo
B1: Historical Information
B3: This tab intents to keep historical information. At light green highlited cells, please paste figures as value (there are no formulas set).
B6: Financials at GPDS Exit Phases
B8: Definition
B10: Dates (Calendar Year): | AQ10: ** No Action needed on this portion
D11: Mth | E11: Year
B12: Def Exit Approved | D12: NA | E12: NA | G12: Provide when Def Exit was approved | AQ12: H/(L) Table
AQ13: Current Rebaseline vs Definition Exit Commitment
AQ15: Sunk | AR15: =G15 -> 0 | AS15: =H15 -> 0 | AT15: =I15 -> 0 | AU15: =J15 -> 0 | AV15: =K15 -> 0 | AW15: =L15 -> 0 | AX15: =M15 -> 0 | AY15: =N15 -> 0 | ... BU15: =AJ15 -> 0 | BW15: =AM15 -> 0
B17: Incremental Revenue | AQ17: =Calc!AP127-HistInfo!F17 -> 0 | AR17: =Calc!AQ127-HistInfo!G17 -> 0 | AS17: =Calc!AR127-HistInfo!H17 -> 0 | AT17: =Calc!AS127-HistInfo!I17 -> 0 | AU17: =Calc!AT127-HistInfo!J17 -> 0 | AV17: =Calc!AU127-HistInfo!K17 -> 0 | AW17: =Calc!AV127-HistInfo!L17 -> 0 | AX17: =Calc!AW127-HistInfo!M17 -> 0 | ... BU17: =Calc!BT127-HistInfo!AJ17 -> 0 | BW17: =Calc!BW127-HistInfo!AM17 -> 0
B18: Growth %
B19: Category Share | C19: Volume (units)
B20: True Inc Rev (exc. Loss Avoid): PPD
B21: Cost of Sales | AQ21: =Calc!AP131-HistInfo!F21 -> 0 | AR21: =Calc!AQ131-HistInfo!G21 -> 0 | AS21: =Calc!AR131-HistInfo!H21 -> 0 | AT21: =Calc!AS131-HistInfo!I21 -> 0 | AU21: =Calc!AT131-HistInfo!J21 -> 0 | AV21: =Calc!AU131-HistInfo!K21 -> 0 | AW21: =Calc!AV131-HistInfo!L21 -> 0 | AX21: =Calc!AW131-HistInfo!M21 -> 0 | ... BU21: =Calc!BT131-HistInfo!AJ21 -> 0 | BW21: =Calc!BW131-HistInfo!AM21 -> 0
B22: Depreciation | AQ22: =Calc!AP132-HistInfo!F22 -> 0 | AR22: =Calc!AQ132-HistInfo!G22 -> 0 | AS22: =Calc!AR132-HistInfo!H22 -> 0 | AT22: =Calc!AS132-HistInfo!I22 -> 0 | AU22: =Calc!AT132-HistInfo!J22 -> 0 | AV22: =Calc!AU132-HistInfo!K22 -> 0 | AW22: =Calc!AV132-HistInfo!L22 -> 0 | AX22: =Calc!AW132-HistInfo!M22 -> 0 | ... BU22: =Calc!BT132-HistInfo!AJ22 -> 0 | BW22: =Calc!BW132-HistInfo!AM22 -> 0
B23: Gross Profit | AQ23: =Calc!AP133-HistInfo!F23 -> 0 | AR23: =Calc!AQ133-HistInfo!G23 -> 0 | AS23: =Calc!AR133-HistInfo!H23 -> 0 | AT23: =Calc!AS133-HistInfo!I23 -> 0 | AU23: =Calc!AT133-HistInfo!J23 -> 0 | AV23: =Calc!AU133-HistInfo!K23 -> 0 | AW23: =Calc!AV133-HistInfo!L23 -> 0 | AX23: =Calc!AW133-HistInfo!M23 -> 0 | ... BU23: =Calc!BT133-HistInfo!AJ23 -> 0 | BW23: =Calc!BW133-HistInfo!AM23 -> 0
C24: % of Revenue
B25: SSG&A | AQ25: =Calc!AP135-HistInfo!F25 -> 0 | AR25: =Calc!AQ135-HistInfo!G25 -> 0 | AS25: =Calc!AR135-HistInfo!H25 -> 0 | AT25: =Calc!AS135-HistInfo!I25 -> 0 | AU25: =Calc!AT135-HistInfo!J25 -> 0 | AV25: =Calc!AU135-HistInfo!K25 -> 0 | AW25: =Calc!AV135-HistInfo!L25 -> 0 | AX25: =Calc!AW135-HistInfo!M25 -> 0 | ... BU25: =Calc!BT135-HistInfo!AJ25 -> 0 | BW25: =Calc!BW135-HistInfo!AM25 -> 0
B26: R&D | AQ26: =Calc!AP136-HistInfo!F26 -> 0 | AR26: =Calc!AQ136-HistInfo!G26 -> 0 | AS26: =Calc!AR136-HistInfo!H26 -> 0 | AT26: =Calc!AS136-HistInfo!I26 -> 0 | AU26: =Calc!AT136-HistInfo!J26 -> 0 | AV26: =Calc!AU136-HistInfo!K26 -> 0 | AW26: =Calc!AV136-HistInfo!L26 -> 0 | AX26: =Calc!AW136-HistInfo!M26 -> 0 | ... BU26: =Calc!BT136-HistInfo!AJ26 -> 0 | BW26: =Calc!BW136-HistInfo!AM26 -> 0
B27: OIBT | AQ27: =Calc!AP137-HistInfo!F27 -> 0 | AR27: =Calc!AQ137-HistInfo!G27 -> 0 | AS27: =Calc!AR137-HistInfo!H27 -> 0 | AT27: =Calc!AS137-HistInfo!I27 -> 0 | AU27: =Calc!AT137-HistInfo!J27 -> 0 | AV27: =Calc!AU137-HistInfo!K27 -> 0 | AW27: =Calc!AV137-HistInfo!L27 -> 0 | AX27: =Calc!AW137-HistInfo!M27 -> 0 | ... BU27: =Calc!BT137-HistInfo!AJ27 -> 0 | BW27: =Calc!BW137-HistInfo!AM27 -> 0
C28: % of Revenue
B29: Other (Inc) / Exp | AQ29: =Calc!AP139-HistInfo!F29 -> 0 | AR29: =Calc!AQ139-HistInfo!G29 -> 0 | AS29: =Calc!AR139-HistInfo!H29 -> 0 | AT29: =Calc!AS139-HistInfo!I29 -> 0 | AU29: =Calc!AT139-HistInfo!J29 -> 0 | AV29: =Calc!AU139-HistInfo!K29 -> 0 | AW29: =Calc!AV139-HistInfo!L29 -> 0 | AX29: =Calc!AW139-HistInfo!M29 -> 0 | ... BU29: =Calc!BT139-HistInfo!AJ29 -> 0 | BW29: =Calc!BW139-HistInfo!AM29 -> 0
B30: Tax Exp / (Ben) | AQ30: =Calc!AP140-HistInfo!F30 -> 0 | AR30: =Calc!AQ140-HistInfo!G30 -> 0 | AS30: =Calc!AR140-HistInfo!H30 -> 0 | AT30: =Calc!AS140-HistInfo!I30 -> 0 | AU30: =Calc!AT140-HistInfo!J30 -> 0 | AV30: =Calc!AU140-HistInfo!K30 -> 0 | AW30: =Calc!AV140-HistInfo!L30 -> 0 | AX30: =Calc!AW140-HistInfo!M30 -> 0 | ... BU30: =Calc!BT140-HistInfo!AJ30 -> 0 | BW30: =Calc!BW140-HistInfo!AM30 -> 0
B31: Net Income | AQ31: =Calc!AP141-HistInfo!F31 -> 0 | AR31: =Calc!AQ141-HistInfo!G31 -> 0 | AS31: =Calc!AR141-HistInfo!H31 -> 0 | AT31: =Calc!AS141-HistInfo!I31 -> 0 | AU31: =Calc!AT141-HistInfo!J31 -> 0 | AV31: =Calc!AU141-HistInfo!K31 -> 0 | AW31: =Calc!AV141-HistInfo!L31 -> 0 | AX31: =Calc!AW141-HistInfo!M31 -> 0 | ... BU31: =Calc!BT141-HistInfo!AJ31 -> 0 | BW31: =Calc!BW141-HistInfo!AM31 -> 0
C32: % of Revenue
B33: Capital | AQ33: =Calc!AP143-HistInfo!F33 -> 0 | AR33: =Calc!AQ143-HistInfo!G33 -> 0 | AS33: =Calc!AR143-HistInfo!H33 -> 0 | AT33: =Calc!AS143-HistInfo!I33 -> 0 | AU33: =Calc!AT143-HistInfo!J33 -> 0 | AV33: =Calc!AU143-HistInfo!K33 -> 0 | AW33: =Calc!AV143-HistInfo!L33 -> 0 | AX33: =Calc!AW143-HistInfo!M33 -> 0 | ... BU33: =Calc!BT143-HistInfo!AJ33 -> 0 | BW33: =Calc!BW143-HistInfo!AM33 -> 0
B34: Increase in Working Capital | AQ34: =Calc!AP144-HistInfo!F34 -> 0 | AR34: =Calc!AQ144-HistInfo!G34 -> 0 | AS34: =Calc!AR144-HistInfo!H34 -> 0 | AT34: =Calc!AS144-HistInfo!I34 -> 0 | AU34: =Calc!AT144-HistInfo!J34 -> 0 | AV34: =Calc!AU144-HistInfo!K34 -> 0 | AW34: =Calc!AV144-HistInfo!L34 -> 0 | AX34: =Calc!AW144-HistInfo!M34 -> 0 | ... BU34: =Calc!BT144-HistInfo!AJ34 -> 0 | BW34: =Calc!BW144-HistInfo!AM34 -> 0
B35: Free Cash Flow* | AQ35: =Calc!AP145-HistInfo!F35 -> 0 | AR35: =Calc!AQ145-HistInfo!G35 -> 0 | AS35: =Calc!AR145-HistInfo!H35 -> 0 | AT35: =Calc!AS145-HistInfo!I35 -> 0 | AU35: =Calc!AT145-HistInfo!J35 -> 0 | AV35: =Calc!AU145-HistInfo!K35 -> 0 | AW35: =Calc!AV145-HistInfo!L35 -> 0 | AX35: =Calc!AW145-HistInfo!M35 -> 0 | ... BU35: =Calc!BT145-HistInfo!AJ35 -> 0 | BW35: =Calc!BW145-HistInfo!AM35 -> 0
C36: % of Revenue
H40: Def Exit Approvers and Dates: | O40: Def Exit Commitment | V40: Actual / Expected Exit GPDS Phases, as project exited Definition
H41: Name and Last Review Date (Calendar Year) | Q41: 10 Yrs | R41: 15 Yrs
H42: Finance | K42: Mth | L42: Year | Q42: FY XX - ZZ | R42: FY XX - ZZ | V42: Dates (Calendar Year) | X42: Mth | Y42: Year | AA42: FY (equivalent)
H43: <Enter Name> | K43: NA | L43: NA | O43: MIRR | V43: Concept | X43: N/A | Y43: N/A | AA43: ="FY"&IF(OR(X43="Oct",X43="Nov",X43="Dec"),Y43+1,Y43) -> FYN/A
H44: Marketing | O44: NPV | V44: Definition | X44: N/A | Y44: N/A | AA44: ="FY"&IF(OR(X44="Oct",X44="Nov",X44="Dec"),Y44+1,Y44) -> FYN/A | AB44: =RIGHT(AA44,2)*1 -> #VALUE!
H45: <Enter Name> | K45: NA | L45: NA | O45: MIRR (with TV) | X45: Def Exit Commt
H46: R&D | O46: NPV (with TV) | V46: Development | X46: N/A | Y46: N/A | AA46: ="FY"&IF(OR(X46="Oct",X46="Nov",X46="Dec"),Y46+1,Y46) -> FYN/A
H47: <Enter Name> | K47: NA | L47: NA | V47: Qualification | X47: N/A | Y47: N/A | AA47: ="FY"&IF(OR(X47="Oct",X47="Nov",X47="Dec"),Y47+1,Y47) -> FYN/A
H48: Operations | O48: Tax Rate | V48: Launch | X48: N/A | Y48: N/A | AA48: ="FY"&IF(OR(X48="Oct",X48="Nov",X48="Dec"),Y48+1,Y48) -> FYN/A | AB48: =RIGHT(AA48,2)*1 -> #VALUE!
H49: <Enter Name> | K49: NA | L49: NA | O49: Discount Rate
B54: Development
B56: Dates (Calendar Year):
D57: Mth | E57: Year
B58: Dev Exit Approved | D58: NA | E58: NA | G58: Provide when Development Exit was approved
F61: Sunk | G61: FY | H61: FY | I61: FY | J61: FY | K61: FY | L61: FY | M61: FY | N61: FY | O61: FY | P61: FY | Q61: FY | R61: FY | S61: FY | T61: FY | U61: FY | V61: FY | W61: FY | X61: FY | Y61: FY | Z61: FY | AA61: FY | AB61: FY | AC61: FY | AD61: FY | AE61: FY | AF61: FY | AG61: FY | AH61: FY | AI61: FY | AJ61: FYAA-FYBB | AK61: % Rev | AM61: FYAA-FYBB
B63: Incremental Revenue | F63: 0 | G63: 0 | H63: 0 | I63: 0 | J63: 0 | K63: 0 | L63: 0 | M63: 0 | N63: 0 | O63: 0 | P63: 0 | Q63: 0 | R63: 0 | S63: 0 | T63: 0 | U63: 0 | V63: 0 | W63: 0 | X63: 0 | Y63: 0 | Z63: 0 | AA63: 0 | AB63: 0 | AC63: 0 | AD63: 0 | AE63: 0 | AF63: 0 | AG63: 0 | AH63: 0 | AI63: 0 | AJ63: 0 | AM63: 0
B64: Growth % | G64: 0 | H64: 0 | I64: 0 | J64: 0 | K64: 0 | L64: 0 | M64: 0 | N64: 0 | O64: 0 | P64: 0 | Q64: 0 | R64: 0 | S64: 0 | T64: 0 | U64: 0 | V64: 0 | W64: 0 | X64: 0 | Y64: 0 | Z64: 0 | AA64: 0 | AB64: 0 | AC64: 0 | AD64: 0 | AE64: 0 | AF64: 0 | AG64: 0 | AH64: 0 | AI64: 0 | AJ64: 0 | AK64: 5 Yr CAGR
B65: Category Share | C65: Volume (units) | G65: 0 | H65: 0 | I65: 0 | J65: 0 | K65: 0 | L65: 0 | M65: 0 | N65: 0 | O65: 0 | P65: 0 | Q65: 0 | R65: 0 | S65: 0 | T65: 0 | U65: 0 | V65: 0 | W65: 0 | X65: 0 | Y65: 0 | Z65: 0 | AA65: 0 | AB65: 0 | AC65: 0 | AD65: 0 | AE65: 0 | AF65: 0 | AG65: 0 | AH65: 0 | AI65: 0 | AJ65: 0
B66: True Inc Rev (exc. Loss Avoid): PPD | G66: 0 | H66: 0 | I66: 0 | J66: 0 | K66: 0 | L66: 0 | M66: 0 | N66: 0 | O66: 0 | P66: 0 | Q66: 0 | R66: 0 | S66: 0 | T66: 0 | U66: 0 | V66: 0 | W66: 0 | X66: 0 | Y66: 0 | Z66: 0 | AA66: 0 | AB66: 0 | AC66: 0 | AD66: 0 | AE66: 0 | AF66: 0 | AG66: 0 | AH66: 0 | AI66: 0 | AJ66: 0 | AM66: 0
B67: Cost of Sales | F67: 0 | G67: 0 | H67: 0 | I67: 0 | J67: 0 | K67: 0 | L67: 0 | M67: 0 | N67: 0 | O67: 0 | P67: 0 | Q67: 0 | R67: 0 | S67: 0 | T67: 0 | U67: 0 | V67: 0 | W67: 0 | X67: 0 | Y67: 0 | Z67: 0 | AA67: 0 | AB67: 0 | AC67: 0 | AD67: 0 | AE67: 0 | AF67: 0 | AG67: 0 | AH67: 0 | AI67: 0 | AJ67: 0 | AK67: 0 | AM67: 0
B68: Depreciation | F68: 0 | G68: 0 | H68: 0 | I68: 0 | J68: 0 | K68: 0 | L68: 0 | M68: 0 | N68: 0 | O68: 0 | P68: 0 | Q68: 0 | R68: 0 | S68: 0 | T68: 0 | U68: 0 | V68: 0 | W68: 0 | X68: 0 | Y68: 0 | Z68: 0 | AA68: 0 | AB68: 0 | AC68: 0 | AD68: 0 | AE68: 0 | AF68: 0 | AG68: 0 | AH68: 0 | AI68: 0 | AJ68: 0 | AK68: 0 | AM68: 0
B69: Gross Profit | F69: 0 | G69: 0 | H69: 0 | I69: 0 | J69: 0 | K69: 0 | L69: 0 | M69: 0 | N69: 0 | O69: 0 | P69: 0 | Q69: 0 | R69: 0 | S69: 0 | T69: 0 | U69: 0 | V69: 0 | W69: 0 | X69: 0 | Y69: 0 | Z69: 0 | AA69: 0 | AB69: 0 | AC69: 0 | AD69: 0 | AE69: 0 | AF69: 0 | AG69: 0 | AH69: 0 | AI69: 0 | AJ69: 0 | AM69: 0
C70: % of Revenue | G70: 0 | H70: 0 | I70: 0 | J70: 0 | K70: 0 | L70: 0 | M70: 0 | N70: 0 | O70: 0 | P70: 0 | Q70: 0 | R70: 0 | S70: 0 | T70: 0 | U70: 0 | V70: 0 | W70: 0 | X70: 0 | Y70: 0 | Z70: 0 | AA70: 0 | AB70: 0 | AC70: 0 | AD70: 0 | AE70: 0 | AF70: 0 | AG70: 0 | AH70: 0 | AI70: 0 | AJ70: 0
B71: SSG&A | F71: 0 | G71: 0 | H71: 0 | I71: 0 | J71: 0 | K71: 0 | L71: 0 | M71: 0 | N71: 0 | O71: 0 | P71: 0 | Q71: 0 | R71: 0 | S71: 0 | T71: 0 | U71: 0 | V71: 0 | W71: 0 | X71: 0 | Y71: 0 | Z71: 0 | AA71: 0 | AB71: 0 | AC71: 0 | AD71: 0 | AE71: 0 | AF71: 0 | AG71: 0 | AH71: 0 | AI71: 0 | AJ71: 0 | AK71: 0 | AM71: 0
B72: R&D | F72: 0 | G72: 0 | H72: 0 | I72: 0 | J72: 0 | K72: 0 | L72: 0 | M72: 0 | N72: 0 | O72: 0 | P72: 0 | Q72: 0 | R72: 0 | S72: 0 | T72: 0 | U72: 0 | V72: 0 | W72: 0 | X72: 0 | Y72: 0 | Z72: 0 | AA72: 0 | AB72: 0 | AC72: 0 | AD72: 0 | AE72: 0 | AF72: 0 | AG72: 0 | AH72: 0 | AI72: 0 | AJ72: 0 | AK72: 0 | AM72: 0
B73: OIBT | F73: 0 | G73: 0 | H73: 0 | I73: 0 | J73: 0 | K73: 0 | L73: 0 | M73: 0 | N73: 0 | O73: 0 | P73: 0 | Q73: 0 | R73: 0 | S73: 0 | T73: 0 | U73: 0 | V73: 0 | W73: 0 | X73: 0 | Y73: 0 | Z73: 0 | AA73: 0 | AB73: 0 | AC73: 0 | AD73: 0 | AE73: 0 | AF73: 0 | AG73: 0 | AH73: 0 | AI73: 0 | AJ73: 0 | AM73: 0
C74: % of Revenue | G74: 0 | H74: 0 | I74: 0 | J74: 0 | K74: 0 | L74: 0 | M74: 0 | N74: 0 | O74: 0 | P74: 0 | Q74: 0 | R74: 0 | S74: 0 | T74: 0 | U74: 0 | V74: 0 | W74: 0 | X74: 0 | Y74: 0 | Z74: 0 | AA74: 0 | AB74: 0 | AC74: 0 | AD74: 0 | AE74: 0 | AF74: 0 | AG74: 0 | AH74: 0 | AI74: 0 | AJ74: 0
B75: Other (Inc) / Exp | F75: 0 | G75: 0 | H75: 0 | I75: 0 | J75: 0 | K75: 0 | L75: 0 | M75: 0 | N75: 0 | O75: 0 | P75: 0 | Q75: 0 | R75: 0 | S75: 0 | T75: 0 | U75: 0 | V75: 0 | W75: 0 | X75: 0 | Y75: 0 | Z75: 0 | AA75: 0 | AB75: 0 | AC75: 0 | AD75: 0 | AE75: 0 | AF75: 0 | AG75: 0 | AH75: 0 | AI75: 0 | AJ75: 0 | AK75: Tax Rate | AM75: 0
B76: Tax Exp / (Ben) | F76: 0 | G76: 0 | H76: 0 | I76: 0 | J76: 0 | K76: 0 | L76: 0 | M76: 0 | N76: 0 | O76: 0 | P76: 0 | Q76: 0 | R76: 0 | S76: 0 | T76: 0 | U76: 0 | V76: 0 | W76: 0 | X76: 0 | Y76: 0 | Z76: 0 | AA76: 0 | AB76: 0 | AC76: 0 | AD76: 0 | AE76: 0 | AF76: 0 | AG76: 0 | AH76: 0 | AI76: 0 | AJ76: 0 | AK76: 0 | AM76: 0
B77: Net Income | F77: 0 | G77: 0 | H77: 0 | I77: 0 | J77: 0 | K77: 0 | L77: 0 | M77: 0 | N77: 0 | O77: 0 | P77: 0 | Q77: 0 | R77: 0 | S77: 0 | T77: 0 | U77: 0 | V77: 0 | W77: 0 | X77: 0 | Y77: 0 | Z77: 0 | AA77: 0 | AB77: 0 | AC77: 0 | AD77: 0 | AE77: 0 | AF77: 0 | AG77: 0 | AH77: 0 | AI77: 0 | AJ77: 0 | AM77: 0
C78: % of Revenue | G78: 0 | H78: 0 | I78: 0 | J78: 0 | K78: 0 | L78: 0 | M78: 0 | N78: 0 | O78: 0 | P78: 0 | Q78: 0 | R78: 0 | S78: 0 | T78: 0 | U78: 0 | V78: 0 | W78: 0 | X78: 0 | Y78: 0 | Z78: 0 | AA78: 0 | AB78: 0 | AC78: 0 | AD78: 0 | AE78: 0 | AF78: 0 | AG78: 0 | AH78: 0 | AI78: 0 | AJ78: 0
B79: Capital | F79: 0 | G79: 0 | H79: 0 | I79: 0 | J79: 0 | K79: 0 | L79: 0 | M79: 0 | N79: 0 | O79: 0 | P79: 0 | Q79: 0 | R79: 0 | S79: 0 | T79: 0 | U79: 0 | V79: 0 | W79: 0 | X79: 0 | Y79: 0 | Z79: 0 | AA79: 0 | AB79: 0 | AC79: 0 | AD79: 0 | AE79: 0 | AF79: 0 | AG79: 0 | AH79: 0 | AI79: 0 | AJ79: 0 | AK79: 0 | AM79: 0
B80: Increase in Working Capital | F80: 0 | G80: 0 | H80: 0 | I80: 0 | J80: 0 | K80: 0 | L80: 0 | M80: 0 | N80: 0 | O80: 0 | P80: 0 | Q80: 0 | R80: 0 | S80: 0 | T80: 0 | U80: 0 | V80: 0 | W80: 0 | X80: 0 | Y80: 0 | Z80: 0 | AA80: 0 | AB80: 0 | AC80: 0 | AD80: 0 | AE80: 0 | AF80: 0 | AG80: 0 | AH80: 0 | AI80: 0 | AJ80: 0 | AK80: 0 | AM80: 0
B81: Free Cash Flow* | F81: 0 | G81: 0 | H81: 0 | I81: 0 | J81: 0 | K81: 0 | L81: 0 | M81: 0 | N81: 0 | O81: 0 | P81: 0 | Q81: 0 | R81: 0 | S81: 0 | T81: 0 | U81: 0 | V81: 0 | W81: 0 | X81: 0 | Y81: 0 | Z81: 0 | AA81: 0 | AB81: 0 | AC81: 0 | AD81: 0 | AE81: 0 | AF81: 0 | AG81: 0 | AH81: 0 | AI81: 0 | AJ81: 0 | AM81: 0
C82: % of Revenue | G82: 0 | H82: 0 | I82: 0 | J82: 0 | K82: 0 | L82: 0 | M82: 0 | N82: 0 | O82: 0 | P82: 0 | Q82: 0 | R82: 0 | S82: 0 | T82: 0 | U82: 0 | V82: 0 | W82: 0 | X82: 0 | Y82: 0 | Z82: 0 | AA82: 0 | AB82: 0 | AC82: 0 | AD82: 0 | AE82: 0 | AF82: 0 | AG82: 0 | AH82: 0 | AI82: 0 | AJ82: 0
H86: Dev Exit Approvers and Dates: | O86: Fwd Look (as of Dev Exit) | V86: Actual / Expected Exit GPDS Phases, as project exited Qualification
H87: Name and Last Review Date (Calendar Year) | Q87: 10 Yrs | R87: 15 Yrs
H88: Finance | K88: Mth | L88: Year | Q88: FY XX-YY | R88: FY XX-YY | V88: Dates (Calendar Year) | X88: Mth | Y88: Year
H89: <Enter Name> | K89: NA | L89: NA | O89: MIRR | V89: Concept | X89: NA | Y89: NA
H90: Marketing | O90: NPV | V90: Definition | X90: NA | Y90: NA
H91: <Enter Name> | K91: NA | L91: NA | O91: MIRR (with TV)
H92: R&D | O92: NPV (with TV) | V92: Development | X92: NA | Y92: NA
H93: <Enter Name> | K93: NA | L93: NA | V93: Qualification | X93: NA | Y93: NA
H94: Operations | O94: Tax Rate | V94: Launch | X94: NA | Y94: NA
H95: <Enter Name> | K95: NA | L95: NA | O95: Discount Rate
B100: Qualification
B102: Dates (Calendar Year):
D103: Mth | E103: Year
B104: Qual Exit Approved | D104: NA | E104: NA | G104: Provide when Qualification Exit was approved
F107: Sunk | G107: FY | H107: FY | I107: FY | J107: FY | K107: FY | L107: FY | M107: FY | N107: FY | O107: FY | P107: FY | Q107: FY | R107: FY | S107: FY | T107: FY | U107: FY | V107: FY | W107: FY | X107: FY | Y107: FY | Z107: FY | AA107: FY | AB107: FY | AC107: FY | AD107: FY | AE107: FY | AF107: FY | AG107: FY | AH107: FY | AI107: FY | AJ107: FYAA-FYBB | AK107: % Rev | AM107: FYAA-FYBB
B109: Incremental Revenue | F109: 0 | G109: 0 | H109: 0 | I109: 0 | J109: 0 | K109: 0 | L109: 0 | M109: 0 | N109: 0 | O109: 0 | P109: 0 | Q109: 0 | R109: 0 | S109: 0 | T109: 0 | U109: 0 | V109: 0 | W109: 0 | X109: 0 | Y109: 0 | Z109: 0 | AA109: 0 | AB109: 0 | AC109: 0 | AD109: 0 | AE109: 0 | AF109: 0 | AG109: 0 | AH109: 0 | AI109: 0 | AJ109: 0 | AM109: 0
B110: Growth % | G110: 0 | H110: 0 | I110: 0 | J110: 0 | K110: 0 | L110: 0 | M110: 0 | N110: 0 | O110: 0 | P110: 0 | Q110: 0 | R110: 0 | S110: 0 | T110: 0 | U110: 0 | V110: 0 | W110: 0 | X110: 0 | Y110: 0 | Z110: 0 | AA110: 0 | AB110: 0 | AC110: 0 | AD110: 0 | AE110: 0 | AF110: 0 | AG110: 0 | AH110: 0 | AI110: 0 | AJ110: 0 | AK110: 5 Yr CAGR
B111: Category Share | C111: Volume (units) | G111: 0 | H111: 0 | I111: 0 | J111: 0 | K111: 0 | L111: 0 | M111: 0 | N111: 0 | O111: 0 | P111: 0 | Q111: 0 | R111: 0 | S111: 0 | T111: 0 | U111: 0 | V111: 0 | W111: 0 | X111: 0 | Y111: 0 | Z111: 0 | AA111: 0 | AB111: 0 | AC111: 0 | AD111: 0 | AE111: 0 | AF111: 0 | AG111: 0 | AH111: 0 | AI111: 0 | AJ111: 0
B112: True Inc Rev (exc. Loss Avoid): PPD | G112: 0 | H112: 0 | I112: 0 | J112: 0 | K112: 0 | L112: 0 | M112: 0 | N112: 0 | O112: 0 | P112: 0 | Q112: 0 | R112: 0 | S112: 0 | T112: 0 | U112: 0 | V112: 0 | W112: 0 | X112: 0 | Y112: 0 | Z112: 0 | AA112: 0 | AB112: 0 | AC112: 0 | AD112: 0 | AE112: 0 | AF112: 0 | AG112: 0 | AH112: 0 | AI112: 0 | AJ112: 0 | AM112: 0
B113: Cost of Sales | F113: 0 | G113: 0 | H113: 0 | I113: 0 | J113: 0 | K113: 0 | L113: 0 | M113: 0 | N113: 0 | O113: 0 | P113: 0 | Q113: 0 | R113: 0 | S113: 0 | T113: 0 | U113: 0 | V113: 0 | W113: 0 | X113: 0 | Y113: 0 | Z113: 0 | AA113: 0 | AB113: 0 | AC113: 0 | AD113: 0 | AE113: 0 | AF113: 0 | AG113: 0 | AH113: 0 | AI113: 0 | AJ113: 0 | AK113: 0 | AM113: 0
B114: Depreciation | F114: 0 | G114: 0 | H114: 0 | I114: 0 | J114: 0 | K114: 0 | L114: 0 | M114: 0 | N114: 0 | O114: 0 | P114: 0 | Q114: 0 | R114: 0 | S114: 0 | T114: 0 | U114: 0 | V114: 0 | W114: 0 | X114: 0 | Y114: 0 | Z114: 0 | AA114: 0 | AB114: 0 | AC114: 0 | AD114: 0 | AE114: 0 | AF114: 0 | AG114: 0 | AH114: 0 | AI114: 0 | AJ114: 0 | AK114: 0 | AM114: 0
B115: Gross Profit | F115: 0 | G115: 0 | H115: 0 | I115: 0 | J115: 0 | K115: 0 | L115: 0 | M115: 0 | N115: 0 | O115: 0 | P115: 0 | Q115: 0 | R115: 0 | S115: 0 | T115: 0 | U115: 0 | V115: 0 | W115: 0 | X115: 0 | Y115: 0 | Z115: 0 | AA115: 0 | AB115: 0 | AC115: 0 | AD115: 0 | AE115: 0 | AF115: 0 | AG115: 0 | AH115: 0 | AI115: 0 | AJ115: 0 | AM115: 0
C116: % of Revenue | G116: 0 | H116: 0 | I116: 0 | J116: 0 | K116: 0 | L116: 0 | M116: 0 | N116: 0 | O116: 0 | P116: 0 | Q116: 0 | R116: 0 | S116: 0 | T116: 0 | U116: 0 | V116: 0 | W116: 0 | X116: 0 | Y116: 0 | Z116: 0 | AA116: 0 | AB116: 0 | AC116: 0 | AD116: 0 | AE116: 0 | AF116: 0 | AG116: 0 | AH116: 0 | AI116: 0 | AJ116: 0
B117: SSG&A | F117: 0 | G117: 0 | H117: 0 | I117: 0 | J117: 0 | K117: 0 | L117: 0 | M117: 0 | N117: 0 | O117: 0 | P117: 0 | Q117: 0 | R117: 0 | S117: 0 | T117: 0 | U117: 0 | V117: 0 | W117: 0 | X117: 0 | Y117: 0 | Z117: 0 | AA117: 0 | AB117: 0 | AC117: 0 | AD117: 0 | AE117: 0 | AF117: 0 | AG117: 0 | AH117: 0 | AI117: 0 | AJ117: 0 | AK117: 0 | AM117: 0
B118: R&D | F118: 0 | G118: 0 | H118: 0 | I118: 0 | J118: 0 | K118: 0 | L118: 0 | M118: 0 | N118: 0 | O118: 0 | P118: 0 | Q118: 0 | R118: 0 | S118: 0 | T118: 0 | U118: 0 | V118: 0 | W118: 0 | X118: 0 | Y118: 0 | Z118: 0 | AA118: 0 | AB118: 0 | AC118: 0 | AD118: 0 | AE118: 0 | AF118: 0 | AG118: 0 | AH118: 0 | AI118: 0 | AJ118: 0 | AK118: 0 | AM118: 0
B119: OIBT | F119: 0 | G119: 0 | H119: 0 | I119: 0 | J119: 0 | K119: 0 | L119: 0 | M119: 0 | N119: 0 | O119: 0 | P119: 0 | Q119: 0 | R119: 0 | S119: 0 | T119: 0 | U119: 0 | V119: 0 | W119: 0 | X119: 0 | Y119: 0 | Z119: 0 | AA119: 0 | AB119: 0 | AC119: 0 | AD119: 0 | AE119: 0 | AF119: 0 | AG119: 0 | AH119: 0 | AI119: 0 | AJ119: 0 | AM119: 0
C120: % of Revenue | G120: 0 | H120: 0 | I120: 0 | J120: 0 | K120: 0 | L120: 0 | M120: 0 | N120: 0 | O120: 0 | P120: 0 | Q120: 0 | R120: 0 | S120: 0 | T120: 0 | U120: 0 | V120: 0 | W120: 0 | X120: 0 | Y120: 0 | Z120: 0 | AA120: 0 | AB120: 0 | AC120: 0 | AD120: 0 | AE120: 0 | AF120: 0 | AG120: 0 | AH120: 0 | AI120: 0 | AJ120: 0
B121: Other (Inc) / Exp | F121: 0 | G121: 0 | H121: 0 | I121: 0 | J121: 0 | K121: 0 | L121: 0 | M121: 0 | N121: 0 | O121: 0 | P121: 0 | Q121: 0 | R121: 0 | S121: 0 | T121: 0 | U121: 0 | V121: 0 | W121: 0 | X121: 0 | Y121: 0 | Z121: 0 | AA121: 0 | AB121: 0 | AC121: 0 | AD121: 0 | AE121: 0 | AF121: 0 | AG121: 0 | AH121: 0 | AI121: 0 | AJ121: 0 | AK121: Tax Rate | AM121: 0
B122: Tax Exp / (Ben) | F122: 0 | G122: 0 | H122: 0 | I122: 0 | J122: 0 | K122: 0 | L122: 0 | M122: 0 | N122: 0 | O122: 0 | P122: 0 | Q122: 0 | R122: 0 | S122: 0 | T122: 0 | U122: 0 | V122: 0 | W122: 0 | X122: 0 | Y122: 0 | Z122: 0 | AA122: 0 | AB122: 0 | AC122: 0 | AD122: 0 | AE122: 0 | AF122: 0 | AG122: 0 | AH122: 0 | AI122: 0 | AJ122: 0 | AK122: 0 | AM122: 0
B123: Net Income | F123: 0 | G123: 0 | H123: 0 | I123: 0 | J123: 0 | K123: 0 | L123: 0 | M123: 0 | N123: 0 | O123: 0 | P123: 0 | Q123: 0 | R123: 0 | S123: 0 | T123: 0 | U123: 0 | V123: 0 | W123: 0 | X123: 0 | Y123: 0 | Z123: 0 | AA123: 0 | AB123: 0 | AC123: 0 | AD123: 0 | AE123: 0 | AF123: 0 | AG123: 0 | AH123: 0 | AI123: 0 | AJ123: 0 | AM123: 0
C124: % of Revenue | G124: 0 | H124: 0 | I124: 0 | J124: 0 | K124: 0 | L124: 0 | M124: 0 | N124: 0 | O124: 0 | P124: 0 | Q124: 0 | R124: 0 | S124: 0 | T124: 0 | U124: 0 | V124: 0 | W124: 0 | X124: 0 | Y124: 0 | Z124: 0 | AA124: 0 | AB124: 0 | AC124: 0 | AD124: 0 | AE124: 0 | AF124: 0 | AG124: 0 | AH124: 0 | AI124: 0 | AJ124: 0
B125: Capital | F125: 0 | G125: 0 | H125: 0 | I125: 0 | J125: 0 | K125: 0 | L125: 0 | M125: 0 | N125: 0 | O125: 0 | P125: 0 | Q125: 0 | R125: 0 | S125: 0 | T125: 0 | U125: 0 | V125: 0 | W125: 0 | X125: 0 | Y125: 0 | Z125: 0 | AA125: 0 | AB125: 0 | AC125: 0 | AD125: 0 | AE125: 0 | AF125: 0 | AG125: 0 | AH125: 0 | AI125: 0 | AJ125: 0 | AK125: 0 | AM125: 0
B126: Increase in Working Capital | F126: 0 | G126: 0 | H126: 0 | I126: 0 | J126: 0 | K126: 0 | L126: 0 | M126: 0 | N126: 0 | O126: 0 | P126: 0 | Q126: 0 | R126: 0 | S126: 0 | T126: 0 | U126: 0 | V126: 0 | W126: 0 | X126: 0 | Y126: 0 | Z126: 0 | AA126: 0 | AB126: 0 | AC126: 0 | AD126: 0 | AE126: 0 | AF126: 0 | AG126: 0 | AH126: 0 | AI126: 0 | AJ126: 0 | AK126: 0 | AM126: 0
B127: Free Cash Flow* | F127: 0 | G127: 0 | H127: 0 | I127: 0 | J127: 0 | K127: 0 | L127: 0 | M127: 0 | N127: 0 | O127: 0 | P127: 0 | Q127: 0 | R127: 0 | S127: 0 | T127: 0 | U127: 0 | V127: 0 | W127: 0 | X127: 0 | Y127: 0 | Z127: 0 | AA127: 0 | AB127: 0 | AC127: 0 | AD127: 0 | AE127: 0 | AF127: 0 | AG127: 0 | AH127: 0 | AI127: 0 | AJ127: 0 | AM127: 0
C128: % of Revenue | G128: 0 | H128: 0 | I128: 0 | J128: 0 | K128: 0 | L128: 0 | M128: 0 | N128: 0 | O128: 0 | P128: 0 | Q128: 0 | R128: 0 | S128: 0 | T128: 0 | U128: 0 | V128: 0 | W128: 0 | X128: 0 | Y128: 0 | Z128: 0 | AA128: 0 | AB128: 0 | AC128: 0 | AD128: 0 | AE128: 0 | AF128: 0 | AG128: 0 | AH128: 0 | AI128: 0 | AJ128: 0
H132: Qual Exit Approvers and Dates: | O132: Fwd Look (as of Qual Exit) | V132: Actual / Expected Exit GPDS Phases, as project exited Qualification
...

Sheet Capital_Dep
B2: Capital and Depreciation: Actual / Projections | AN2: ="Capital and Depreciation: "&Comp -> Capital and Depreciation: Def Exit
H4: =ProjStartFY -> 18 | I4: =ProjStartFY+1 -> 19 | J4: =ProjStartFY+2 -> 20 | K4: =ProjStartFY+3 -> 21 | L4: =ProjStartFY+4 -> 22 | M4: =ProjStartFY+5 -> 23 | N4: =ProjStartFY+6 -> 24 | O4: =ProjStartFY+7 -> 25 | P4: =ProjStartFY+8 -> 26 | Q4: =ProjStartFY+9 -> 27 | R4: =ProjStartFY+10 -> 28 | S4: =ProjStartFY+11 -> 29 | T4: =ProjStartFY+12 -> 30 | U4: =ProjStartFY+13 -> 31 | V4: =ProjStartFY+14 -> 32 | W4: =ProjStartFY+15 -> 33 | X4: =ProjStartFY+16 -> 34 | Y4: =ProjStartFY+17 -> 35 | Z4: =ProjStartFY+18 -> 36 | AA4: =ProjStartFY+19 -> 37 | AB4: =ProjStartFY+20 -> 38 | AC4: =ProjStartFY+21 -> 39 | AD4: =ProjStartFY+22 -> 40 | AE4: =ProjStartFY+23 -> 41 | AF4: =ProjStartFY+24 -> 42 | AG4: =ProjStartFY+25 -> 43 | AH4: =ProjStartFY+26 -> 44 | AI4: =ProjStartFY+27 -> 45 | AJ4: =ProjStartFY+28 -> 46 | AT4: =ProjStartFY -> 18 | AU4: =ProjStartFY+1 -> 19 | AV4: =ProjStartFY+2 -> 20 | AW4: =ProjStartFY+3 -> 21 | AX4: =ProjStartFY+4 -> 22 | AY4: =ProjStartFY+5 -> 23 | AZ4: =ProjStartFY+6 -> 24 | BA4: =ProjStartFY+7 -> 25 | BB4: =ProjStartFY+8 -> 26 | BC4: =ProjStartFY+9 -> 27 | BD4: =ProjStartFY+10 -> 28 | BE4: =ProjStartFY+11 -> 29 | BF4: =ProjStartFY+12 -> 30 | BG4: =ProjStartFY+13 -> 31 | BH4: =ProjStartFY+14 -> 32 | BI4: =ProjStartFY+15 -> 33 | BJ4: =ProjStartFY+16 -> 34 | BK4: =ProjStartFY+17 -> 35 | BL4: =ProjStartFY+18 -> 36 | BM4: =ProjStartFY+19 -> 37 | BN4: =ProjStartFY+20 -> 38 | BO4: =ProjStartFY+21 -> 39 | BP4: =ProjStartFY+22 -> 40 | BQ4: =ProjStartFY+23 -> 41 | BR4: =ProjStartFY+24 -> 42 | BS4: =ProjStartFY+25 -> 43 | BT4: =ProjStartFY+26 -> 44 | BU4: =ProjStartFY+27 -> 45 | BV4: =ProjStartFY+28 -> 46
B5: Item | C5: Capital Requirements | D5: Asset Useful Life (years) | E5: Service Mth | F5: Service Year | G5: FY | H5: ="FY"&ProjStartFY -> FY18 | I5: ="FY"&ProjStartFY+1 -> FY19 | J5: ="FY"&ProjStartFY+2 -> FY20 | K5: ="FY"&ProjStartFY+3 -> FY21 | L5: ="FY"&ProjStartFY+4 -> FY22 | M5: ="FY"&ProjStartFY+5 -> FY23 | N5: ="FY"&ProjStartFY+6 -> FY24 | O5: ="FY"&ProjStartFY+7 -> FY25 | P5: ="FY"&ProjStartFY+8 -> FY26 | Q5: ="FY"&ProjStartFY+9 -> FY27 | R5: ="FY"&ProjStartFY+10 -> FY28 | S5: ="FY"&ProjStartFY+11 -> FY29 | T5: ="FY"&ProjStartFY+12 -> FY30 | U5: ="FY"&ProjStartFY+13 -> FY31 | V5: ="FY"&ProjStartFY+14 -> FY32 | W5: ="FY"&ProjStartFY+15 -> FY33 | X5: ="FY"&ProjStartFY+16 -> FY34 | Y5: ="FY"&ProjStartFY+17 -> FY35 | Z5: ="FY"&ProjStartFY+18 -> FY36 | AA5: ="FY"&ProjStartFY+19 -> FY37 | AB5: ="FY"&ProjStartFY+20 -> FY38 | AC5: ="FY"&ProjStartFY+21 -> FY39 | AD5: ="FY"&ProjStartFY+22 -> FY40 | AE5: ="FY"&ProjStartFY+23 -> FY41 | AF5: ="FY"&ProjStartFY+24 -> FY42 | AG5: ="FY"&ProjStartFY+25 -> FY43 | AH5: ="FY"&ProjStartFY+26 -> FY44 | AI5: ="FY"&ProjStartFY+27 -> FY45 | AJ5: ="FY"&ProjStartFY+28 -> FY46 | AK5: Total | AN5: Item | AO5: Capital Requirements | AP5: Asset Useful Life (years) | AQ5: Service Mth | AR5: Service Year | AS5: FY | AT5: ="FY"&ProjStartFY -> FY18 | AU5: ="FY"&ProjStartFY+1 -> FY19 | AV5: ="FY"&ProjStartFY+2 -> FY20 | AW5: ="FY"&ProjStartFY+3 -> FY21 | AX5: ="FY"&ProjStartFY+4 -> FY22 | AY5: ="FY"&ProjStartFY+5 -> FY23 | AZ5: ="FY"&ProjStartFY+6 -> FY24 | BA5: ="FY"&ProjStartFY+7 -> FY25 | BB5: ="FY"&ProjStartFY+8 -> FY26 | BC5: ="FY"&ProjStartFY+9 -> FY27 | BD5: ="FY"&ProjStartFY+10 -> FY28 | BE5: ="FY"&ProjStartFY+11 -> FY29 | BF5: ="FY"&ProjStartFY+12 -> FY30 | BG5: ="FY"&ProjStartFY+13 -> FY31 | BH5: ="FY"&ProjStartFY+14 -> FY32 | BI5: ="FY"&ProjStartFY+15 -> FY33 | BJ5: ="FY"&ProjStartFY+16 -> FY34 | BK5: ="FY"&ProjStartFY+17 -> FY35 | BL5: ="FY"&ProjStartFY+18 -> FY36 | BM5: ="FY"&ProjStartFY+19 -> FY37 | BN5: ="FY"&ProjStartFY+20 -> FY38 | BO5: ="FY"&ProjStartFY+21 -> FY39 | BP5: ="FY"&ProjStartFY+22 -> FY40 | BQ5: ="FY"&ProjStartFY+23 -> FY41 | BR5: ="FY"&ProjStartFY+24 -> FY42 | BS5: ="FY"&ProjStartFY+25 -> FY43 | BT5: ="FY"&ProjStartFY+26 -> FY44 | BU5: ="FY"&ProjStartFY+27 -> FY45 | BV5: ="FY"&ProjStartFY+28 -> FY46 | BW5: Total
B6: 1 | E6: N/A | F6: N/A | G6: =IF(OR(E6="N/A",F6="N/A"),0,IF(OR(E6="Oct",E6="Nov",E6="Dec"),F6+1,F6)) -> 0 | AK6: =SUM(H6:AJ6) -> 0 | AN6: 1 | AO6: AAA - Assembly Line | AQ6: N/A | AR6: N/A | AS6: =IF(OR(AQ6="N/A",AR6="N/A"),0,IF(OR(AQ6="Oct",AQ6="Nov",AQ6="Dec"),AR6+1,AR6)) -> 0 | BW6: =SUM(AT6:BV6) -> 0
B7: =B6+1 -> 2 | E7: N/A | F7: N/A | G7: =IF(OR(E7="N/A",F7="N/A"),0,IF(OR(E7="Oct",E7="Nov",E7="Dec"),F7+1,F7)) -> 0 | AK7: =SUM(H7:AJ7) -> 0 | AN7: =AN6+1 -> 2 | AQ7: N/A | AR7: N/A | AS7: =IF(OR(AQ7="N/A",AR7="N/A"),0,IF(OR(AQ7="Oct",AQ7="Nov",AQ7="Dec"),AR7+1,AR7)) -> 0 | BW7: =SUM(AT7:BV7) -> 0
B8: =B7+1 -> 3 | E8: N/A | F8: N/A | G8: =IF(OR(E8="N/A",F8="N/A"),0,IF(OR(E8="Oct",E8="Nov",E8="Dec"),F8+1,F8)) -> 0 | AK8: =SUM(H8:AJ8) -> 0 | AN8: =AN7+1 -> 3 | AQ8: N/A | AR8: N/A | AS8: =IF(OR(AQ8="N/A",AR8="N/A"),0,IF(OR(AQ8="Oct",AQ8="Nov",AQ8="Dec"),AR8+1,AR8)) -> 0 | BW8: =SUM(AT8:BV8) -> 0
B9: =B8+1 -> 4 | E9: N/A | F9: N/A | G9: =IF(OR(E9="N/A",F9="N/A"),0,IF(OR(E9="Oct",E9="Nov",E9="Dec"),F9+1,F9)) -> 0 | AK9: =SUM(H9:AJ9) -> 0 | AN9: =AN8+1 -> 4 | AQ9: N/A | AR9: N/A | AS9: =IF(OR(AQ9="N/A",AR9="N/A"),0,IF(OR(AQ9="Oct",AQ9="Nov",AQ9="Dec"),AR9+1,AR9)) -> 0 | BW9: =SUM(AT9:BV9) -> 0
B10: =B9+1 -> 5 | E10: N/A | F10: N/A | G10: =IF(OR(E10="N/A",F10="N/A"),0,IF(OR(E10="Oct",E10="Nov",E10="Dec"),F10+1,F10)) -> 0 | AK10: =SUM(H10:AJ10) -> 0 | AN10: =AN9+1 -> 5 | AQ10: N/A | AR10: N/A | AS10: =IF(OR(AQ10="N/A",AR10="N/A"),0,IF(OR(AQ10="Oct",AQ10="Nov",AQ10="Dec"),AR10+1,AR10)) -> 0 | BW10: =SUM(AT10:BV10) -> 0
B11: =B10+1 -> 6 | E11: N/A | F11: N/A | G11: =IF(OR(E11="N/A",F11="N/A"),0,IF(OR(E11="Oct",E11="Nov",E11="Dec"),F11+1,F11)) -> 0 | AK11: =SUM(H11:AJ11) -> 0 | AN11: =AN10+1 -> 6 | AQ11: N/A | AR11: N/A | AS11: =IF(OR(AQ11="N/A",AR11="N/A"),0,IF(OR(AQ11="Oct",AQ11="Nov",AQ11="Dec"),AR11+1,AR11)) -> 0 | BW11: =SUM(AT11:BV11) -> 0
B12: =B11+1 -> 7 | E12: N/A | F12: N/A | G12: =IF(OR(E12="N/A",F12="N/A"),0,IF(OR(E12="Oct",E12="Nov",E12="Dec"),F12+1,F12)) -> 0 | AK12: =SUM(H12:AJ12) -> 0 | AN12: =AN11+1 -> 7 | AQ12: N/A | AR12: N/A | AS12: =IF(OR(AQ12="N/A",AR12="N/A"),0,IF(OR(AQ12="Oct",AQ12="Nov",AQ12="Dec"),AR12+1,AR12)) -> 0 | BW12: =SUM(AT12:BV12) -> 0
B13: =B12+1 -> 8 | E13: N/A | F13: N/A | G13: =IF(OR(E13="N/A",F13="N/A"),0,IF(OR(E13="Oct",E13="Nov",E13="Dec"),F13+1,F13)) -> 0 | AK13: =SUM(H13:AJ13) -> 0 | AN13: =AN12+1 -> 8 | AQ13: N/A | AR13: N/A | AS13: =IF(OR(AQ13="N/A",AR13="N/A"),0,IF(OR(AQ13="Oct",AQ13="Nov",AQ13="Dec"),AR13+1,AR13)) -> 0 | BW13: =SUM(AT13:BV13) -> 0
B14: =B13+1 -> 9 | E14: N/A | F14: N/A | G14: =IF(OR(E14="N/A",F14="N/A"),0,IF(OR(E14="Oct",E14="Nov",E14="Dec"),F14+1,F14)) -> 0 | AK14: =SUM(H14:AJ14) -> 0 | AN14: =AN13+1 -> 9 | AQ14: N/A | AR14: N/A | AS14: =IF(OR(AQ14="N/A",AR14="N/A"),0,IF(OR(AQ14="Oct",AQ14="Nov",AQ14="Dec"),AR14+1,AR14)) -> 0 | BW14: =SUM(AT14:BV14) -> 0
B15: =B14+1 -> 10 | C15: JJJ | E15: N/A | F15: N/A | G15: =IF(OR(E15="N/A",F15="N/A"),0,IF(OR(E15="Oct",E15="Nov",E15="Dec"),F15+1,F15)) -> 0 | AK15: =SUM(H15:AJ15) -> 0 | AN15: =AN14+1 -> 10 | AQ15: N/A | AR15: N/A | AS15: =IF(OR(AQ15="N/A",AR15="N/A"),0,IF(OR(AQ15="Oct",AQ15="Nov",AQ15="Dec"),AR15+1,AR15)) -> 0 | BW15: =SUM(AT15:BV15) -> 0
B16: =B15+1 -> 11 | C16: KKK | E16: N/A | F16: N/A | G16: =IF(OR(E16="N/A",F16="N/A"),0,IF(OR(E16="Oct",E16="Nov",E16="Dec"),F16+1,F16)) -> 0 | AK16: =SUM(H16:AJ16) -> 0 | AN16: =AN15+1 -> 11 | AQ16: N/A | AR16: N/A | AS16: =IF(OR(AQ16="N/A",AR16="N/A"),0,IF(OR(AQ16="Oct",AQ16="Nov",AQ16="Dec"),AR16+1,AR16)) -> 0 | BW16: =SUM(AT16:BV16) -> 0
B17: =B16+1 -> 12 | C17: LLL | E17: N/A | F17: N/A | G17: =IF(OR(E17="N/A",F17="N/A"),0,IF(OR(E17="Oct",E17="Nov",E17="Dec"),F17+1,F17)) -> 0 | AK17: =SUM(H17:AJ17) -> 0 | AN17: =AN16+1 -> 12 | AO17: LLL | AQ17: N/A | AR17: N/A | AS17: =IF(OR(AQ17="N/A",AR17="N/A"),0,IF(OR(AQ17="Oct",AQ17="Nov",AQ17="Dec"),AR17+1,AR17)) -> 0 | BW17: =SUM(AT17:BV17) -> 0
B18: =B17+1 -> 13 | C18: MMM | E18: N/A | F18: N/A | G18: =IF(OR(E18="N/A",F18="N/A"),0,IF(OR(E18="Oct",E18="Nov",E18="Dec"),F18+1,F18)) -> 0 | AK18: =SUM(H18:AJ18) -> 0 | AN18: =AN17+1 -> 13 | AO18: MMM | AQ18: N/A | AR18: N/A | AS18: =IF(OR(AQ18="N/A",AR18="N/A"),0,IF(OR(AQ18="Oct",AQ18="Nov",AQ18="Dec"),AR18+1,AR18)) -> 0 | BW18: =SUM(AT18:BV18) -> 0
B19: =B18+1 -> 14 | C19: NNN | E19: N/A | F19: N/A | G19: =IF(OR(E19="N/A",F19="N/A"),0,IF(OR(E19="Oct",E19="Nov",E19="Dec"),F19+1,F19)) -> 0 | AK19: =SUM(H19:AJ19) -> 0 | AN19: =AN18+1 -> 14 | AO19: NNN | AQ19: N/A | AR19: N/A | AS19: =IF(OR(AQ19="N/A",AR19="N/A"),0,IF(OR(AQ19="Oct",AQ19="Nov",AQ19="Dec"),AR19+1,AR19)) -> 0 | BW19: =SUM(AT19:BV19) -> 0
B20: =B19+1 -> 15 | C20: OOO | E20: N/A | F20: N/A | G20: =IF(OR(E20="N/A",F20="N/A"),0,IF(OR(E20="Oct",E20="Nov",E20="Dec"),F20+1,F20)) -> 0 | AK20: =SUM(H20:AJ20) -> 0 | AN20: =AN19+1 -> 15 | AO20: OOO | AQ20: N/A | AR20: N/A | AS20: =IF(OR(AQ20="N/A",AR20="N/A"),0,IF(OR(AQ20="Oct",AQ20="Nov",AQ20="Dec"),AR20+1,AR20)) -> 0 | BW20: =SUM(AT20:BV20) -> 0
B21: =B20+1 -> 16 | C21: PPP | E21: N/A | F21: N/A | G21: =IF(OR(E21="N/A",F21="N/A"),0,IF(OR(E21="Oct",E21="Nov",E21="Dec"),F21+1,F21)) -> 0 | AK21: =SUM(H21:AJ21) -> 0 | AN21: =AN20+1 -> 16 | AO21: PPP | AQ21: N/A | AR21: N/A | AS21: =IF(OR(AQ21="N/A",AR21="N/A"),0,IF(OR(AQ21="Oct",AQ21="Nov",AQ21="Dec"),AR21+1,AR21)) -> 0 | BW21: =SUM(AT21:BV21) -> 0
B22: =B21+1 -> 17 | C22: QQQ | E22: N/A | F22: N/A | G22: =IF(OR(E22="N/A",F22="N/A"),0,IF(OR(E22="Oct",E22="Nov",E22="Dec"),F22+1,F22)) -> 0 | AK22: =SUM(H22:AJ22) -> 0 | AN22: =AN21+1 -> 17 | AO22: QQQ | AQ22: N/A | AR22: N/A | AS22: =IF(OR(AQ22="N/A",AR22="N/A"),0,IF(OR(AQ22="Oct",AQ22="Nov",AQ22="Dec"),AR22+1,AR22)) -> 0 | BW22: =SUM(AT22:BV22) -> 0
B23: =B22+1 -> 18 | C23: RRR | E23: N/A | F23: N/A | G23: =IF(OR(E23="N/A",F23="N/A"),0,IF(OR(E23="Oct",E23="Nov",E23="Dec"),F23+1,F23)) -> 0 | AK23: =SUM(H23:AJ23) -> 0 | AN23: =AN22+1 -> 18 | AO23: RRR | AQ23: N/A | AR23: N/A | AS23: =IF(OR(AQ23="N/A",AR23="N/A"),0,IF(OR(AQ23="Oct",AQ23="Nov",AQ23="Dec"),AR23+1,AR23)) -> 0 | BW23: =SUM(AT23:BV23) -> 0
B24: =B23+1 -> 19 | C24: SSS | E24: N/A | F24: N/A | G24: =IF(OR(E24="N/A",F24="N/A"),0,IF(OR(E24="Oct",E24="Nov",E24="Dec"),F24+1,F24)) -> 0 | AK24: =SUM(H24:AJ24) -> 0 | AN24: =AN23+1 -> 19 | AO24: SSS | AQ24: N/A | AR24: N/A | AS24: =IF(OR(AQ24="N/A",AR24="N/A"),0,IF(OR(AQ24="Oct",AQ24="Nov",AQ24="Dec"),AR24+1,AR24)) -> 0 | BW24: =SUM(AT24:BV24) -> 0
B25: =B24+1 -> 20 | C25: TTT | E25: N/A | F25: N/A | G25: =IF(OR(E25="N/A",F25="N/A"),0,IF(OR(E25="Oct",E25="Nov",E25="Dec"),F25+1,F25)) -> 0 | AK25: =SUM(H25:AJ25) -> 0 | AN25: =AN24+1 -> 20 | AO25: TTT | AQ25: N/A | AR25: N/A | AS25: =IF(OR(AQ25="N/A",AR25="N/A"),0,IF(OR(AQ25="Oct",AQ25="Nov",AQ25="Dec"),AR25+1,AR25)) -> 0 | BW25: =SUM(AT25:BV25) -> 0
B26: =B25+1 -> 21 | C26: UUU | E26: N/A | F26: N/A | G26: =IF(OR(E26="N/A",F26="N/A"),0,IF(OR(E26="Oct",E26="Nov",E26="Dec"),F26+1,F26)) -> 0 | AK26: =SUM(H26:AJ26) -> 0 | AN26: =AN25+1 -> 21 | AO26: UUU | AQ26: N/A | AR26: N/A | AS26: =IF(OR(AQ26="N/A",AR26="N/A"),0,IF(OR(AQ26="Oct",AQ26="Nov",AQ26="Dec"),AR26+1,AR26)) -> 0 | BW26: =SUM(AT26:BV26) -> 0
B27: =B26+1 -> 22 | C27: VVV | E27: N/A | F27: N/A | G27: =IF(OR(E27="N/A",F27="N/A"),0,IF(OR(E27="Oct",E27="Nov",E27="Dec"),F27+1,F27)) -> 0 | AK27: =SUM(H27:AJ27) -> 0 | AN27: =AN26+1 -> 22 | AO27: VVV | AQ27: N/A | AR27: N/A | AS27: =IF(OR(AQ27="N/A",AR27="N/A"),0,IF(OR(AQ27="Oct",AQ27="Nov",AQ27="Dec"),AR27+1,AR27)) -> 0 | BW27: =SUM(AT27:BV27) -> 0
B28: =B27+1 -> 23 | C28: WWW | E28: N/A | F28: N/A | G28: =IF(OR(E28="N/A",F28="N/A"),0,IF(OR(E28="Oct",E28="Nov",E28="Dec"),F28+1,F28)) -> 0 | AK28: =SUM(H28:AJ28) -> 0 | AN28: =AN27+1 -> 23 | AO28: WWW | AQ28: N/A | AR28: N/A | AS28: =IF(OR(AQ28="N/A",AR28="N/A"),0,IF(OR(AQ28="Oct",AQ28="Nov",AQ28="Dec"),AR28+1,AR28)) -> 0 | BW28: =SUM(AT28:BV28) -> 0
... B35: =B34+1 -> 30 | C35: DD1 | E35: N/A | F35: N/A | G35: =IF(OR(E35="N/A",F35="N/A"),0,IF(OR(E35="Oct",E35="Nov",E35="Dec"),F35+1,F35)) -> 0 | AK35: =SUM(H35:AJ35) -> 0 | AN35: =AN34+1 -> 30 | AO35: DD1 | AQ35: N/A | AR35: N/A | AS35: =IF(OR(AQ35="N/A",AR35="N/A"),0,IF(OR(AQ35="Oct",AQ35="Nov",AQ35="Dec"),AR35+1,AR35)) -> 0 | BW35: =SUM(AT35:BV35) -> 0
C36: Total Capital Employed | H36: =SUM(H6:H35) -> 0 | I36: =SUM(I6:I35) -> 0 | J36: =SUM(J6:J35) -> 0 | K36: =SUM(K6:K35) -> 0 | L36: =SUM(L6:L35) -> 0 | M36: =SUM(M6:M35) -> 0 | N36: =SUM(N6:N35) -> 0 | O36: =SUM(O6:O35) -> 0 | ... AK36: =SUM(AK6:AK35) -> 0 | AO36: Total Capital Employed | AT36: =SUM(AT6:AT35) -> 0 | AU36: =SUM(AU6:AU35) -> 0 | AV36: =SUM(AV6:AV35) -> 0 | AW36: =SUM(AW6:AW35) -> 0 | AX36: =SUM(AX6:AX35) -> 0 | AY36: =SUM(AY6:AY35) -> 0 | AZ36: =SUM(AZ6:AZ35) -> 0 | BA36: =SUM(BA6:BA35) -> 0 | ... BW36: =SUM(BW6:BW35) -> 0
B38: Item | C38: Depreciation for New Line | D38: Monthly Depreciation | H38: =+H5 -> FY18 | I38: =+I5 -> FY19 | J38: =+J5 -> FY20 | K38: =+K5 -> FY21 | L38: =+L5 -> FY22 | M38: =+M5 -> FY23 | N38: =+N5 -> FY24 | O38: =+O5 -> FY25 | ... AJ38: =+AJ5 -> FY46 | AK38: Total | AN38: Item | AO38: Depreciation for New Line | AP38: Monthly Depreciation | AT38: =+AT5 -> FY18 | AU38: =+AU5 -> FY19 | AV38: =+AV5 -> FY20 | AW38: =+AW5 -> FY21 | AX38: =+AX5 -> FY22 | AY38: =+AY5 -> FY23 | AZ38: =+AZ5 -> FY24 | BA38: =+BA5 -> FY25 | ... BV38: =+BV5 -> FY46 | BW38: Total
B39: =B6 -> 1 | C39: =C6 -> 0 | D39: =IFERROR(AK6/D6/12,0) -> 0 | H39: =IF(H$4=$G6,$D39*(12-VLOOKUP($E6,$E$79:$F$90,2,0)),IF(AND(H$4>$G6,H$4<($G6+$D6)),$D39*12,IF(H$4=($G6+$D6),$D39*VLOOKUP($E6,$E$79:$F$90,2,0),0))) -> 0 | I39: =IF(I$4=$G6,$D39*(12-VLOOKUP($E6,$E$79:$F$90,2,0)),IF(AND(I$4>$G6,I$4<($G6+$D6)),$D39*12,IF(I$4=($G6+$D6),$D39*VLOOKUP($E6,$E$79:$F$90,2,0),0))) -> 0 | J39: =IF(J$4=$G6,$D39*(12-VLOOKUP($E6,$E$79:$F$90,2,0)),IF(AND(J$4>$G6,J$4<($G6+$D6)),$D39*12,IF(J$4=($G6+$D6),$D39*VLOOKUP($E6,$E$79:$F$90,2,0),0))) -> 0 | K39: =IF(K$4=$G6,$D39*(12-VLOOKUP($E6,$E$79:$F$90,2,0)),IF(AND(K$4>$G6,K$4<($G6+$D6)),$D39*12,IF(K$4=($G6+$D6),$D39*VLOOKUP($E6,$E$79:$F$90,2,0),0))) -> 0 | L39: =IF(L$4=$G6,$D39*(12-VLOOKUP($E6,$E$79:$F$90,2,0)),IF(AND(L$4>$G6,L$4<($G6+$D6)),$D39*12,IF(L$4=($G6+$D6),$D39*VLOOKUP($E6,$E$79:$F$90,2,0),0))) -> 0 | M39: =IF(M$4=$G6,$D39*(12-VLOOKUP($E6,$E$79:$F$90,2,0)),IF(AND(M$4>$G6,M$4<($G6+$D6)),$D39*12,IF(M$4=($G6+$D6),$D39*VLOOKUP($E6,$E$79:$F$90,2,0),0))) -> 0 | N39: =IF(N$4=$G6,$D39*(12-VLOOKUP($E6,$E$79:$F$90,2,0)),IF(AND(N$4>$G6,N$4<($G6+$D6)),$D39*12,IF(N$4=($G6+$D6),$D39*VLOOKUP($E6,$E$79:$F$90,2,0),0))) -> 0 | O39: =IF(O$4=$G6,$D39*(12-VLOOKUP($E6,$E$79:$F$90,2,0)),IF(AND(O$4>$G6,O$4<($G6+$D6)),$D39*12,IF(O$4=($G6+$D6),$D39*VLOOKUP($E6,$E$79:$F$90,2,0),0))) -> 0 | ... AJ39: =IF(AJ$4=$G6,$D39*(12-VLOOKUP($E6,$E$79:$F$90,2,0)),IF(AND(AJ$4>$G6,AJ$4<($G6+$D6)),$D39*12,IF(AJ$4=($G6+$D6),$D39*VLOOKUP($E6,$E$79:$F$90,2,0),0))) -> 0 | AK39: =SUM(H39:AJ39) -> 0 | AN39: =AN6 -> 1 | AO39: =AO6 -> AAA - Assembly Line | AP39: =IFERROR(BW6/AP6/12,0) -> 0 | AT39: =IF(AT$4=$AS6,$AP39*(12-VLOOKUP($AQ6,$E$79:$F$90,2,0)),IF(AND(AT$4>$AS6,AT$4<($AS6+$AP6)),$AP39*12,IF(AT$4=($AS6+$AP6),$AP39*VLOOKUP($AQ6,$E$79:$F$90,2,0),0))) -> 0 | AU39: =IF(AU$4=$AS6,$AP39*(12-VLOOKUP($AQ6,$E$79:$F$90,2,0)),IF(AND(AU$4>$AS6,AU$4<($AS6+$AP6)),$AP39*12,IF(AU$4=($AS6+$AP6),$AP39*VLOOKUP($AQ6,$E$79:$F$90,2,0),0))) -> 0 | AV39: =IF(AV$4=$AS6,$AP39*(12-VLOOKUP($AQ6,$E$79:$F$90,2,0)),IF(AND(AV$4>$AS6,AV$4<($AS6+$AP6)),$AP39*12,IF(AV$4=($AS6+$AP6),$AP39*VLOOKUP($AQ6,$E$79:$F$90,2,0),0))) -> 0 | AW39: =IF(AW$4=$AS6,$AP39*(12-VLOOKUP($AQ6,$E$79:$F$90,2,0)),IF(AND(AW$4>$AS6,AW$4<($AS6+$AP6)),$AP39*12,IF(AW$4=($AS6+$AP6),$AP39*VLOOKUP($AQ6,$E$79:$F$90,2,0),0))) -> 0 | AX39: =IF(AX$4=$AS6,$AP39*(12-VLOOKUP($AQ6,$E$79:$F$90,2,0)),IF(AND(AX$4>$AS6,AX$4<($AS6+$AP6)),$AP39*12,IF(AX$4=($AS6+$AP6),$AP39*VLOOKUP($AQ6,$E$79:$F$90,2,0),0))) -> 0 | AY39: =IF(AY$4=$AS6,$AP39*(12-VLOOKUP($AQ6,$E$79:$F$90,2,0)),IF(AND(AY$4>$AS6,AY$4<($AS6+$AP6)),$AP39*12,IF(AY$4=($AS6+$AP6),$AP39*VLOOKUP($AQ6,$E$79:$F$90,2,0),0))) -> 0 | AZ39: =IF(AZ$4=$AS6,$AP39*(12-VLOOKUP($AQ6,$E$79:$F$90,2,0)),IF(AND(AZ$4>$AS6,AZ$4<($AS6+$AP6)),$AP39*12,IF(AZ$4=($AS6+$AP6),$AP39*VLOOKUP($AQ6,$E$79:$F$90,2,0),0))) -> 0 | BA39: =IF(BA$4=$AS6,$AP39*(12-VLOOKUP($AQ6,$E$79:$F$90,2,0)),IF(AND(BA$4>$AS6,BA$4<($AS6+$AP6)),$AP39*12,IF(BA$4=($AS6+$AP6),$AP39*VLOOKUP($AQ6,$E$79:$F$90,2,0),0))) -> 0 | ... BV39: =IF(BV$4=$AS6,$AP39*(12-VLOOKUP($AQ6,$E$79:$F$90,2,0)),IF(AND(BV$4>$AS6,BV$4<($AS6+$AP6)),$AP39*12,IF(BV$4=($AS6+$AP6),$AP39*VLOOKUP($AQ6,$E$79:$F$90,2,0),0))) -> 0 | BW39: =SUM(AT39:BV39) -> 0
B40: =B7 -> 2 | C40: =C7 -> 0 | D40: =IFERROR(AK7/D7/12,0) -> 0 | H40: =IF(H$4=$G7,$D40*(12-VLOOKUP($E7,$E$79:$F$90,2,0)),IF(AND(H$4>$G7,H$4<($G7+$D7)),$D40*12,IF(H$4=($G7+$D7),$D40*VLOOKUP($E7,$E$79:$F$90,2,0),0))) -> 0 | I40: =IF(I$4=$G7,$D40*(12-VLOOKUP($E7,$E$79:$F$90,2,0)),IF(AND(I$4>$G7,I$4<($G7+$D7)),$D40*12,IF(I$4=($G7+$D7),$D40*VLOOKUP($E7,$E$79:$F$90,2,0),0))) -> 0 | J40: =IF(J$4=$G7,$D40*(12-VLOOKUP($E7,$E$79:$F$90,2,0)),IF(AND(J$4>$G7,J$4<($G7+$D7)),$D40*12,IF(J$4=($G7+$D7),$D40*VLOOKUP($E7,$E$79:$F$90,2,0),0))) -> 0 | K40: =IF(K$4=$G7,$D40*(12-VLOOKUP($E7,$E$79:$F$90,2,0)),IF(AND(K$4>$G7,K$4<($G7+$D7)),$D40*12,IF(K$4=($G7+$D7),$D40*VLOOKUP($E7,$E$79:$F$90,2,0),0))) -> 0 | L40: =IF(L$4=$G7,$D40*(12-VLOOKUP($E7,$E$79:$F$90,2,0)),IF(AND(L$4>$G7,L$4<($G7+$D7)),$D40*12,IF(L$4=($G7+$D7),$D40*VLOOKUP($E7,$E$79:$F$90,2,0),0))) -> 0 | M40: =IF(M$4=$G7,$D40*(12-VLOOKUP($E7,$E$79:$F$90,2,0)),IF(AND(M$4>$G7,M$4<($G7+$D7)),$D40*12,IF(M$4=($G7+$D7),$D40*VLOOKUP($E7,$E$79:$F$90,2,0),0))) -> 0 | N40: =IF(N$4=$G7,$D40*(12-VLOOKUP($E7,$E$79:$F$90,2,0)),IF(AND(N$4>$G7,N$4<($G7+$D7)),$D40*12,IF(N$4=($G7+$D7),$D40*VLOOKUP($E7,$E$79:$F$90,2,0),0))) -> 0 | O40: =IF(O$4=$G7,$D40*(12-VLOOKUP($E7,$E$79:$F$90,2,0)),IF(AND(O$4>$G7,O$4<($G7+$D7)),$D40*12,IF(O$4=($G7+$D7),$D40*VLOOKUP($E7,$E$79:$F$90,2,0),0))) -> 0 | ... AJ40: =IF(AJ$4=$G7,$D40*(12-VLOOKUP($E7,$E$79:$F$90,2,0)),IF(AND(AJ$4>$G7,AJ$4<($G7+$D7)),$D40*12,IF(AJ$4=($G7+$D7),$D40*VLOOKUP($E7,$E$79:$F$90,2,0),0))) -> 0 | AK40: =SUM(H40:AJ40) -> 0 | AN40: =AN7 -> 2 | AO40: =AO7 -> 0 | AP40: =IFERROR(BW7/AP7/12,0) -> 0 | AT40: =IF(AT$4=$AS7,$AP40*(12-VLOOKUP($AQ7,$E$79:$F$90,2,0)),IF(AND(AT$4>$AS7,AT$4<($AS7+$AP7)),$AP40*12,IF(AT$4=($AS7+$AP7),$AP40*VLOOKUP($AQ7,$E$79:$F$90,2,0),0))) -> 0 | AU40: =IF(AU$4=$AS7,$AP40*(12-VLOOKUP($AQ7,$E$79:$F$90,2,0)),IF(AND(AU$4>$AS7,AU$4<($AS7+$AP7)),$AP40*12,IF(AU$4=($AS7+$AP7),$AP40*VLOOKUP($AQ7,$E$79:$F$90,2,0),0))) -> 0 | AV40: =IF(AV$4=$AS7,$AP40*(12-VLOOKUP($AQ7,$E$79:$F$90,2,0)),IF(AND(AV$4>$AS7,AV$4<($AS7+$AP7)),$AP40*12,IF(AV$4=($AS7+$AP7),$AP40*VLOOKUP($AQ7,$E$79:$F$90,2,0),0))) -> 0 | AW40: =IF(AW$4=$AS7,$AP40*(12-VLOOKUP($AQ7,$E$79:$F$90,2,0)),IF(AND(AW$4>$AS7,AW$4<($AS7+$AP7)),$AP40*12,IF(AW$4=($AS7+$AP7),$AP40*VLOOKUP($AQ7,$E$79:$F$90,2,0),0))) -> 0 | AX40: =IF(AX$4=$AS7,$AP40*(12-VLOOKUP($AQ7,$E$79:$F$90,2,0)),IF(AND(AX$4>$AS7,AX$4<($AS7+$AP7)),$AP40*12,IF(AX$4=($AS7+$AP7),$AP40*VLOOKUP($AQ7,$E$79:$F$90,2,0),0))) -> 0 | AY40: =IF(AY$4=$AS7,$AP40*(12-VLOOKUP($AQ7,$E$79:$F$90,2,0)),IF(AND(AY$4>$AS7,AY$4<($AS7+$AP7)),$AP40*12,IF(AY$4=($AS7+$AP7),$AP40*VLOOKUP($AQ7,$E$79:$F$90,2,0),0))) -> 0 | AZ40: =IF(AZ$4=$AS7,$AP40*(12-VLOOKUP($AQ7,$E$79:$F$90,2,0)),IF(AND(AZ$4>$AS7,AZ$4<($AS7+$AP7)),$AP40*12,IF(AZ$4=($AS7+$AP7),$AP40*VLOOKUP($AQ7,$E$79:$F$90,2,0),0))) -> 0 | BA40: =IF(BA$4=$AS7,$AP40*(12-VLOOKUP($AQ7,$E$79:$F$90,2,0)),IF(AND(BA$4>$AS7,BA$4<($AS7+$AP7)),$AP40*12,IF(BA$4=($AS7+$AP7),$AP40*VLOOKUP($AQ7,$E$79:$F$90,2,0),0))) -> 0 | ... BV40: =IF(BV$4=$AS7,$AP40*(12-VLOOKUP($AQ7,$E$79:$F$90,2,0)),IF(AND(BV$4>$AS7,BV$4<($AS7+$AP7)),$AP40*12,IF(BV$4=($AS7+$AP7),$AP40*VLOOKUP($AQ7,$E$79:$F$90,2,0),0))) -> 0 | BW40: =SUM(AT40:BV40) -> 0
B41: =B8 -> 3 | C41: =C8 -> 0 | D41: =IFERROR(AK8/D8/12,0) -> 0 | H41: =IF(H$4=$G8,$D41*(12-VLOOKUP($E8,$E$79:$F$90,2,0)),IF(AND(H$4>$G8,H$4<($G8+$D8)),$D41*12,IF(H$4=($G8+$D8),$D41*VLOOKUP($E8,$E$79:$F$90,2,0),0))) -> 0 | I41: =IF(I$4=$G8,$D41*(12-VLOOKUP($E8,$E$79:$F$90,2,0)),IF(AND(I$4>$G8,I$4<($G8+$D8)),$D41*12,IF(I$4=($G8+$D8),$D41*VLOOKUP($E8,$E$79:$F$90,2,0),0))) -> 0 | J41: =IF(J$4=$G8,$D41*(12-VLOOKUP($E8,$E$79:$F$90,2,0)),IF(AND(J$4>$G8,J$4<($G8+$D8)),$D41*12,IF(J$4=($G8+$D8),$D41*VLOOKUP($E8,$E$79:$F$90,2,0),0))) -> 0 | K41: =IF(K$4=$G8,$D41*(12-VLOOKUP($E8,$E$79:$F$90,2,0)),IF(AND(K$4>$G8,K$4<($G8+$D8)),$D41*12,IF(K$4=($G8+$D8),$D41*VLOOKUP($E8,$E$79:$F$90,2,0),0))) -> 0 | L41: =IF(L$4=$G8,$D41*(12-VLOOKUP($E8,$E$79:$F$90,2,0)),IF(AND(L$4>$G8,L$4<($G8+$D8)),$D41*12,IF(L$4=($G8+$D8),$D41*VLOOKUP($E8,$E$79:$F$90,2,0),0))) -> 0 | M41: =IF(M$4=$G8,$D41*(12-VLOOKUP($E8,$E$79:$F$90,2,0)),IF(AND(M$4>$G8,M$4<($G8+$D8)),$D41*12,IF(M$4=($G8+$D8),$D41*VLOOKUP($E8,$E$79:$F$90,2,0),0))) -> 0 | N41: =IF(N$4=$G8,$D41*(12-VLOOKUP($E8,$E$79:$F$90,2,0)),IF(AND(N$4>$G8,N$4<($G8+$D8)),$D41*12,IF(N$4=($G8+$D8),$D41*VLOOKUP($E8,$E$79:$F$90,2,0),0))) -> 0 | O41: =IF(O$4=$G8,$D41*(12-VLOOKUP($E8,$E$79:$F$90,2,0)),IF(AND(O$4>$G8,O$4<($G8+$D8)),$D41*12,IF(O$4=($G8+$D8),$D41*VLOOKUP($E8,$E$79:$F$90,2,0),0))) -> 0 | ... AJ41: =IF(AJ$4=$G8,$D41*(12-VLOOKUP($E8,$E$79:$F$90,2,0)),IF(AND(AJ$4>$G8,AJ$4<($G8+$D8)),$D41*12,IF(AJ$4=($G8+$D8),$D41*VLOOKUP($E8,$E$79:$F$90,2,0),0))) -> 0 | AK41: =SUM(H41:AJ41) -> 0 | AN41: =AN8 -> 3 | AO41: =AO8 -> 0 | AP41: =IFERROR(BW8/AP8/12,0) -> 0 | AT41: =IF(AT$4=$AS8,$AP41*(12-VLOOKUP($AQ8,$E$79:$F$90,2,0)),IF(AND(AT$4>$AS8,AT$4<($AS8+$AP8)),$AP41*12,IF(AT$4=($AS8+$AP8),$AP41*VLOOKUP($AQ8,$E$79:$F$90,2,0),0))) -> 0 | AU41: =IF(AU$4=$AS8,$AP41*(12-VLOOKUP($AQ8,$E$79:$F$90,2,0)),IF(AND(AU$4>$AS8,AU$4<($AS8+$AP8)),$AP41*12,IF(AU$4=($AS8+$AP8),$AP41*VLOOKUP($AQ8,$E$79:$F$90,2,0),0))) -> 0 | AV41: =IF(AV$4=$AS8,$AP41*(12-VLOOKUP($AQ8,$E$79:$F$90,2,0)),IF(AND(AV$4>$AS8,AV$4<($AS8+$AP8)),$AP41*12,IF(AV$4=($AS8+$AP8),$AP41*VLOOKUP($AQ8,$E$79:$F$90,2,0),0))) -> 0 | AW41: =IF(AW$4=$AS8,$AP41*(12-VLOOKUP($AQ8,$E$79:$F$90,2,0)),IF(AND(AW$4>$AS8,AW$4<($AS8+$AP8)),$AP41*12,IF(AW$4=($AS8+$AP8),$AP41*VLOOKUP($AQ8,$E$79:$F$90,2,0),0))) -> 0 | AX41: =IF(AX$4=$AS8,$AP41*(12-VLOOKUP($AQ8,$E$79:$F$90,2,0)),IF(AND(AX$4>$AS8,AX$4<($AS8+$AP8)),$AP41*12,IF(AX$4=($AS8+$AP8),$AP41*VLOOKUP($AQ8,$E$79:$F$90,2,0),0))) -> 0 | AY41: =IF(AY$4=$AS8,$AP41*(12-VLOOKUP($AQ8,$E$79:$F$90,2,0)),IF(AND(AY$4>$AS8,AY$4<($AS8+$AP8)),$AP41*12,IF(AY$4=($AS8+$AP8),$AP41*VLOOKUP($AQ8,$E$79:$F$90,2,0),0))) -> 0 | AZ41: =IF(AZ$4=$AS8,$AP41*(12-VLOOKUP($AQ8,$E$79:$F$90,2,0)),IF(AND(AZ$4>$AS8,AZ$4<($AS8+$AP8)),$AP41*12,IF(AZ$4=($AS8+$AP8),$AP41*VLOOKUP($AQ8,$E$79:$F$90,2,0),0))) -> 0 | BA41: =IF(BA$4=$AS8,$AP41*(12-VLOOKUP($AQ8,$E$79:$F$90,2,0)),IF(AND(BA$4>$AS8,BA$4<($AS8+$AP8)),$AP41*12,IF(BA$4=($AS8+$AP8),$AP41*VLOOKUP($AQ8,$E$79:$F$90,2,0),0))) -> 0 | ... BV41: =IF(BV$4=$AS8,$AP41*(12-VLOOKUP($AQ8,$E$79:$F$90,2,0)),IF(AND(BV$4>$AS8,BV$4<($AS8+$AP8)),$AP41*12,IF(BV$4=($AS8+$AP8),$AP41*VLOOKUP($AQ8,$E$79:$F$90,2,0),0))) -> 0 | BW41: =SUM(AT41:BV41) -> 0
B42: =B9 -> 4 | C42: =C9 -> 0 | D42: =IFERROR(AK9/D9/12,0) -> 0 | H42: =IF(H$4=$G9,$D42*(12-VLOOKUP($E9,$E$79:$F$90,2,0)),IF(AND(H$4>$G9,H$4<($G9+$D9)),$D42*12,IF(H$4=($G9+$D9),$D42*VLOOKUP($E9,$E$79:$F$90,2,0),0))) -> 0 | I42: =IF(I$4=$G9,$D42*(12-VLOOKUP($E9,$E$79:$F$90,2,0)),IF(AND(I$4>$G9,I$4<($G9+$D9)),$D42*12,IF(I$4=($G9+$D9),$D42*VLOOKUP($E9,$E$79:$F$90,2,0),0))) -> 0 | J42: =IF(J$4=$G9,$D42*(12-VLOOKUP($E9,$E$79:$F$90,2,0)),IF(AND(J$4>$G9,J$4<($G9+$D9)),$D42*12,IF(J$4=($G9+$D9),$D42*VLOOKUP($E9,$E$79:$F$90,2,0),0))) -> 0 | K42: =IF(K$4=$G9,$D42*(12-VLOOKUP($E9,$E$79:$F$90,2,0)),IF(AND(K$4>$G9,K$4<($G9+$D9)),$D42*12,IF(K$4=($G9+$D9),$D42*VLOOKUP($E9,$E$79:$F$90,2,0),0))) -> 0 | L42: =IF(L$4=$G9,$D42*(12-VLOOKUP($E9,$E$79:$F$90,2,0)),IF(AND(L$4>$G9,L$4<($G9+$D9)),$D42*12,IF(L$4=($G9+$D9),$D42*VLOOKUP($E9,$E$79:$F$90,2,0),0))) -> 0 | M42: =IF(M$4=$G9,$D42*(12-VLOOKUP($E9,$E$79:$F$90,2,0)),IF(AND(M$4>$G9,M$4<($G9+$D9)),$D42*12,IF(M$4=($G9+$D9),$D42*VLOOKUP($E9,$E$79:$F$90,2,0),0))) -> 0 | N42: =IF(N$4=$G9,$D42*(12-VLOOKUP($E9,$E$79:$F$90,2,0)),IF(AND(N$4>$G9,N$4<($G9+$D9)),$D42*12,IF(N$4=($G9+$D9),$D42*VLOOKUP($E9,$E$79:$F$90,2,0),0))) -> 0 | O42: =IF(O$4=$G9,$D42*(12-VLOOKUP($E9,$E$79:$F$90,2,0)),IF(AND(O$4>$G9,O$4<($G9+$D9)),$D42*12,IF(O$4=($G9+$D9),$D42*VLOOKUP($E9,$E$79:$F$90,2,0),0))) -> 0 | ... AJ42: =IF(AJ$4=$G9,$D42*(12-VLOOKUP($E9,$E$79:$F$90,2,0)),IF(AND(AJ$4>$G9,AJ$4<($G9+$D9)),$D42*12,IF(AJ$4=($G9+$D9),$D42*VLOOKUP($E9,$E$79:$F$90,2,0),0))) -> 0 | AK42: =SUM(H42:AJ42) -> 0 | AN42: =AN9 -> 4 | AO42: =AO9 -> 0 | AP42: =IFERROR(BW9/AP9/12,0) -> 0 | AT42: =IF(AT$4=$AS9,$AP42*(12-VLOOKUP($AQ9,$E$79:$F$90,2,0)),IF(AND(AT$4>$AS9,AT$4<($AS9+$AP9)),$AP42*12,IF(AT$4=($AS9+$AP9),$AP42*VLOOKUP($AQ9,$E$79:$F$90,2,0),0))) -> 0 | AU42: =IF(AU$4=$AS9,$AP42*(12-VLOOKUP($AQ9,$E$79:$F$90,2,0)),IF(AND(AU$4>$AS9,AU$4<($AS9+$AP9)),$AP42*12,IF(AU$4=($AS9+$AP9),$AP42*VLOOKUP($AQ9,$E$79:$F$90,2,0),0))) -> 0 | AV42: =IF(AV$4=$AS9,$AP42*(12-VLOOKUP($AQ9,$E$79:$F$90,2,0)),IF(AND(AV$4>$AS9,AV$4<($AS9+$AP9)),$AP42*12,IF(AV$4=($AS9+$AP9),$AP42*VLOOKUP($AQ9,$E$79:$F$90,2,0),0))) -> 0 | AW42: =IF(AW$4=$AS9,$AP42*(12-VLOOKUP($AQ9,$E$79:$F$90,2,0)),IF(AND(AW$4>$AS9,AW$4<($AS9+$AP9)),$AP42*12,IF(AW$4=($AS9+$AP9),$AP42*VLOOKUP($AQ9,$E$79:$F$90,2,0),0))) -> 0 | AX42: =IF(AX$4=$AS9,$AP42*(12-VLOOKUP($AQ9,$E$79:$F$90,2,0)),IF(AND(AX$4>$AS9,AX$4<($AS9+$AP9)),$AP42*12,IF(AX$4=($AS9+$AP9),$AP42*VLOOKUP($AQ9,$E$79:$F$90,2,0),0))) -> 0 | AY42: =IF(AY$4=$AS9,$AP42*(12-VLOOKUP($AQ9,$E$79:$F$90,2,0)),IF(AND(AY$4>$AS9,AY$4<($AS9+$AP9)),$AP42*12,IF(AY$4=($AS9+$AP9),$AP42*VLOOKUP($AQ9,$E$79:$F$90,2,0),0))) -> 0 | AZ42: =IF(AZ$4=$AS9,$AP42*(12-VLOOKUP($AQ9,$E$79:$F$90,2,0)),IF(AND(AZ$4>$AS9,AZ$4<($AS9+$AP9)),$AP42*12,IF(AZ$4=($AS9+$AP9),$AP42*VLOOKUP($AQ9,$E$79:$F$90,2,0),0))) -> 0 | BA42: =IF(BA$4=$AS9,$AP42*(12-VLOOKUP($AQ9,$E$79:$F$90,2,0)),IF(AND(BA$4>$AS9,BA$4<($AS9+$AP9)),$AP42*12,IF(BA$4=($AS9+$AP9),$AP42*VLOOKUP($AQ9,$E$79:$F$90,2,0),0))) -> 0 | ... BV42: =IF(BV$4=$AS9,$AP42*(12-VLOOKUP($AQ9,$E$79:$F$90,2,0)),IF(AND(BV$4>$AS9,BV$4<($AS9+$AP9)),$AP42*12,IF(BV$4=($AS9+$AP9),$AP42*VLOOKUP($AQ9,$E$79:$F$90,2,0),0))) -> 0 | BW42: =SUM(AT42:BV42) -> 0
B43: =B10 -> 5 | C43: =C10 -> 0 | D43: =IFERROR(AK10/D10/12,0) -> 0 | H43: =IF(H$4=$G10,$D43*(12-VLOOKUP($E10,$E$79:$F$90,2,0)),IF(AND(H$4>$G10,H$4<($G10+$D10)),$D43*12,IF(H$4=($G10+$D10),$D43*VLOOKUP($E10,$E$79:$F$90,2,0),0))) -> 0 | I43: =IF(I$4=$G10,$D43*(12-VLOOKUP($E10,$E$79:$F$90,2,0)),IF(AND(I$4>$G10,I$4<($G10+$D10)),$D43*12,IF(I$4=($G10+$D10),$D43*VLOOKUP($E10,$E$79:$F$90,2,0),0))) -> 0 | J43: =IF(J$4=$G10,$D43*(12-VLOOKUP($E10,$E$79:$F$90,2,0)),IF(AND(J$4>$G10,J$4<($G10+$D10)),$D43*12,IF(J$4=($G10+$D10),$D43*VLOOKUP($E10,$E$79:$F$90,2,0),0))) -> 0 | K43: =IF(K$4=$G10,$D43*(12-VLOOKUP($E10,$E$79:$F$90,2,0)),IF(AND(K$4>$G10,K$4<($G10+$D10)),$D43*12,IF(K$4=($G10+$D10),$D43*VLOOKUP($E10,$E$79:$F$90,2,0),0))) -> 0 | L43: =IF(L$4=$G10,$D43*(12-VLOOKUP($E10,$E$79:$F$90,2,0)),IF(AND(L$4>$G10,L$4<($G10+$D10)),$D43*12,IF(L$4=($G10+$D10),$D43*VLOOKUP($E10,$E$79:$F$90,2,0),0))) -> 0 | M43: =IF(M$4=$G10,$D43*(12-VLOOKUP($E10,$E$79:$F$90,2,0)),IF(AND(M$4>$G10,M$4<($G10+$D10)),$D43*12,IF(M$4=($G10+$D10),$D43*VLOOKUP($E10,$E$79:$F$90,2,0),0))) -> 0 | N43: =IF(N$4=$G10,$D43*(12-VLOOKUP($E10,$E$79:$F$90,2,0)),IF(AND(N$4>$G10,N$4<($G10+$D10)),$D43*12,IF(N$4=($G10+$D10),$D43*VLOOKUP($E10,$E$79:$F$90,2,0),0))) -> 0 | O43: =IF(O$4=$G10,$D43*(12-VLOOKUP($E10,$E$79:$F$90,2,0)),IF(AND(O$4>$G10,O$4<($G10+$D10)),$D43*12,IF(O$4=($G10+$D10),$D43*VLOOKUP($E10,$E$79:$F$90,2,0),0))) -> 0 | ... AJ43: =IF(AJ$4=$G10,$D43*(12-VLOOKUP($E10,$E$79:$F$90,2,0)),IF(AND(AJ$4>$G10,AJ$4<($G10+$D10)),$D43*12,IF(AJ$4=($G10+$D10),$D43*VLOOKUP($E10,$E$79:$F$90,2,0),0))) -> 0 | AK43: =SUM(H43:AJ43) -> 0 | AN43: =AN10 -> 5 | AO43: =AO10 -> 0 | AP43: =IFERROR(BW10/AP10/12,0) -> 0 | AT43: =IF(AT$4=$AS10,$AP43*(12-VLOOKUP($AQ10,$E$79:$F$90,2,0)),IF(AND(AT$4>$AS10,AT$4<($AS10+$AP10)),$AP43*12,IF(AT$4=($AS10+$AP10),$AP43*VLOOKUP($AQ10,$E$79:$F$90,2,0),0))) -> 0 | AU43: =IF(AU$4=$AS10,$AP43*(12-VLOOKUP($AQ10,$E$79:$F$90,2,0)),IF(AND(AU$4>$AS10,AU$4<($AS10+$AP10)),$AP43*12,IF(AU$4=($AS10+$AP10),$AP43*VLOOKUP($AQ10,$E$79:$F$90,2,0),0))) -> 0 | AV43: =IF(AV$4=$AS10,$AP43*(12-VLOOKUP($AQ10,$E$79:$F$90,2,0)),IF(AND(AV$4>$AS10,AV$4<($AS10+$AP10)),$AP43*12,IF(AV$4=($AS10+$AP10),$AP43*VLOOKUP($AQ10,$E$79:$F$90,2,0),0))) -> 0 | AW43: =IF(AW$4=$AS10,$AP43*(12-VLOOKUP($AQ10,$E$79:$F$90,2,0)),IF(AND(AW$4>$AS10,AW$4<($AS10+$AP10)),$AP43*12,IF(AW$4=($AS10+$AP10),$AP43*VLOOKUP($AQ10,$E$79:$F$90,2,0),0))) -> 0 | AX43: =IF(AX$4=$AS10,$AP43*(12-VLOOKUP($AQ10,$E$79:$F$90,2,0)),IF(AND(AX$4>$AS10,AX$4<($AS10+$AP10)),$AP43*12,IF(AX$4=($AS10+$AP10),$AP43*VLOOKUP($AQ10,$E$79:$F$90,2,0),0))) -> 0 | AY43: =IF(AY$4=$AS10,$AP43*(12-VLOOKUP($AQ10,$E$79:$F$90,2,0)),IF(AND(AY$4>$AS10,AY$4<($AS10+$AP10)),$AP43*12,IF(AY$4=($AS10+$AP10),$AP43*VLOOKUP($AQ10,$E$79:$F$90,2,0),0))) -> 0 | AZ43: =IF(AZ$4=$AS10,$AP43*(12-VLOOKUP($AQ10,$E$79:$F$90,2,0)),IF(AND(AZ$4>$AS10,AZ$4<($AS10+$AP10)),$AP43*12,IF(AZ$4=($AS10+$AP10),$AP43*VLOOKUP($AQ10,$E$79:$F$90,2,0),0))) -> 0 | BA43: =IF(BA$4=$AS10,$AP43*(12-VLOOKUP($AQ10,$E$79:$F$90,2,0)),IF(AND(BA$4>$AS10,BA$4<($AS10+$AP10)),$AP43*12,IF(BA$4=($AS10+$AP10),$AP43*VLOOKUP($AQ10,$E$79:$F$90,2,0),0))) -> 0 | ... BV43: =IF(BV$4=$AS10,$AP43*(12-VLOOKUP($AQ10,$E$79:$F$90,2,0)),IF(AND(BV$4>$AS10,BV$4<($AS10+$AP10)),$AP43*12,IF(BV$4=($AS10+$AP10),$AP43*VLOOKUP($AQ10,$E$79:$F$90,2,0),0))) -> 0 | BW43: =SUM(AT43:BV43) -> 0
B44: =B11 -> 6 | C44: =C11 -> 0 | D44: =IFERROR(AK11/D11/12,0) -> 0 | H44: =IF(H$4=$G11,$D44*(12-VLOOKUP($E11,$E$79:$F$90,2,0)),IF(AND(H$4>$G11,H$4<($G11+$D11)),$D44*12,IF(H$4=($G11+$D11),$D44*VLOOKUP($E11,$E$79:$F$90,2,0),0))) -> 0 | I44: =IF(I$4=$G11,$D44*(12-VLOOKUP($E11,$E$79:$F$90,2,0)),IF(AND(I$4>$G11,I$4<($G11+$D11)),$D44*12,IF(I$4=($G11+$D11),$D44*VLOOKUP($E11,$E$79:$F$90,2,0),0))) -> 0 | J44: =IF(J$4=$G11,$D44*(12-VLOOKUP($E11,$E$79:$F$90,2,0)),IF(AND(J$4>$G11,J$4<($G11+$D11)),$D44*12,IF(J$4=($G11+$D11),$D44*VLOOKUP($E11,$E$79:$F$90,2,0),0))) -> 0 | K44: =IF(K$4=$G11,$D44*(12-VLOOKUP($E11,$E$79:$F$90,2,0)),IF(AND(K$4>$G11,K$4<($G11+$D11)),$D44*12,IF(K$4=($G11+$D11),$D44*VLOOKUP($E11,$E$79:$F$90,2,0),0))) -> 0 | L44: =IF(L$4=$G11,$D44*(12-VLOOKUP($E11,$E$79:$F$90,2,0)),IF(AND(L$4>$G11,L$4<($G11+$D11)),$D44*12,IF(L$4=($G11+$D11),$D44*VLOOKUP($E11,$E$79:$F$90,2,0),0))) -> 0 | M44: =IF(M$4=$G11,$D44*(12-VLOOKUP($E11,$E$79:$F$90,2,0)),IF(AND(M$4>$G11,M$4<($G11+$D11)),$D44*12,IF(M$4=($G11+$D11),$D44*VLOOKUP($E11,$E$79:$F$90,2,0),0))) -> 0 | N44: =IF(N$4=$G11,$D44*(12-VLOOKUP($E11,$E$79:$F$90,2,0)),IF(AND(N$4>$G11,N$4<($G11+$D11)),$D44*12,IF(N$4=($G11+$D11),$D44*VLOOKUP($E11,$E$79:$F$90,2,0),0))) -> 0 | O44: =IF(O$4=$G11,$D44*(12-VLOOKUP($E11,$E$79:$F$90,2,0)),IF(AND(O$4>$G11,O$4<($G11+$D11)),$D44*12,IF(O$4=($G11+$D11),$D44*VLOOKUP($E11,$E$79:$F$90,2,0),0))) -> 0 | ... AJ44: =IF(AJ$4=$G11,$D44*(12-VLOOKUP($E11,$E$79:$F$90,2,0)),IF(AND(AJ$4>$G11,AJ$4<($G11+$D11)),$D44*12,IF(AJ$4=($G11+$D11),$D44*VLOOKUP($E11,$E$79:$F$90,2,0),0))) -> 0 | AK44: =SUM(H44:AJ44) -> 0 | AN44: =AN11 -> 6 | AO44: =AO11 -> 0 | AP44: =IFERROR(BW11/AP11/12,0) -> 0 | AT44: =IF(AT$4=$AS11,$AP44*(12-VLOOKUP($AQ11,$E$79:$F$90,2,0)),IF(AND(AT$4>$AS11,AT$4<($AS11+$AP11)),$AP44*12,IF(AT$4=($AS11+$AP11),$AP44*VLOOKUP($AQ11,$E$79:$F$90,2,0),0))) -> 0 | AU44: =IF(AU$4=$AS11,$AP44*(12-VLOOKUP($AQ11,$E$79:$F$90,2,0)),IF(AND(AU$4>$AS11,AU$4<($AS11+$AP11)),$AP44*12,IF(AU$4=($AS11+$AP11),$AP44*VLOOKUP($AQ11,$E$79:$F$90,2,0),0))) -> 0 | AV44: =IF(AV$4=$AS11,$AP44*(12-VLOOKUP($AQ11,$E$79:$F$90,2,0)),IF(AND(AV$4>$AS11,AV$4<($AS11+$AP11)),$AP44*12,IF(AV$4=($AS11+$AP11),$AP44*VLOOKUP($AQ11,$E$79:$F$90,2,0),0))) -> 0 | AW44: =IF(AW$4=$AS11,$AP44*(12-VLOOKUP($AQ11,$E$79:$F$90,2,0)),IF(AND(AW$4>$AS11,AW$4<($AS11+$AP11)),$AP44*12,IF(AW$4=($AS11+$AP11),$AP44*VLOOKUP($AQ11,$E$79:$F$90,2,0),0))) -> 0 | AX44: =IF(AX$4=$AS11,$AP44*(12-VLOOKUP($AQ11,$E$79:$F$90,2,0)),IF(AND(AX$4>$AS11,AX$4<($AS11+$AP11)),$AP44*12,IF(AX$4=($AS11+$AP11),$AP44*VLOOKUP($AQ11,$E$79:$F$90,2,0),0))) -> 0 | AY44: =IF(AY$4=$AS11,$AP44*(12-VLOOKUP($AQ11,$E$79:$F$90,2,0)),IF(AND(AY$4>$AS11,AY$4<($AS11+$AP11)),$AP44*12,IF(AY$4=($AS11+$AP11),$AP44*VLOOKUP($AQ11,$E$79:$F$90,2,0),0))) -> 0 | AZ44: =IF(AZ$4=$AS11,$AP44*(12-VLOOKUP($AQ11,$E$79:$F$90,2,0)),IF(AND(AZ$4>$AS11,AZ$4<($AS11+$AP11)),$AP44*12,IF(AZ$4=($AS11+$AP11),$AP44*VLOOKUP($AQ11,$E$79:$F$90,2,0),0))) -> 0 | BA44: =IF(BA$4=$AS11,$AP44*(12-VLOOKUP($AQ11,$E$79:$F$90,2,0)),IF(AND(BA$4>$AS11,BA$4<($AS11+$AP11)),$AP44*12,IF(BA$4=($AS11+$AP11),$AP44*VLOOKUP($AQ11,$E$79:$F$90,2,0),0))) -> 0 | ... BV44: =IF(BV$4=$AS11,$AP44*(12-VLOOKUP($AQ11,$E$79:$F$90,2,0)),IF(AND(BV$4>$AS11,BV$4<($AS11+$AP11)),$AP44*12,IF(BV$4=($AS11+$AP11),$AP44*VLOOKUP($AQ11,$E$79:$F$90,2,0),0))) -> 0 | BW44: =SUM(AT44:BV44) -> 0
B45: =B12 -> 7 | C45: =C12 -> 0 | D45: =IFERROR(AK12/D12/12,0) -> 0 | H45: =IF(H$4=$G12,$D45*(12-VLOOKUP($E12,$E$79:$F$90,2,0)),IF(AND(H$4>$G12,H$4<($G12+$D12)),$D45*12,IF(H$4=($G12+$D12),$D45*VLOOKUP($E12,$E$79:$F$90,2,0),0))) -> 0 | I45: =IF(I$4=$G12,$D45*(12-VLOOKUP($E12,$E$79:$F$90,2,0)),IF(AND(I$4>$G12,I$4<($G12+$D12)),$D45*12,IF(I$4=($G12+$D12),$D45*VLOOKUP($E12,$E$79:$F$90,2,0),0))) -> 0 | J45: =IF(J$4=$G12,$D45*(12-VLOOKUP($E12,$E$79:$F$90,2,0)),IF(AND(J$4>$G12,J$4<($G12+$D12)),$D45*12,IF(J$4=($G12+$D12),$D45*VLOOKUP($E12,$E$79:$F$90,2,0),0))) -> 0 | K45: =IF(K$4=$G12,$D45*(12-VLOOKUP($E12,$E$79:$F$90,2,0)),IF(AND(K$4>$G12,K$4<($G12+$D12)),$D45*12,IF(K$4=($G12+$D12),$D45*VLOOKUP($E12,$E$79:$F$90,2,0),0))) -> 0 | L45: =IF(L$4=$G12,$D45*(12-VLOOKUP($E12,$E$79:$F$90,2,0)),IF(AND(L$4>$G12,L$4<($G12+$D12)),$D45*12,IF(L$4=($G12+$D12),$D45*VLOOKUP($E12,$E$79:$F$90,2,0),0))) -> 0 | M45: =IF(M$4=$G12,$D45*(12-VLOOKUP($E12,$E$79:$F$90,2,0)),IF(AND(M$4>$G12,M$4<($G12+$D12)),$D45*12,IF(M$4=($G12+$D12),$D45*VLOOKUP($E12,$E$79:$F$90,2,0),0))) -> 0 | N45: =IF(N$4=$G12,$D45*(12-VLOOKUP($E12,$E$79:$F$90,2,0)),IF(AND(N$4>$G12,N$4<($G12+$D12)),$D45*12,IF(N$4=($G12+$D12),$D45*VLOOKUP($E12,$E$79:$F$90,2,0),0))) -> 0 | O45: =IF(O$4=$G12,$D45*(12-VLOOKUP($E12,$E$79:$F$90,2,0)),IF(AND(O$4>$G12,O$4<($G12+$D12)),$D45*12,IF(O$4=($G12+$D12),$D45*VLOOKUP($E12,$E$79:$F$90,2,0),0))) -> 0 | ... AJ45: =IF(AJ$4=$G12,$D45*(12-VLOOKUP($E12,$E$79:$F$90,2,0)),IF(AND(AJ$4>$G12,AJ$4<($G12+$D12)),$D45*12,IF(AJ$4=($G12+$D12),$D45*VLOOKUP($E12,$E$79:$F$90,2,0),0))) -> 0 | AK45: =SUM(H45:AJ45) -> 0 | AN45: =AN12 -> 7 | AO45: =AO12 -> 0 | AP45: =IFERROR(BW12/AP12/12,0) -> 0 | AT45: =IF(AT$4=$AS12,$AP45*(12-VLOOKUP($AQ12,$E$79:$F$90,2,0)),IF(AND(AT$4>$AS12,AT$4<($AS12+$AP12)),$AP45*12,IF(AT$4=($AS12+$AP12),$AP45*VLOOKUP($AQ12,$E$79:$F$90,2,0),0))) -> 0 | AU45: =IF(AU$4=$AS12,$AP45*(12-VLOOKUP($AQ12,$E$79:$F$90,2,0)),IF(AND(AU$4>$AS12,AU$4<($AS12+$AP12)),$AP45*12,IF(AU$4=($AS12+$AP12),$AP45*VLOOKUP($AQ12,$E$79:$F$90,2,0),0))) -> 0 | AV45: =IF(AV$4=$AS12,$AP45*(12-VLOOKUP($AQ12,$E$79:$F$90,2,0)),IF(AND(AV$4>$AS12,AV$4<($AS12+$AP12)),$AP45*12,IF(AV$4=($AS12+$AP12),$AP45*VLOOKUP($AQ12,$E$79:$F$90,2,0),0))) -> 0 | AW45: =IF(AW$4=$AS12,$AP45*(12-VLOOKUP($AQ12,$E$79:$F$90,2,0)),IF(AND(AW$4>$AS12,AW$4<($AS12+$AP12)),$AP45*12,IF(AW$4=($AS12+$AP12),$AP45*VLOOKUP($AQ12,$E$79:$F$90,2,0),0))) -> 0 | AX45: =IF(AX$4=$AS12,$AP45*(12-VLOOKUP($AQ12,$E$79:$F$90,2,0)),IF(AND(AX$4>$AS12,AX$4<($AS12+$AP12)),$AP45*12,IF(AX$4=($AS12+$AP12),$AP45*VLOOKUP($AQ12,$E$79:$F$90,2,0),0))) -> 0 | AY45: =IF(AY$4=$AS12,$AP45*(12-VLOOKUP($AQ12,$E$79:$F$90,2,0)),IF(AND(AY$4>$AS12,AY$4<($AS12+$AP12)),$AP45*12,IF(AY$4=($AS12+$AP12),$AP45*VLOOKUP($AQ12,$E$79:$F$90,2,0),0))) -> 0 | AZ45: =IF(AZ$4=$AS12,$AP45*(12-VLOOKUP($AQ12,$E$79:$F$90,2,0)),IF(AND(AZ$4>$AS12,AZ$4<($AS12+$AP12)),$AP45*12,IF(AZ$4=($AS12+$AP12),$AP45*VLOOKUP($AQ12,$E$79:$F$90,2,0),0))) -> 0 | BA45: =IF(BA$4=$AS12,$AP45*(12-VLOOKUP($AQ12,$E$79:$F$90,2,0)),IF(AND(BA$4>$AS12,BA$4<($AS12+$AP12)),$AP45*12,IF(BA$4=($AS12+$AP12),$AP45*VLOOKUP($AQ12,$E$79:$F$90,2,0),0))) -> 0 | ... BV45: =IF(BV$4=$AS12,$AP45*(12-VLOOKUP($AQ12,$E$79:$F$90,2,0)),IF(AND(BV$4>$AS12,BV$4<($AS12+$AP12)),$AP45*12,IF(BV$4=($AS12+$AP12),$AP45*VLOOKUP($AQ12,$E$79:$F$90,2,0),0))) -> 0 | BW45: =SUM(AT45:BV45) -> 0
B46: =B13 -> 8 | C46: =C13 -> 0 | D46: =IFERROR(AK13/D13/12,0) -> 0 | H46: =IF(H$4=$G13,$D46*(12-VLOOKUP($E13,$E$79:$F$90,2,0)),IF(AND(H$4>$G13,H$4<($G13+$D13)),$D46*12,IF(H$4=($G13+$D13),$D46*VLOOKUP($E13,$E$79:$F$90,2,0),0))) -> 0 | I46: =IF(I$4=$G13,$D46*(12-VLOOKUP($E13,$E$79:$F$90,2,0)),IF(AND(I$4>$G13,I$4<($G13+$D13)),$D46*12,IF(I$4=($G13+$D13),$D46*VLOOKUP($E13,$E$79:$F$90,2,0),0))) -> 0 | J46: =IF(J$4=$G13,$D46*(12-VLOOKUP($E13,$E$79:$F$90,2,0)),IF(AND(J$4>$G13,J$4<($G13+$D13)),$D46*12,IF(J$4=($G13+$D13),$D46*VLOOKUP($E13,$E$79:$F$90,2,0),0))) -> 0 | K46: =IF(K$4=$G13,$D46*(12-VLOOKUP($E13,$E$79:$F$90,2,0)),IF(AND(K$4>$G13,K$4<($G13+$D13)),$D46*12,IF(K$4=($G13+$D13),$D46*VLOOKUP($E13,$E$79:$F$90,2,0),0))) -> 0 | L46: =IF(L$4=$G13,$D46*(12-VLOOKUP($E13,$E$79:$F$90,2,0)),IF(AND(L$4>$G13,L$4<($G13+$D13)),$D46*12,IF(L$4=($G13+$D13),$D46*VLOOKUP($E13,$E$79:$F$90,2,0),0))) -> 0 | M46: =IF(M$4=$G13,$D46*(12-VLOOKUP($E13,$E$79:$F$90,2,0)),IF(AND(M$4>$G13,M$4<($G13+$D13)),$D46*12,IF(M$4=($G13+$D13),$D46*VLOOKUP($E13,$E$79:$F$90,2,0),0))) -> 0 | N46: =IF(N$4=$G13,$D46*(12-VLOOKUP($E13,$E$79:$F$90,2,0)),IF(AND(N$4>$G13,N$4<($G13+$D13)),$D46*12,IF(N$4=($G13+$D13),$D46*VLOOKUP($E13,$E$79:$F$90,2,0),0))) -> 0 | O46: =IF(O$4=$G13,$D46*(12-VLOOKUP($E13,$E$79:$F$90,2,0)),IF(AND(O$4>$G13,O$4<($G13+$D13)),$D46*12,IF(O$4=($G13+$D13),$D46*VLOOKUP($E13,$E$79:$F$90,2,0),0))) -> 0 | ... AJ46: =IF(AJ$4=$G13,$D46*(12-VLOOKUP($E13,$E$79:$F$90,2,0)),IF(AND(AJ$4>$G13,AJ$4<($G13+$D13)),$D46*12,IF(AJ$4=($G13+$D13),$D46*VLOOKUP($E13,$E$79:$F$90,2,0),0))) -> 0 | AK46: =SUM(H46:AJ46) -> 0 | AN46: =AN13 -> 8 | AO46: =AO13 -> 0 | AP46: =IFERROR(BW13/AP13/12,0) -> 0 | AT46: =IF(AT$4=$AS13,$AP46*(12-VLOOKUP($AQ13,$E$79:$F$90,2,0)),IF(AND(AT$4>$AS13,AT$4<($AS13+$AP13)),$AP46*12,IF(AT$4=($AS13+$AP13),$AP46*VLOOKUP($AQ13,$E$79:$F$90,2,0),0))) -> 0 | AU46: =IF(AU$4=$AS13,$AP46*(12-VLOOKUP($AQ13,$E$79:$F$90,2,0)),IF(AND(AU$4>$AS13,AU$4<($AS13+$AP13)),$AP46*12,IF(AU$4=($AS13+$AP13),$AP46*VLOOKUP($AQ13,$E$79:$F$90,2,0),0))) -> 0 | AV46: =IF(AV$4=$AS13,$AP46*(12-VLOOKUP($AQ13,$E$79:$F$90,2,0)),IF(AND(AV$4>$AS13,AV$4<($AS13+$AP13)),$AP46*12,IF(AV$4=($AS13+$AP13),$AP46*VLOOKUP($AQ13,$E$79:$F$90,2,0),0))) -> 0 | AW46: =IF(AW$4=$AS13,$AP46*(12-VLOOKUP($AQ13,$E$79:$F$90,2,0)),IF(AND(AW$4>$AS13,AW$4<($AS13+$AP13)),$AP46*12,IF(AW$4=($AS13+$AP13),$AP46*VLOOKUP($AQ13,$E$79:$F$90,2,0),0))) -> 0 | AX46: =IF(AX$4=$AS13,$AP46*(12-VLOOKUP($AQ13,$E$79:$F$90,2,0)),IF(AND(AX$4>$AS13,AX$4<($AS13+$AP13)),$AP46*12,IF(AX$4=($AS13+$AP13),$AP46*VLOOKUP($AQ13,$E$79:$F$90,2,0),0))) -> 0 | AY46: =IF(AY$4=$AS13,$AP46*(12-VLOOKUP($AQ13,$E$79:$F$90,2,0)),IF(AND(AY$4>$AS13,AY$4<($AS13+$AP13)),$AP46*12,IF(AY$4=($AS13+$AP13),$AP46*VLOOKUP($AQ13,$E$79:$F$90,2,0),0))) -> 0 | AZ46: =IF(AZ$4=$AS13,$AP46*(12-VLOOKUP($AQ13,$E$79:$F$90,2,0)),IF(AND(AZ$4>$AS13,AZ$4<($AS13+$AP13)),$AP46*12,IF(AZ$4=($AS13+$AP13),$AP46*VLOOKUP($AQ13,$E$79:$F$90,2,0),0))) -> 0 | BA46: =IF(BA$4=$AS13,$AP46*(12-VLOOKUP($AQ13,$E$79:$F$90,2,0)),IF(AND(BA$4>$AS13,BA$4<($AS13+$AP13)),$AP46*12,IF(BA$4=($AS13+$AP13),$AP46*VLOOKUP($AQ13,$E$79:$F$90,2,0),0))) -> 0 | ... BV46: =IF(BV$4=$AS13,$AP46*(12-VLOOKUP($AQ13,$E$79:$F$90,2,0)),IF(AND(BV$4>$AS13,BV$4<($AS13+$AP13)),$AP46*12,IF(BV$4=($AS13+$AP13),$AP46*VLOOKUP($AQ13,$E$79:$F$90,2,0),0))) -> 0 | BW46: =SUM(AT46:BV46) -> 0
B47: =B14 -> 9 | C47: =C14 -> 0 | D47: =IFERROR(AK14/D14/12,0) -> 0 | H47: =IF(H$4=$G14,$D47*(12-VLOOKUP($E14,$E$79:$F$90,2,0)),IF(AND(H$4>$G14,H$4<($G14+$D14)),$D47*12,IF(H$4=($G14+$D14),$D47*VLOOKUP($E14,$E$79:$F$90,2,0),0))) -> 0 | I47: =IF(I$4=$G14,$D47*(12-VLOOKUP($E14,$E$79:$F$90,2,0)),IF(AND(I$4>$G14,I$4<($G14+$D14)),$D47*12,IF(I$4=($G14+$D14),$D47*VLOOKUP($E14,$E$79:$F$90,2,0),0))) -> 0 | J47: =IF(J$4=$G14,$D47*(12-VLOOKUP($E14,$E$79:$F$90,2,0)),IF(AND(J$4>$G14,J$4<($G14+$D14)),$D47*12,IF(J$4=($G14+$D14),$D47*VLOOKUP($E14,$E$79:$F$90,2,0),0))) -> 0 | K47: =IF(K$4=$G14,$D47*(12-VLOOKUP($E14,$E$79:$F$90,2,0)),IF(AND(K$4>$G14,K$4<($G14+$D14)),$D47*12,IF(K$4=($G14+$D14),$D47*VLOOKUP($E14,$E$79:$F$90,2,0),0))) -> 0 | L47: =IF(L$4=$G14,$D47*(12-VLOOKUP($E14,$E$79:$F$90,2,0)),IF(AND(L$4>$G14,L$4<($G14+$D14)),$D47*12,IF(L$4=($G14+$D14),$D47*VLOOKUP($E14,$E$79:$F$90,2,0),0))) -> 0 | M47: =IF(M$4=$G14,$D47*(12-VLOOKUP($E14,$E$79:$F$90,2,0)),IF(AND(M$4>$G14,M$4<($G14+$D14)),$D47*12,IF(M$4=($G14+$D14),$D47*VLOOKUP($E14,$E$79:$F$90,2,0),0))) -> 0 | N47: =IF(N$4=$G14,$D47*(12-VLOOKUP($E14,$E$79:$F$90,2,0)),IF(AND(N$4>$G14,N$4<($G14+$D14)),$D47*12,IF(N$4=($G14+$D14),$D47*VLOOKUP($E14,$E$79:$F$90,2,0),0))) -> 0 | O47: =IF(O$4=$G14,$D47*(12-VLOOKUP($E14,$E$79:$F$90,2,0)),IF(AND(O$4>$G14,O$4<($G14+$D14)),$D47*12,IF(O$4=($G14+$D14),$D47*VLOOKUP($E14,$E$79:$F$90,2,0),0))) -> 0 | ... AJ47: =IF(AJ$4=$G14,$D47*(12-VLOOKUP($E14,$E$79:$F$90,2,0)),IF(AND(AJ$4>$G14,AJ$4<($G14+$D14)),$D47*12,IF(AJ$4=($G14+$D14),$D47*VLOOKUP($E14,$E$79:$F$90,2,0),0))) -> 0 | AK47: =SUM(H47:AJ47) -> 0 | AN47: =AN14 -> 9 | AO47: =AO14 -> 0 | AP47: =IFERROR(BW14/AP14/12,0) -> 0 | AT47: =IF(AT$4=$AS14,$AP47*(12-VLOOKUP($AQ14,$E$79:$F$90,2,0)),IF(AND(AT$4>$AS14,AT$4<($AS14+$AP14)),$AP47*12,IF(AT$4=($AS14+$AP14),$AP47*VLOOKUP($AQ14,$E$79:$F$90,2,0),0))) -> 0 | AU47: =IF(AU$4=$AS14,$AP47*(12-VLOOKUP($AQ14,$E$79:$F$90,2,0)),IF(AND(AU$4>$AS14,AU$4<($AS14+$AP14)),$AP47*12,IF(AU$4=($AS14+$AP14),$AP47*VLOOKUP($AQ14,$E$79:$F$90,2,0),0))) -> 0 | AV47: =IF(AV$4=$AS14,$AP47*(12-VLOOKUP($AQ14,$E$79:$F$90,2,0)),IF(AND(AV$4>$AS14,AV$4<($AS14+$AP14)),$AP47*12,IF(AV$4=($AS14+$AP14),$AP47*VLOOKUP($AQ14,$E$79:$F$90,2,0),0))) -> 0 | AW47: =IF(AW$4=$AS14,$AP47*(12-VLOOKUP($AQ14,$E$79:$F$90,2,0)),IF(AND(AW$4>$AS14,AW$4<($AS14+$AP14)),$AP47*12,IF(AW$4=($AS14+$AP14),$AP47*VLOOKUP($AQ14,$E$79:$F$90,2,0),0))) -> 0 | AX47: =IF(AX$4=$AS14,$AP47*(12-VLOOKUP($AQ14,$E$79:$F$90,2,0)),IF(AND(AX$4>$AS14,AX$4<($AS14+$AP14)),$AP47*12,IF(AX$4=($AS14+$AP14),$AP47*VLOOKUP($AQ14,$E$79:$F$90,2,0),0))) -> 0 | AY47: =IF(AY$4=$AS14,$AP47*(12-VLOOKUP($AQ14,$E$79:$F$90,2,0)),IF(AND(AY$4>$AS14,AY$4<($AS14+$AP14)),$AP47*12,IF(AY$4=($AS14+$AP14),$AP47*VLOOKUP($AQ14,$E$79:$F$90,2,0),0))) -> 0 | AZ47: =IF(AZ$4=$AS14,$AP47*(12-VLOOKUP($AQ14,$E$79:$F$90,2,0)),IF(AND(AZ$4>$AS14,AZ$4<($AS14+$AP14)),$AP47*12,IF(AZ$4=($AS14+$AP14),$AP47*VLOOKUP($AQ14,$E$79:$F$90,2,0),0))) -> 0 | BA47: =IF(BA$4=$AS14,$AP47*(12-VLOOKUP($AQ14,$E$79:$F$90,2,0)),IF(AND(BA$4>$AS14,BA$4<($AS14+$AP14)),$AP47*12,IF(BA$4=($AS14+$AP14),$AP47*VLOOKUP($AQ14,$E$79:$F$90,2,0),0))) -> 0 | ... BV47: =IF(BV$4=$AS14,$AP47*(12-VLOOKUP($AQ14,$E$79:$F$90,2,0)),IF(AND(BV$4>$AS14,BV$4<($AS14+$AP14)),$AP47*12,IF(BV$4=($AS14+$AP14),$AP47*VLOOKUP($AQ14,$E$79:$F$90,2,0),0))) -> 0 | BW47: =SUM(AT47:BV47) -> 0
B48: =B15 -> 10 | C48: =C15 -> JJJ | D48: =IFERROR(AK15/D15/12,0) -> 0 | H48: =IF(H$4=$G15,$D48*(12-VLOOKUP($E15,$E$79:$F$90,2,0)),IF(AND(H$4>$G15,H$4<($G15+$D15)),$D48*12,IF(H$4=($G15+$D15),$D48*VLOOKUP($E15,$E$79:$F$90,2,0),0))) -> 0 | I48: =IF(I$4=$G15,$D48*(12-VLOOKUP($E15,$E$79:$F$90,2,0)),IF(AND(I$4>$G15,I$4<($G15+$D15)),$D48*12,IF(I$4=($G15+$D15),$D48*VLOOKUP($E15,$E$79:$F$90,2,0),0))) -> 0 | J48: =IF(J$4=$G15,$D48*(12-VLOOKUP($E15,$E$79:$F$90,2,0)),IF(AND(J$4>$G15,J$4<($G15+$D15)),$D48*12,IF(J$4=($G15+$D15),$D48*VLOOKUP($E15,$E$79:$F$90,2,0),0))) -> 0 | K48: =IF(K$4=$G15,$D48*(12-VLOOKUP($E15,$E$79:$F$90,2,0)),IF(AND(K$4>$G15,K$4<($G15+$D15)),$D48*12,IF(K$4=($G15+$D15),$D48*VLOOKUP($E15,$E$79:$F$90,2,0),0))) -> 0 | L48: =IF(L$4=$G15,$D48*(12-VLOOKUP($E15,$E$79:$F$90,2,0)),IF(AND(L$4>$G15,L$4<($G15+$D15)),$D48*12,IF(L$4=($G15+$D15),$D48*VLOOKUP($E15,$E$79:$F$90,2,0),0))) -> 0 | M48: =IF(M$4=$G15,$D48*(12-VLOOKUP($E15,$E$79:$F$90,2,0)),IF(AND(M$4>$G15,M$4<($G15+$D15)),$D48*12,IF(M$4=($G15+$D15),$D48*VLOOKUP($E15,$E$79:$F$90,2,0),0))) -> 0 | N48: =IF(N$4=$G15,$D48*(12-VLOOKUP($E15,$E$79:$F$90,2,0)),IF(AND(N$4>$G15,N$4<($G15+$D15)),$D48*12,IF(N$4=($G15+$D15),$D48*VLOOKUP($E15,$E$79:$F$90,2,0),0))) -> 0 | O48: =IF(O$4=$G15,$D48*(12-VLOOKUP($E15,$E$79:$F$90,2,0)),IF(AND(O$4>$G15,O$4<($G15+$D15)),$D48*12,IF(O$4=($G15+$D15),$D48*VLOOKUP($E15,$E$79:$F$90,2,0),0))) -> 0 | ... AJ48: =IF(AJ$4=$G15,$D48*(12-VLOOKUP($E15,$E$79:$F$90,2,0)),IF(AND(AJ$4>$G15,AJ$4<($G15+$D15)),$D48*12,IF(AJ$4=($G15+$D15),$D48*VLOOKUP($E15,$E$79:$F$90,2,0),0))) -> 0 | AK48: =SUM(H48:AJ48) -> 0 | AN48: =AN15 -> 10 | AO48: =AO15 -> 0 | AP48: =IFERROR(BW15/AP15/12,0) -> 0 | AT48: =IF(AT$4=$AS15,$AP48*(12-VLOOKUP($AQ15,$E$79:$F$90,2,0)),IF(AND(AT$4>$AS15,AT$4<($AS15+$AP15)),$AP48*12,IF(AT$4=($AS15+$AP15),$AP48*VLOOKUP($AQ15,$E$79:$F$90,2,0),0))) -> 0 | AU48: =IF(AU$4=$AS15,$AP48*(12-VLOOKUP($AQ15,$E$79:$F$90,2,0)),IF(AND(AU$4>$AS15,AU$4<($AS15+$AP15)),$AP48*12,IF(AU$4=($AS15+$AP15),$AP48*VLOOKUP($AQ15,$E$79:$F$90,2,0),0))) -> 0 | AV48: =IF(AV$4=$AS15,$AP48*(12-VLOOKUP($AQ15,$E$79:$F$90,2,0)),IF(AND(AV$4>$AS15,AV$4<($AS15+$AP15)),$AP48*12,IF(AV$4=($AS15+$AP15),$AP48*VLOOKUP($AQ15,$E$79:$F$90,2,0),0))) -> 0 | AW48: =IF(AW$4=$AS15,$AP48*(12-VLOOKUP($AQ15,$E$79:$F$90,2,0)),IF(AND(AW$4>$AS15,AW$4<($AS15+$AP15)),$AP48*12,IF(AW$4=($AS15+$AP15),$AP48*VLOOKUP($AQ15,$E$79:$F$90,2,0),0))) -> 0 | AX48: =IF(AX$4=$AS15,$AP48*(12-VLOOKUP($AQ15,$E$79:$F$90,2,0)),IF(AND(AX$4>$AS15,AX$4<($AS15+$AP15)),$AP48*12,IF(AX$4=($AS15+$AP15),$AP48*VLOOKUP($AQ15,$E$79:$F$90,2,0),0))) -> 0 | AY48: =IF(AY$4=$AS15,$AP48*(12-VLOOKUP($AQ15,$E$79:$F$90,2,0)),IF(AND(AY$4>$AS15,AY$4<($AS15+$AP15)),$AP48*12,IF(AY$4=($AS15+$AP15),$AP48*VLOOKUP($AQ15,$E$79:$F$90,2,0),0))) -> 0 | AZ48: =IF(AZ$4=$AS15,$AP48*(12-VLOOKUP($AQ15,$E$79:$F$90,2,0)),IF(AND(AZ$4>$AS15,AZ$4<($AS15+$AP15)),$AP48*12,IF(AZ$4=($AS15+$AP15),$AP48*VLOOKUP($AQ15,$E$79:$F$90,2,0),0))) -> 0 | BA48: =IF(BA$4=$AS15,$AP48*(12-VLOOKUP($AQ15,$E$79:$F$90,2,0)),IF(AND(BA$4>$AS15,BA$4<($AS15+$AP15)),$AP48*12,IF(BA$4=($AS15+$AP15),$AP48*VLOOKUP($AQ15,$E$79:$F$90,2,0),0))) -> 0 | ... BV48: =IF(BV$4=$AS15,$AP48*(12-VLOOKUP($AQ15,$E$79:$F$90,2,0)),IF(AND(BV$4>$AS15,BV$4<($AS15+$AP15)),$AP48*12,IF(BV$4=($AS15+$AP15),$AP48*VLOOKUP($AQ15,$E$79:$F$90,2,0),0))) -> 0 | BW48: =SUM(AT48:BV48) -> 0
B49: =B16 -> 11 | C49: =C16 -> KKK | D49: =IFERROR(AK16/D16/12,0) -> 0 | H49: =IF(H$4=$G16,$D49*(12-VLOOKUP($E16,$E$79:$F$90,2,0)),IF(AND(H$4>$G16,H$4<($G16+$D16)),$D49*12,IF(H$4=($G16+$D16),$D49*VLOOKUP($E16,$E$79:$F$90,2,0),0))) -> 0 | I49: =IF(I$4=$G16,$D49*(12-VLOOKUP($E16,$E$79:$F$90,2,0)),IF(AND(I$4>$G16,I$4<($G16+$D16)),$D49*12,IF(I$4=($G16+$D16),$D49*VLOOKUP($E16,$E$79:$F$90,2,0),0))) -> 0 | J49: =IF(J$4=$G16,$D49*(12-VLOOKUP($E16,$E$79:$F$90,2,0)),IF(AND(J$4>$G16,J$4<($G16+$D16)),$D49*12,IF(J$4=($G16+$D16),$D49*VLOOKUP($E16,$E$79:$F$90,2,0),0))) -> 0 | K49: =IF(K$4=$G16,$D49*(12-VLOOKUP($E16,$E$79:$F$90,2,0)),IF(AND(K$4>$G16,K$4<($G16+$D16)),$D49*12,IF(K$4=($G16+$D16),$D49*VLOOKUP($E16,$E$79:$F$90,2,0),0))) -> 0 | L49: =IF(L$4=$G16,$D49*(12-VLOOKUP($E16,$E$79:$F$90,2,0)),IF(AND(L$4>$G16,L$4<($G16+$D16)),$D49*12,IF(L$4=($G16+$D16),$D49*VLOOKUP($E16,$E$79:$F$90,2,0),0))) -> 0 | M49: =IF(M$4=$G16,$D49*(12-VLOOKUP($E16,$E$79:$F$90,2,0)),IF(AND(M$4>$G16,M$4<($G16+$D16)),$D49*12,IF(M$4=($G16+$D16),$D49*VLOOKUP($E16,$E$79:$F$90,2,0),0))) -> 0 | N49: =IF(N$4=$G16,$D49*(12-VLOOKUP($E16,$E$79:$F$90,2,0)),IF(AND(N$4>$G16,N$4<($G16+$D16)),$D49*12,IF(N$4=($G16+$D16),$D49*VLOOKUP($E16,$E$79:$F$90,2,0),0))) -> 0 | O49: =IF(O$4=$G16,$D49*(12-VLOOKUP($E16,$E$79:$F$90,2,0)),IF(AND(O$4>$G16,O$4<($G16+$D16)),$D49*12,IF(O$4=($G16+$D16),$D49*VLOOKUP($E16,$E$79:$F$90,2,0),0))) -> 0 | ... AJ49: =IF(AJ$4=$G16,$D49*(12-VLOOKUP($E16,$E$79:$F$90,2,0)),IF(AND(AJ$4>$G16,AJ$4<($G16+$D16)),$D49*12,IF(AJ$4=($G16+$D16),$D49*VLOOKUP($E16,$E$79:$F$90,2,0),0))) -> 0 | AK49: =SUM(H49:AJ49) -> 0 | AN49: =AN16 -> 11 | AO49: =AO16 -> 0 | AP49: =IFERROR(BW16/AP16/12,0) -> 0 | AT49: =IF(AT$4=$AS16,$AP49*(12-VLOOKUP($AQ16,$E$79:$F$90,2,0)),IF(AND(AT$4>$AS16,AT$4<($AS16+$AP16)),$AP49*12,IF(AT$4=($AS16+$AP16),$AP49*VLOOKUP($AQ16,$E$79:$F$90,2,0),0))) -> 0 | AU49: =IF(AU$4=$AS16,$AP49*(12-VLOOKUP($AQ16,$E$79:$F$90,2,0)),IF(AND(AU$4>$AS16,AU$4<($AS16+$AP16)),$AP49*12,IF(AU$4=($AS16+$AP16),$AP49*VLOOKUP($AQ16,$E$79:$F$90,2,0),0))) -> 0 | AV49: =IF(AV$4=$AS16,$AP49*(12-VLOOKUP($AQ16,$E$79:$F$90,2,0)),IF(AND(AV$4>$AS16,AV$4<($AS16+$AP16)),$AP49*12,IF(AV$4=($AS16+$AP16),$AP49*VLOOKUP($AQ16,$E$79:$F$90,2,0),0))) -> 0 | AW49: =IF(AW$4=$AS16,$AP49*(12-VLOOKUP($AQ16,$E$79:$F$90,2,0)),IF(AND(AW$4>$AS16,AW$4<($AS16+$AP16)),$AP49*12,IF(AW$4=($AS16+$AP16),$AP49*VLOOKUP($AQ16,$E$79:$F$90,2,0),0))) -> 0 | AX49: =IF(AX$4=$AS16,$AP49*(12-VLOOKUP($AQ16,$E$79:$F$90,2,0)),IF(AND(AX$4>$AS16,AX$4<($AS16+$AP16)),$AP49*12,IF(AX$4=($AS16+$AP16),$AP49*VLOOKUP($AQ16,$E$79:$F$90,2,0),0))) -> 0 | AY49: =IF(AY$4=$AS16,$AP49*(12-VLOOKUP($AQ16,$E$79:$F$90,2,0)),IF(AND(AY$4>$AS16,AY$4<($AS16+$AP16)),$AP49*12,IF(AY$4=($AS16+$AP16),$AP49*VLOOKUP($AQ16,$E$79:$F$90,2,0),0))) -> 0 | AZ49: =IF(AZ$4=$AS16,$AP49*(12-VLOOKUP($AQ16,$E$79:$F$90,2,0)),IF(AND(AZ$4>$AS16,AZ$4<($AS16+$AP16)),$AP49*12,IF(AZ$4=($AS16+$AP16),$AP49*VLOOKUP($AQ16,$E$79:$F$90,2,0),0))) -> 0 | BA49: =IF(BA$4=$AS16,$AP49*(12-VLOOKUP($AQ16,$E$79:$F$90,2,0)),IF(AND(BA$4>$AS16,BA$4<($AS16+$AP16)),$AP49*12,IF(BA$4=($AS16+$AP16),$AP49*VLOOKUP($AQ16,$E$79:$F$90,2,0),0))) -> 0 | ... BV49: =IF(BV$4=$AS16,$AP49*(12-VLOOKUP($AQ16,$E$79:$F$90,2,0)),IF(AND(BV$4>$AS16,BV$4<($AS16+$AP16)),$AP49*12,IF(BV$4=($AS16+$AP16),$AP49*VLOOKUP($AQ16,$E$79:$F$90,2,0),0))) -> 0 | BW49: =SUM(AT49:BV49) -> 0
B50: =B17 -> 12 | C50: =C17 -> LLL | D50: =IFERROR(AK17/D17/12,0) -> 0 | H50: =IF(H$4=$G17,$D50*(12-VLOOKUP($E17,$E$79:$F$90,2,0)),IF(AND(H$4>$G17,H$4<($G17+$D17)),$D50*12,IF(H$4=($G17+$D17),$D50*VLOOKUP($E17,$E$79:$F$90,2,0),0))) -> 0 | I50: =IF(I$4=$G17,$D50*(12-VLOOKUP($E17,$E$79:$F$90,2,0)),IF(AND(I$4>$G17,I$4<($G17+$D17)),$D50*12,IF(I$4=($G17+$D17),$D50*VLOOKUP($E17,$E$79:$F$90,2,0),0))) -> 0 | J50: =IF(J$4=$G17,$D50*(12-VLOOKUP($E17,$E$79:$F$90,2,0)),IF(AND(J$4>$G17,J$4<($G17+$D17)),$D50*12,IF(J$4=($G17+$D17),$D50*VLOOKUP($E17,$E$79:$F$90,2,0),0))) -> 0 | K50: =IF(K$4=$G17,$D50*(12-VLOOKUP($E17,$E$79:$F$90,2,0)),IF(AND(K$4>$G17,K$4<($G17+$D17)),$D50*12,IF(K$4=($G17+$D17),$D50*VLOOKUP($E17,$E$79:$F$90,2,0),0))) -> 0 | L50: =IF(L$4=$G17,$D50*(12-VLOOKUP($E17,$E$79:$F$90,2,0)),IF(AND(L$4>$G17,L$4<($G17+$D17)),$D50*12,IF(L$4=($G17+$D17),$D50*VLOOKUP($E17,$E$79:$F$90,2,0),0))) -> 0 | M50: =IF(M$4=$G17,$D50*(12-VLOOKUP($E17,$E$79:$F$90,2,0)),IF(AND(M$4>$G17,M$4<($G17+$D17)),$D50*12,IF(M$4=($G17+$D17),$D50*VLOOKUP($E17,$E$79:$F$90,2,0),0))) -> 0 | N50: =IF(N$4=$G17,$D50*(12-VLOOKUP($E17,$E$79:$F$90,2,0)),IF(AND(N$4>$G17,N$4<($G17+$D17)),$D50*12,IF(N$4=($G17+$D17),$D50*VLOOKUP($E17,$E$79:$F$90,2,0),0))) -> 0 | O50: =IF(O$4=$G17,$D50*(12-VLOOKUP($E17,$E$79:$F$90,2,0)),IF(AND(O$4>$G17,O$4<($G17+$D17)),$D50*12,IF(O$4=($G17+$D17),$D50*VLOOKUP($E17,$E$79:$F$90,2,0),0))) -> 0 | ... AJ50: =IF(AJ$4=$G17,$D50*(12-VLOOKUP($E17,$E$79:$F$90,2,0)),IF(AND(AJ$4>$G17,AJ$4<($G17+$D17)),$D50*12,IF(AJ$4=($G17+$D17),$D50*VLOOKUP($E17,$E$79:$F$90,2,0),0))) -> 0 | AK50: =SUM(H50:AJ50) -> 0 | AN50: =AN17 -> 12 | AO50: =AO17 -> LLL | AP50: =IFERROR(BW17/AP17/12,0) -> 0 | AT50: =IF(AT$4=$AS17,$AP50*(12-VLOOKUP($AQ17,$E$79:$F$90,2,0)),IF(AND(AT$4>$AS17,AT$4<($AS17+$AP17)),$AP50*12,IF(AT$4=($AS17+$AP17),$AP50*VLOOKUP($AQ17,$E$79:$F$90,2,0),0))) -> 0 | AU50: =IF(AU$4=$AS17,$AP50*(12-VLOOKUP($AQ17,$E$79:$F$90,2,0)),IF(AND(AU$4>$AS17,AU$4<($AS17+$AP17)),$AP50*12,IF(AU$4=($AS17+$AP17),$AP50*VLOOKUP($AQ17,$E$79:$F$90,2,0),0))) -> 0 | AV50: =IF(AV$4=$AS17,$AP50*(12-VLOOKUP($AQ17,$E$79:$F$90,2,0)),IF(AND(AV$4>$AS17,AV$4<($AS17+$AP17)),$AP50*12,IF(AV$4=($AS17+$AP17),$AP50*VLOOKUP($AQ17,$E$79:$F$90,2,0),0))) -> 0 | AW50: =IF(AW$4=$AS17,$AP50*(12-VLOOKUP($AQ17,$E$79:$F$90,2,0)),IF(AND(AW$4>$AS17,AW$4<($AS17+$AP17)),$AP50*12,IF(AW$4=($AS17+$AP17),$AP50*VLOOKUP($AQ17,$E$79:$F$90,2,0),0))) -> 0 | AX50: =IF(AX$4=$AS17,$AP50*(12-VLOOKUP($AQ17,$E$79:$F$90,2,0)),IF(AND(AX$4>$AS17,AX$4<($AS17+$AP17)),$AP50*12,IF(AX$4=($AS17+$AP17),$AP50*VLOOKUP($AQ17,$E$79:$F$90,2,0),0))) -> 0 | AY50: =IF(AY$4=$AS17,$AP50*(12-VLOOKUP($AQ17,$E$79:$F$90,2,0)),IF(AND(AY$4>$AS17,AY$4<($AS17+$AP17)),$AP50*12,IF(AY$4=($AS17+$AP17),$AP50*VLOOKUP($AQ17,$E$79:$F$90,2,0),0))) -> 0 | AZ50: =IF(AZ$4=$AS17,$AP50*(12-VLOOKUP($AQ17,$E$79:$F$90,2,0)),IF(AND(AZ$4>$AS17,AZ$4<($AS17+$AP17)),$AP50*12,IF(AZ$4=($AS17+$AP17),$AP50*VLOOKUP($AQ17,$E$79:$F$90,2,0),0))) -> 0 | BA50: =IF(BA$4=$AS17,$AP50*(12-VLOOKUP($AQ17,$E$79:$F$90,2,0)),IF(AND(BA$4>$AS17,BA$4<($AS17+$AP17)),$AP50*12,IF(BA$4=($AS17+$AP17),$AP50*VLOOKUP($AQ17,$E$79:$F$90,2,0),0))) -> 0 | ... BV50: =IF(BV$4=$AS17,$AP50*(12-VLOOKUP($AQ17,$E$79:$F$90,2,0)),IF(AND(BV$4>$AS17,BV$4<($AS17+$AP17)),$AP50*12,IF(BV$4=($AS17+$AP17),$AP50*VLOOKUP($AQ17,$E$79:$F$90,2,0),0))) -> 0 | BW50: =SUM(AT50:BV50) -> 0
... B68: =B35 -> 30 | C68: =C35 -> DD1 | D68: =IFERROR(AK35/D35/12,0) -> 0 | H68: =IF(H$4=$G35,$D68*(12-VLOOKUP($E35,$E$79:$F$90,2,0)),IF(AND(H$4>$G35,H$4<($G35+$D35)),$D68*12,IF(H$4=($G35+$D35),$D68*VLOOKUP($E35,$E$79:$F$90,2,0),0))) -> 0 | I68: =IF(I$4=$G35,$D68*(12-VLOOKUP($E35,$E$79:$F$90,2,0)),IF(AND(I$4>$G35,I$4<($G35+$D35)),$D68*12,IF(I$4=($G35+$D35),$D68*VLOOKUP($E35,$E$79:$F$90,2,0),0))) -> 0 | J68: =IF(J$4=$G35,$D68*(12-VLOOKUP($E35,$E$79:$F$90,2,0)),IF(AND(J$4>$G35,J$4<($G35+$D35)),$D68*12,IF(J$4=($G35+$D35),$D68*VLOOKUP($E35,$E$79:$F$90,2,0),0))) -> 0 | K68: =IF(K$4=$G35,$D68*(12-VLOOKUP($E35,$E$79:$F$90,2,0)),IF(AND(K$4>$G35,K$4<($G35+$D35)),$D68*12,IF(K$4=($G35+$D35),$D68*VLOOKUP($E35,$E$79:$F$90,2,0),0))) -> 0 | L68: =IF(L$4=$G35,$D68*(12-VLOOKUP($E35,$E$79:$F$90,2,0)),IF(AND(L$4>$G35,L$4<($G35+$D35)),$D68*12,IF(L$4=($G35+$D35),$D68*VLOOKUP($E35,$E$79:$F$90,2,0),0))) -> 0 | M68: =IF(M$4=$G35,$D68*(12-VLOOKUP($E35,$E$79:$F$90,2,0)),IF(AND(M$4>$G35,M$4<($G35+$D35)),$D68*12,IF(M$4=($G35+$D35),$D68*VLOOKUP($E35,$E$79:$F$90,2,0),0))) -> 0 | N68: =IF(N$4=$G35,$D68*(12-VLOOKUP($E35,$E$79:$F$90,2,0)),IF(AND(N$4>$G35,N$4<($G35+$D35)),$D68*12,IF(N$4=($G35+$D35),$D68*VLOOKUP($E35,$E$79:$F$90,2,0),0))) -> 0 | O68: =IF(O$4=$G35,$D68*(12-VLOOKUP($E35,$E$79:$F$90,2,0)),IF(AND(O$4>$G35,O$4<($G35+$D35)),$D68*12,IF(O$4=($G35+$D35),$D68*VLOOKUP($E35,$E$79:$F$90,2,0),0))) -> 0 | ... AJ68: =IF(AJ$4=$G35,$D68*(12-VLOOKUP($E35,$E$79:$F$90,2,0)),IF(AND(AJ$4>$G35,AJ$4<($G35+$D35)),$D68*12,IF(AJ$4=($G35+$D35),$D68*VLOOKUP($E35,$E$79:$F$90,2,0),0))) -> 0 | AK68: =SUM(H68:AJ68) -> 0 | AN68: =AN35 -> 30 | AO68: =AO35 -> DD1 | AP68: =IFERROR(BW35/AP35/12,0) -> 0 | AT68: =IF(AT$4=$AS35,$AP68*(12-VLOOKUP($AQ35,$E$79:$F$90,2,0)),IF(AND(AT$4>$AS35,AT$4<($AS35+$AP35)),$AP68*12,IF(AT$4=($AS35+$AP35),$AP68*VLOOKUP($AQ35,$E$79:$F$90,2,0),0))) -> 0 | AU68: =IF(AU$4=$AS35,$AP68*(12-VLOOKUP($AQ35,$E$79:$F$90,2,0)),IF(AND(AU$4>$AS35,AU$4<($AS35+$AP35)),$AP68*12,IF(AU$4=($AS35+$AP35),$AP68*VLOOKUP($AQ35,$E$79:$F$90,2,0),0))) -> 0 | AV68: =IF(AV$4=$AS35,$AP68*(12-VLOOKUP($AQ35,$E$79:$F$90,2,0)),IF(AND(AV$4>$AS35,AV$4<($AS35+$AP35)),$AP68*12,IF(AV$4=($AS35+$AP35),$AP68*VLOOKUP($AQ35,$E$79:$F$90,2,0),0))) -> 0 | AW68: =IF(AW$4=$AS35,$AP68*(12-VLOOKUP($AQ35,$E$79:$F$90,2,0)),IF(AND(AW$4>$AS35,AW$4<($AS35+$AP35)),$AP68*12,IF(AW$4=($AS35+$AP35),$AP68*VLOOKUP($AQ35,$E$79:$F$90,2,0),0))) -> 0 | AX68: =IF(AX$4=$AS35,$AP68*(12-VLOOKUP($AQ35,$E$79:$F$90,2,0)),IF(AND(AX$4>$AS35,AX$4<($AS35+$AP35)),$AP68*12,IF(AX$4=($AS35+$AP35),$AP68*VLOOKUP($AQ35,$E$79:$F$90,2,0),0))) -> 0 | AY68: =IF(AY$4=$AS35,$AP68*(12-VLOOKUP($AQ35,$E$79:$F$90,2,0)),IF(AND(AY$4>$AS35,AY$4<($AS35+$AP35)),$AP68*12,IF(AY$4=($AS35+$AP35),$AP68*VLOOKUP($AQ35,$E$79:$F$90,2,0),0))) -> 0 | AZ68: =IF(AZ$4=$AS35,$AP68*(12-VLOOKUP($AQ35,$E$79:$F$90,2,0)),IF(AND(AZ$4>$AS35,AZ$4<($AS35+$AP35)),$AP68*12,IF(AZ$4=($AS35+$AP35),$AP68*VLOOKUP($AQ35,$E$79:$F$90,2,0),0))) -> 0 | BA68: =IF(BA$4=$AS35,$AP68*(12-VLOOKUP($AQ35,$E$79:$F$90,2,0)),IF(AND(BA$4>$AS35,BA$4<($AS35+$AP35)),$AP68*12,IF(BA$4=($AS35+$AP35),$AP68*VLOOKUP($AQ35,$E$79:$F$90,2,0),0))) -> 0 | ... BV68: =IF(BV$4=$AS35,$AP68*(12-VLOOKUP($AQ35,$E$79:$F$90,2,0)),IF(AND(BV$4>$AS35,BV$4<($AS35+$AP35)),$AP68*12,IF(BV$4=($AS35+$AP35),$AP68*VLOOKUP($AQ35,$E$79:$F$90,2,0),0))) -> 0 | BW68: =SUM(AT68:BV68) -> 0
C69: Total Depreciation on Capital Employed | H69: =SUM(H39:H68) -> 0 | I69: =SUM(I39:I68) -> 0 | J69: =SUM(J39:J68) -> 0 | K69: =SUM(K39:K68) -> 0 | L69: =SUM(L39:L68) -> 0 | M69: =SUM(M39:M68) -> 0 | N69: =SUM(N39:N68) -> 0 | O69: =SUM(O39:O68) -> 0 | ... AK69: =SUM(AK39:AK68) -> 0 | AO69: Total Depreciation on Capital Employed | AT69: =SUM(AT39:AT68) -> 0 | AU69: =SUM(AU39:AU68) -> 0 | AV69: =SUM(AV39:AV68) -> 0 | AW69: =SUM(AW39:AW68) -> 0 | AX69: =SUM(AX39:AX68) -> 0 | AY69: =SUM(AY39:AY68) -> 0 | AZ69: =SUM(AZ39:AZ68) -> 0 | BA69: =SUM(BA39:BA68) -> 0 | ... BW69: =SUM(BW39:BW68) -> 0
E79: Jan | F79: 4
E80: Feb | F80: 5
E81: Mar | F81: 6
E82: Apr | F82: 7
E83: May | F83: 8
E84: Jun | F84: 9
E85: Jul | F85: 10
E86: Aug | F86: 11
E87: Sep | F87: 12
E88: Oct | F88: 1
E89: Nov | F89: 2
E90: Dec | F90: 3

Sheet PPT
B2: Display $ Figures (K or M) | D2: $ M
B4: ="Revenue and Profitability ("&D2&"): Actuals / Projections vs. "&Comp -> Revenue and Profitability ($ M): Actuals / Projections vs. Def Exit
E6: =IFERROR(IF(Calc!G$113=ASRFY,"ASR",IF(Calc!G$113=ASRFY+1,"ASR",IF(Calc!G$113=ASRFY+2,"ASR",0))),0) -> 0 | G6: =IFERROR(IF(Calc!H$113=ASRFY,"ASR",IF(Calc!H$113=ASRFY+1,"ASR",IF(Calc!H$113=ASRFY+2,"ASR",0))),0) -> 0 | I6: =IFERROR(IF(Calc!I$113=ASRFY,"ASR",IF(Calc!I$113=ASRFY+1,"ASR",IF(Calc!I$113=ASRFY+2,"ASR",0))),0) -> 0 | K6: =IFERROR(IF(Calc!J$113=ASRFY,"ASR",IF(Calc!J$113=ASRFY+1,"ASR",IF(Calc!J$113=ASRFY+2,"ASR",0))),0) -> 0 | M6: =IFERROR(IF(Calc!K$113=ASRFY,"ASR",IF(Calc!K$113=ASRFY+1,"ASR",IF(Calc!K$113=ASRFY+2,"ASR",0))),0) -> 0 | O6: =IFERROR(IF(Calc!L$113=ASRFY,"ASR",IF(Calc!L$113=ASRFY+1,"ASR",IF(Calc!L$113=ASRFY+2,"ASR",0))),0) -> 0 | Q6: =IFERROR(IF(Calc!M$113=ASRFY,"ASR",IF(Calc!M$113=ASRFY+1,"ASR",IF(Calc!M$113=ASRFY+2,"ASR",0))),0) -> 0 | S6: =IFERROR(IF(Calc!N$113=ASRFY,"ASR",IF(Calc!N$113=ASRFY+1,"ASR",IF(Calc!N$113=ASRFY+2,"ASR",0))),0) -> 0 | U6: =IFERROR(IF(Calc!O$113=ASRFY,"ASR",IF(Calc!O$113=ASRFY+1,"ASR",IF(Calc!O$113=ASRFY+2,"ASR",0))),0) -> 0 | W6: =IFERROR(IF(Calc!P$113=ASRFY,"ASR",IF(Calc!P$113=ASRFY+1,"ASR",IF(Calc!P$113=ASRFY+2,"ASR",0))),0) -> 0 | Y6: =IFERROR(IF(Calc!Q$113=ASRFY,"ASR",IF(Calc!Q$113=ASRFY+1,"ASR",IF(Calc!Q$113=ASRFY+2,"ASR",0))),0) -> 0 | AA6: =IFERROR(IF(Calc!R$113=ASRFY,"ASR",IF(Calc!R$113=ASRFY+1,"ASR",IF(Calc!R$113=ASRFY+2,"ASR",0))),0) -> 0 | AC6: =IFERROR(IF(Calc!S$113=ASRFY,"ASR",IF(Calc!S$113=ASRFY+1,"ASR",IF(Calc!S$113=ASRFY+2,"ASR",0))),0) -> 0 | AE6: =IFERROR(IF(Calc!T$113=ASRFY,"ASR",IF(Calc!T$113=ASRFY+1,"ASR",IF(Calc!T$113=ASRFY+2,"ASR",0))),0) -> 0 | AG6: =IFERROR(IF(Calc!U$113=ASRFY,"ASR",IF(Calc!U$113=ASRFY+1,"ASR",IF(Calc!U$113=ASRFY+2,"ASR",0))),0) -> 0 | AI6: =IFERROR(IF(Calc!V$113=ASRFY,"ASR",IF(Calc!V$113=ASRFY+1,"ASR",IF(Calc!V$113=ASRFY+2,"ASR",0))),0) -> 0 | AK6: =IFERROR(IF(Calc!W$113=ASRFY,"ASR",IF(Calc!W$113=ASRFY+1,"ASR",IF(Calc!W$113=ASRFY+2,"ASR",0))),0) -> 0 | AM6: =IFERROR(IF(Calc!X$113=ASRFY,"ASR",IF(Calc!X$113=ASRFY+1,"ASR",IF(Calc!X$113=ASRFY+2,"ASR",0))),0) -> 0 | AO6: =IFERROR(IF(Calc!Y$113=ASRFY,"ASR",IF(Calc!Y$113=ASRFY+1,"ASR",IF(Calc!Y$113=ASRFY+2,"ASR",0))),0) -> 0 | AQ6: =IFERROR(IF(Calc!Z$113=ASRFY,"ASR",IF(Calc!Z$113=ASRFY+1,"ASR",IF(Calc!Z$113=ASRFY+2,"ASR",0))),0) -> 0 | AS6: =IFERROR(IF(Calc!AA$113=ASRFY,"ASR",IF(Calc!AA$113=ASRFY+1,"ASR",IF(Calc!AA$113=ASRFY+2,"ASR",0))),0) -> 0 | AU6: =IFERROR(IF(Calc!AB$113=ASRFY,"ASR",IF(Calc!AB$113=ASRFY+1,"ASR",IF(Calc!AB$113=ASRFY+2,"ASR",0))),0) -> 0 | AW6: =IFERROR(IF(Calc!AC$113=ASRFY,"ASR",IF(Calc!AC$113=ASRFY+1,"ASR",IF(Calc!AC$113=ASRFY+2,"ASR",0))),0) -> 0 | AY6: =IFERROR(IF(Calc!AD$113=ASRFY,"ASR",IF(Calc!AD$113=ASRFY+1,"ASR",IF(Calc!AD$113=ASRFY+2,"ASR",0))),0) -> 0 | BA6: =IFERROR(IF(Calc!AE$113=ASRFY,"ASR",IF(Calc!AE$113=ASRFY+1,"ASR",IF(Calc!AE$113=ASRFY+2,"ASR",0))),0) -> 0 | BC6: =IFERROR(IF(Calc!AF$113=ASRFY,"ASR",IF(Calc!AF$113=ASRFY+1,"ASR",IF(Calc!AF$113=ASRFY+2,"ASR",0))),0) -> 0 | BE6: =IFERROR(IF(Calc!AG$113=ASRFY,"ASR",IF(Calc!AG$113=ASRFY+1,"ASR",IF(Calc!AG$113=ASRFY+2,"ASR",0))),0) -> 0 | BG6: =IFERROR(IF(Calc!AH$113=ASRFY,"ASR",IF(Calc!AH$113=ASRFY+1,"ASR",IF(Calc!AH$113=ASRFY+2,"ASR",0))),0) -> 0 | BI6: =IFERROR(IF(Calc!AI$113=ASRFY,"ASR",IF(Calc!AI$113=ASRFY+1,"ASR",IF(Calc!AI$113=ASRFY+2,"ASR",0))),0) -> 0 | BK6: 10 Yr Total | BP6: ="15 Yrs Total" -> 15 Yrs Total
B7: =Calc!B9 -> A | E7: =+Calc!G9 -> FY18 | F7: ="vs "&Comp -> vs Def Exit | G7: =+Calc!H9 -> FY19 | H7: ="vs "&Comp -> vs Def Exit | I7: =+Calc!I9 -> FY20 | J7: ="vs "&Comp -> vs Def Exit | K7: =+Calc!J9 -> FY21 | L7: ="vs "&Comp -> vs Def Exit | M7: =+Calc!K9 -> FY22 | N7: ="vs "&Comp -> vs Def Exit | O7: =+Calc!L9 -> FY23 | P7: ="vs "&Comp -> vs Def Exit | Q7: =+Calc!M9 -> FY24 | R7: ="vs "&Comp -> vs Def Exit | S7: =+Calc!N9 -> FY25 | T7: ="vs "&Comp -> vs Def Exit | U7: =+Calc!O9 -> FY26 | V7: ="vs "&Comp -> vs Def Exit | W7: =+Calc!P9 -> FY27 | X7: ="vs "&Comp -> vs Def Exit | Y7: =+Calc!Q9 -> FY28 | Z7: ="vs "&Comp -> vs Def Exit | AA7: =+Calc!R9 -> FY29 | AB7: ="vs "&Comp -> vs Def Exit | AC7: =+Calc!S9 -> FY30 | AD7: ="vs "&Comp -> vs Def Exit | AE7: =+Calc!T9 -> FY31 | AF7: ="vs "&Comp -> vs Def Exit | AG7: =+Calc!U9 -> FY32 | AH7: ="vs "&Comp -> vs Def Exit | AI7: =+Calc!V9 -> FY33 | AJ7: ="vs "&Comp -> vs Def Exit | AK7: =+Calc!W9 -> FY34 | AL7: ="vs "&Comp -> vs Def Exit | AM7: =+Calc!X9 -> FY35 | AN7: ="vs "&Comp -> vs Def Exit | AO7: =+Calc!Y9 -> FY36 | AP7: ="vs "&Comp -> vs Def Exit | AQ7: =+Calc!Z9 -> FY37 | AR7: ="vs "&Comp -> vs Def Exit | AS7: =+Calc!AA9 -> FY38 | AT7: ="vs "&Comp -> vs Def Exit | AU7: =+Calc!AB9 -> FY39 | AV7: ="vs "&Comp -> vs Def Exit | AW7: =+Calc!AC9 -> FY40 | AX7: ="vs "&Comp -> vs Def Exit | AY7: =+Calc!AD9 -> FY41 | AZ7: ="vs "&Comp -> vs Def Exit | BA7: =+Calc!AE9 -> FY42 | BB7: ="vs "&Comp -> vs Def Exit | BC7: =+Calc!AF9 -> FY43 | BD7: ="vs "&Comp -> vs Def Exit | BE7: =+Calc!AG9 -> FY44 | BF7: ="vs "&Comp -> vs Def Exit | BG7: =+Calc!AH9 -> FY45 | BH7: ="vs "&Comp -> vs Def Exit | BI7: =+Calc!AI9 -> FY46 | BJ7: ="vs "&Comp -> vs Def Exit | BK7: ="FY"&CurrentFY&"-"&CurrentFY+9 -> FY18-27 | BM7: ="vs "&Comp&" H/(L)" -> vs Def Exit H/(L) | BP7: ="FY"&CurrentFY&"-"&CurrentFY+14 -> FY18-32
B9: New Product Volume (k) | E9: =IF($D$2="$ K",Calc!G10,Calc!G10/1000) -> 0 | F9: =IF(Calc!AQ10=0,0,IF($D$2="$ M",Calc!CA10/1000,Calc!CA10)) -> 0 | G9: =IF($D$2="$ K",Calc!H10,Calc!H10/1000) -> 0 | H9: =IF(Calc!AR10=0,0,IF($D$2="$ M",Calc!CB10/1000,Calc!CB10)) -> 0 | I9: =IF($D$2="$ K",Calc!I10,Calc!I10/1000) -> 0 | J9: =IF(Calc!AS10=0,0,IF($D$2="$ M",Calc!CC10/1000,Calc!CC10)) -> 0 | K9: =IF($D$2="$ K",Calc!J10,Calc!J10/1000) -> 0 | L9: =IF(Calc!AT10=0,0,IF($D$2="$ M",Calc!CD10/1000,Calc!CD10)) -> 0 | M9: =IF($D$2="$ K",Calc!K10,Calc!K10/1000) -> 0 | N9: =IF(Calc!AU10=0,0,IF($D$2="$ M",Calc!CE10/1000,Calc!CE10)) -> 0 | O9: =IF($D$2="$ K",Calc!L10,Calc!L10/1000) -> 0.21622318 | P9: =IF(Calc!AV10=0,0,IF($D$2="$ M",Calc!CF10/1000,Calc!CF10)) -> 0 | Q9: =IF($D$2="$ K",Calc!M10,Calc!M10/1000) -> 0.52280131 | R9: =IF(Calc!AW10=0,0,IF($D$2="$ M",Calc!CG10/1000,Calc!CG10)) -> 0 | S9: =IF($D$2="$ K",Calc!N10,Calc!N10/1000) -> 1.0010658 | T9: =IF(Calc!AX10=0,0,IF($D$2="$ M",Calc!CH10/1000,Calc!CH10)) -> 0 | U9: =IF($D$2="$ K",Calc!O10,Calc!O10/1000) -> 1.5085056 | V9: =IF(Calc!AY10=0,0,IF($D$2="$ M",Calc!CI10/1000,Calc!CI10)) -> 0 | W9: =IF($D$2="$ K",Calc!P10,Calc!P10/1000) -> 2.032917 | X9: =IF(Calc!AZ10=0,0,IF($D$2="$ M",Calc!CJ10/1000,Calc!CJ10)) -> 0 | Y9: =IF($D$2="$ K",Calc!Q10,Calc!Q10/1000) -> 2.2744425 | Z9: =IF(Calc!BA10=0,0,IF($D$2="$ M",Calc!CK10/1000,Calc!CK10)) -> 0 | AA9: =IF($D$2="$ K",Calc!R10,Calc!R10/1000) -> 2.6032235 | AB9: =IF(Calc!BB10=0,0,IF($D$2="$ M",Calc!CL10/1000,Calc!CL10)) -> 0 | AC9: =IF($D$2="$ K",Calc!S10,Calc!S10/1000) -> 3.1468227 | AD9: =IF(Calc!BC10=0,0,IF($D$2="$ M",Calc!CM10/1000,Calc!CM10)) -> 0 | AE9: =IF($D$2="$ K",Calc!T10,Calc!T10/1000) -> 3.4628716 | AF9: =IF(Calc!BD10=0,0,IF($D$2="$ M",Calc!CN10/1000,Calc!CN10)) -> 0 | AG9: =IF($D$2="$ K",Calc!U10,Calc!U10/1000) -> 4.1679123 | AH9: =IF(Calc!BE10=0,0,IF($D$2="$ M",Calc!CO10/1000,Calc!CO10)) -> 0 | AI9: =IF($D$2="$ K",Calc!V10,Calc!V10/1000) -> 4.9331019 | AJ9: =IF(Calc!BF10=0,0,IF($D$2="$ M",Calc!CP10/1000,Calc!CP10)) -> 0 | AK9: =IF($D$2="$ K",Calc!W10,Calc!W10/1000) -> 5.6922432 | AL9: =IF(Calc!BG10=0,0,IF($D$2="$ M",Calc!CQ10/1000,Calc!CQ10)) -> 0 | AM9: =IF($D$2="$ K",Calc!X10,Calc!X10/1000) -> 5.4365887 | AN9: =IF(Calc!BH10=0,0,IF($D$2="$ M",Calc!CR10/1000,Calc!CR10)) -> 0 | AO9: =IF($D$2="$ K",Calc!Y10,Calc!Y10/1000) -> 0 | AP9: =IF(Calc!BJ10=0,0,IF($D$2="$ M",Calc!CS10/1000,Calc!CS10)) -> 0 | AQ9: =IF($D$2="$ K",Calc!Z10,Calc!Z10/1000) -> 0 | AR9: =IF(Calc!BL10=0,0,IF($D$2="$ M",Calc!CT10/1000,Calc!CT10)) -> 0 | AS9: =IF($D$2="$ K",Calc!AA10,Calc!AA10/1000) -> 0 | AT9: =IF(Calc!BN10=0,0,IF($D$2="$ M",Calc!CU10/1000,Calc!CU10)) -> 0 | AU9: =IF($D$2="$ K",Calc!AB10,Calc!AB10/1000) -> 0 | AV9: =IF(Calc!BP10=0,0,IF($D$2="$ M",Calc!CV10/1000,Calc!CV10)) -> 0 | AW9: =IF($D$2="$ K",Calc!AC10,Calc!AC10/1000) -> 0 | AX9: =IF(Calc!BR10=0,0,IF($D$2="$ M",Calc!CW10/1000,Calc!CW10)) -> 0 | AY9: =IF($D$2="$ K",Calc!AD10,Calc!AD10/1000) -> 0 | AZ9: =IF(Calc!BT10=0,0,IF($D$2="$ M",Calc!CX10/1000,Calc!CX10)) -> 0 | BA9: =IF($D$2="$ K",Calc!AE10,Calc!AE10/1000) -> 0 | BB9: =IF(Calc!BV10=0,0,IF($D$2="$ M",Calc!CY10/1000,Calc!CY10)) -> 0 | BC9: =IF($D$2="$ K",Calc!AF10,Calc!AF10/1000) -> 0 | BD9: =IF(Calc!BX10=0,0,IF($D$2="$ M",Calc!CZ10/1000,Calc!CZ10)) -> 0 | BE9: =IF($D$2="$ K",Calc!AG10,Calc!AG10/1000) -> 0 | BF9: =IF(Calc!BZ10=0,0,IF($D$2="$ M",Calc!DA10/1000,Calc!DA10)) -> 0 | BG9: =IF($D$2="$ K",Calc!AH10,Calc!AH10/1000) -> 0 | BH9: =IF(Calc!CB10=0,0,IF($D$2="$ M",Calc!DB10/1000,Calc!DB10)) -> 0 | BI9: =IF($D$2="$ K",Calc!AI10,Calc!AI10/1000) -> 0 | BJ9: =IF(Calc!BS10=0,0,IF($D$2="$ M",Calc!DC10/1000,Calc!DC10)) -> 0 | BK9: =IF($D$2="$ K",Calc!AJ10,Calc!AJ10/1000) -> 5.2815129 | BM9: =IF(Calc!BT10=0,0,IF($D$2="$ M",Calc!DD10/1000,Calc!DD10)) -> 0 | BP9: =IF($D$2="$ K",Calc!AM10,Calc!AM10/1000) -> 20.936785
B10: New Product ASP ($) | E10: =+Calc!G11 -> 0 | F10: =IF(Calc!AQ11=0,0,Calc!CA11) -> 0 | G10: =+Calc!H11 -> 0 | H10: =IF(Calc!AR11=0,0,Calc!CB11) -> 0 | I10: =+Calc!I11 -> 0 | J10: =IF(Calc!AS11=0,0,Calc!CC11) -> 0 | K10: =+Calc!J11 -> 0 | L10: =IF(Calc!AT11=0,0,Calc!CD11) -> 0 | M10: =+Calc!K11 -> 0 | N10: =IF(Calc!AU11=0,0,Calc!CE11) -> 0 | O10: =+Calc!L11 -> 77.083333 | P10: =IF(Calc!AV11=0,0,Calc!CF11) -> 0 | Q10: =+Calc!M11 -> 73.773208 | R10: =IF(Calc!AW11=0,0,Calc!CG11) -> 0 | S10: =+Calc!N11 -> 73.445693 | T10: =IF(Calc!AX11=0,0,Calc!CH11) -> 0 | U10: =+Calc!O11 -> 73.131313 | V10: =IF(Calc!AY11=0,0,Calc!CI11) -> 0 | W10: =+Calc!P11 -> 67.558614 | X10: =IF(Calc!AZ11=0,0,Calc!CJ11) -> 0 | Y10: =+Calc!Q11 -> 67.209922 | Z10: =IF(Calc!BA11=0,0,Calc!CK11) -> 0 | AA10: =+Calc!R11 -> 63.668972 | AB10: =IF(Calc!BB11=0,0,Calc!CL11) -> 0 | AC10: =+Calc!S11 -> 60.438699 | AD10: =IF(Calc!BC11=0,0,Calc!CM11) -> 0 | AE10: =+Calc!T11 -> 57.416764 | AF10: =IF(Calc!BD11=0,0,Calc!CN11) -> 0 | AG10: =+Calc!U11 -> 57.416764 | AH10: =IF(Calc!BE11=0,0,Calc!CO11) -> 0 | AI10: =+Calc!V11 -> 54.435329 | AJ10: =IF(Calc!BF11=0,0,Calc!CP11) -> 0 | AK10: =+Calc!W11 -> 54.232247 | AL10: =IF(Calc!BG11=0,0,Calc!CQ11) -> 0 | AM10: =+Calc!X11 -> 46.497373 | AN10: =IF(Calc!BH11=0,0,Calc!CR11) -> 0 | AO10: =+Calc!Y11 -> 0 | AP10: =IF(Calc!BJ11=0,0,Calc!CS11) -> 0 | AQ10: =+Calc!Z11 -> 0 | AR10: =IF(Calc!BL11=0,0,Calc!CT11) -> 0 | AS10: =+Calc!AA11 -> 0 | AT10: =IF(Calc!BN11=0,0,Calc!CU11) -> 0 | AU10: =+Calc!AB11 -> 0 | AV10: =IF(Calc!BP11=0,0,Calc!CV11) -> 0 | AW10: =+Calc!AC11 -> 0 | AX10: =IF(Calc!BR11=0,0,Calc!CW11) -> 0 | AY10: =+Calc!AD11 -> 0 | AZ10: =IF(Calc!BT11=0,0,Calc!CX11) -> #DIV/0! | BA10: =+Calc!AE11 -> 0 | BB10: =IF(Calc!BV11=0,0,Calc!CY11) -> 0 | BC10: =+Calc!AF11 -> 0 | BD10: =IF(Calc!BX11=0,0,Calc!CZ11) -> 0 | BE10: =+Calc!AG11 -> 0 | BF10: =IF(Calc!BZ11=0,0,Calc!DA11) -> 0 | BG10: =+Calc!AH11 -> 0 | BH10: =IF(Calc!CB11=0,0,Calc!DB11) -> 0 | BI10: =+Calc!AI11 -> 0 | BJ10: =IF(Calc!BS11=0,0,Calc!DC11) -> 0 | BK10: =+Calc!AJ11 -> 71.271236 | BM10: =IF(Calc!BT11=0,0,Calc!DD11) -> #DIV/0!
B11: New Product Revenue (VolxASP) | E11: =IF($D$2="$ K",Calc!G12,Calc!G12/1000) -> 0 | F11: =IF(Calc!AQ12=0,0,IF($D$2="$ M",Calc!CA12/1000,Calc!CA12)) -> 0 | G11: =IF($D$2="$ K",Calc!H12,Calc!H12/1000) -> 0 | H11: =IF(Calc!AR12=0,0,IF($D$2="$ M",Calc!CB12/1000,Calc!CB12)) -> 0 | I11: =IF($D$2="$ K",Calc!I12,Calc!I12/1000) -> 0 | J11: =IF(Calc!AS12=0,0,IF($D$2="$ M",Calc!CC12/1000,Calc!CC12)) -> 0 | K11: =IF($D$2="$ K",Calc!J12,Calc!J12/1000) -> 0 | L11: =IF(Calc!AT12=0,0,IF($D$2="$ M",Calc!CD12/1000,Calc!CD12)) -> 0 | M11: =IF($D$2="$ K",Calc!K12,Calc!K12/1000) -> 0 | N11: =IF(Calc!AU12=0,0,IF($D$2="$ M",Calc!CE12/1000,Calc!CE12)) -> 0 | O11: =IF($D$2="$ K",Calc!L12,Calc!L12/1000) -> 16.667204 | P11: =IF(Calc!AV12=0,0,IF($D$2="$ M",Calc!CF12/1000,Calc!CF12)) -> 0 | Q11: =IF($D$2="$ K",Calc!M12,Calc!M12/1000) -> 38.568729 | R11: =IF(Calc!AW12=0,0,IF($D$2="$ M",Calc!CG12/1000,Calc!CG12)) -> 0 | S11: =IF($D$2="$ K",Calc!N12,Calc!N12/1000) -> 73.523969 | T11: =IF(Calc!AX12=0,0,IF($D$2="$ M",Calc!CH12/1000,Calc!CH12)) -> 0 | U11: =IF($D$2="$ K",Calc!O12,Calc!O12/1000) -> 110.319 | V11: =IF(Calc!AY12=0,0,IF($D$2="$ M",Calc!CI12/1000,Calc!CI12)) -> 0 | W11: =IF($D$2="$ K",Calc!P12,Calc!P12/1000) -> 137.34105 | X11: =IF(Calc!AZ12=0,0,IF($D$2="$ M",Calc!CJ12/1000,Calc!CJ12)) -> 0 | Y11: =IF($D$2="$ K",Calc!Q12,Calc!Q12/1000) -> 152.8651 | Z11: =IF(Calc!BA12=0,0,IF($D$2="$ M",Calc!CK12/1000,Calc!CK12)) -> 0 | AA11: =IF($D$2="$ K",Calc!R12,Calc!R12/1000) -> 165.74457 | AB11: =IF(Calc!BB12=0,0,IF($D$2="$ M",Calc!CL12/1000,Calc!CL12)) -> 0 | AC11: =IF($D$2="$ K",Calc!S12,Calc!S12/1000) -> 190.18987 | AD11: =IF(Calc!BC12=0,0,IF($D$2="$ M",Calc!CM12/1000,Calc!CM12)) -> 0 | AE11: =IF($D$2="$ K",Calc!T12,Calc!T12/1000) -> 198.82688 | AF11: =IF(Calc!BD12=0,0,IF($D$2="$ M",Calc!CN12/1000,Calc!CN12)) -> 0 | AG11: =IF($D$2="$ K",Calc!U12,Calc!U12/1000) -> 239.30804 | AH11: =IF(Calc!BE12=0,0,IF($D$2="$ M",Calc!CO12/1000,Calc!CO12)) -> 0 | AI11: =IF($D$2="$ K",Calc!V12,Calc!V12/1000) -> 268.53502 | AJ11: =IF(Calc!BF12=0,0,IF($D$2="$ M",Calc!CP12/1000,Calc!CP12)) -> 0 | AK11: =IF($D$2="$ K",Calc!W12,Calc!W12/1000) -> 308.70314 | AL11: =IF(Calc!BG12=0,0,IF($D$2="$ M",Calc!CQ12/1000,Calc!CQ12)) -> 0 | AM11: =IF($D$2="$ K",Calc!X12,Calc!X12/1000) -> 252.78709 | AN11: =IF(Calc!BH12=0,0,IF($D$2="$ M",Calc!CR12/1000,Calc!CR12)) -> 0 | AO11: =IF($D$2="$ K",Calc!Y12,Calc!Y12/1000) -> 0 | AP11: =IF(Calc!BJ12=0,0,IF($D$2="$ M",Calc!CS12/1000,Calc!CS12)) -> 0 | AQ11: =IF($D$2="$ K",Calc!Z12,Calc!Z12/1000) -> 0 | AR11: =IF(Calc!BL12=0,0,IF($D$2="$ M",Calc!CT12/1000,Calc!CT12)) -> 0 | AS11: =IF($D$2="$ K",Calc!AA12,Calc!AA12/1000) -> 0 | AT11: =IF(Calc!BN12=0,0,IF($D$2="$ M",Calc!CU12/1000,Calc!CU12)) -> 0 | AU11: =IF($D$2="$ K",Calc!AB12,Calc!AB12/1000) -> 0 | AV11: =IF(Calc!BP12=0,0,IF($D$2="$ M",Calc!CV12/1000,Calc!CV12)) -> 0 | AW11: =IF($D$2="$ K",Calc!AC12,Calc!AC12/1000) -> 0 | AX11: =IF(Calc!BR12=0,0,IF($D$2="$ M",Calc!CW12/1000,Calc!CW12)) -> 0 | AY11: =IF($D$2="$ K",Calc!AD12,Calc!AD12/1000) -> 0 | AZ11: =IF(Calc!BT12=0,0,IF($D$2="$ M",Calc!CX12/1000,Calc!CX12)) -> 0 | BA11: =IF($D$2="$ K",Calc!AE12,Calc!AE12/1000) -> 0 | BB11: =IF(Calc!BV12=0,0,IF($D$2="$ M",Calc!CY12/1000,Calc!CY12)) -> 0 | BC11: =IF($D$2="$ K",Calc!AF12,Calc!AF12/1000) -> 0 | BD11: =IF(Calc!BX12=0,0,IF($D$2="$ M",Calc!CZ12/1000,Calc!CZ12)) -> 0 | BE11: =IF($D$2="$ K",Calc!AG12,Calc!AG12/1000) -> 0 | BF11: =IF(Calc!BZ12=0,0,IF($D$2="$ M",Calc!DA12/1000,Calc!DA12)) -> 0 | BG11: =IF($D$2="$ K",Calc!AH12,Calc!AH12/1000) -> 0 | BH11: =IF(Calc!CB12=0,0,IF($D$2="$ M",Calc!DB12/1000,Calc!DB12)) -> 0 | BI11: =IF($D$2="$ K",Calc!AI12,Calc!AI12/1000) -> 0 | BJ11: =IF(Calc!BS12=0,0,IF($D$2="$ M",Calc!DC12/1000,Calc!DC12)) -> 0 | BK11: =IF($D$2="$ K",Calc!AJ12,Calc!AJ12/1000) -> 376.41995 | BM11: =IF(Calc!BT12=0,0,IF($D$2="$ M",Calc!DD12/1000,Calc!DD12)) -> 0 | BP11: =IF($D$2="$ K",Calc!AM12,Calc!AM12/1000) -> 1323.3544
B12: Less: Cannibilzation | E12: =IF($D$2="$ K",Calc!G13,Calc!G13/1000) -> 0 | F12: =IF(Calc!AQ13=0,0,IF($D$2="$ M",Calc!CA13/1000,0)) -> 0 | G12: =IF($D$2="$ K",Calc!H13,Calc!H13/1000) -> 0 | H12: =IF(Calc!AR13=0,0,IF($D$2="$ M",Calc!CB13/1000,0)) -> 0 | I12: =IF($D$2="$ K",Calc!I13,Calc!I13/1000) -> 0 | J12: =IF(Calc!AS13=0,0,IF($D$2="$ M",Calc!CC13/1000,0)) -> 0 | K12: =IF($D$2="$ K",Calc!J13,Calc!J13/1000) -> 0 | L12: =IF(Calc!AT13=0,0,IF($D$2="$ M",Calc!CD13/1000,0)) -> 0 | M12: =IF($D$2="$ K",Calc!K13,Calc!K13/1000) -> 0 | N12: =IF(Calc!AU13=0,0,IF($D$2="$ M",Calc!CE13/1000,0)) -> 0 | O12: =IF($D$2="$ K",Calc!L13,Calc!L13/1000) -> 0 | P12: =IF(Calc!AV13=0,0,IF($D$2="$ M",Calc!CF13/1000,0)) -> 0 | Q12: =IF($D$2="$ K",Calc!M13,Calc!M13/1000) -> 0 | R12: =IF(Calc!AW13=0,0,IF($D$2="$ M",Calc!CG13/1000,0)) -> 0 | S12: =IF($D$2="$ K",Calc!N13,Calc!N13/1000) -> 0 | T12: =IF(Calc!AX13=0,0,IF($D$2="$ M",Calc!CH13/1000,0)) -> 0 | U12: =IF($D$2="$ K",Calc!O13,Calc!O13/1000) -> 0 | V12: =IF(Calc!AY13=0,0,IF($D$2="$ M",Calc!CI13/1000,0)) -> 0 | W12: =IF($D$2="$ K",Calc!P13,Calc!P13/1000) -> 0 | X12: =IF(Calc!AZ13=0,0,IF($D$2="$ M",Calc!CJ13/1000,0)) -> 0 | Y12: =IF($D$2="$ K",Calc!Q13,Calc!Q13/1000) -> 0 | Z12: =IF(Calc!BA13=0,0,IF($D$2="$ M",Calc!CK13/1000,0)) -> 0 | AA12: =IF($D$2="$ K",Calc!R13,Calc!R13/1000) -> 0 | AB12: =IF(Calc!BB13=0,0,IF($D$2="$ M",Calc!CL13/1000,0)) -> 0 | AC12: =IF($D$2="$ K",Calc!S13,Calc!S13/1000) -> 0 | AD12: =IF(Calc!BC13=0,0,IF($D$2="$ M",Calc!CM13/1000,0)) -> 0 | AE12: =IF($D$2="$ K",Calc!T13,Calc!T13/1000) -> 0 | AF12: =IF(Calc!BD13=0,0,IF($D$2="$ M",Calc!CN13/1000,0)) -> 0 | AG12: =IF($D$2="$ K",Calc!U13,Calc!U13/1000) -> 0 | AH12: =IF(Calc!BE13=0,0,IF($D$2="$ M",Calc!CO13/1000,0)) -> 0 | AI12: =IF($D$2="$ K",Calc!V13,Calc!V13/1000) -> 0 | AJ12: =IF(Calc!BF13=0,0,IF($D$2="$ M",Calc!CP13/1000,0)) -> 0 | AK12: =IF($D$2="$ K",Calc!W13,Calc!W13/1000) -> 0 | AL12: =IF(Calc!BG13=0,0,IF($D$2="$ M",Calc!CQ13/1000,0)) -> 0 | AM12: =IF($D$2="$ K",Calc!X13,Calc!X13/1000) -> 0 | AN12: =IF(Calc!BH13=0,0,IF($D$2="$ M",Calc!CR13/1000,0)) -> 0 | AO12: =IF($D$2="$ K",Calc!Y13,Calc!Y13/1000) -> 0 | AP12: =IF(Calc!BJ13=0,0,IF($D$2="$ M",Calc!CS13/1000,0)) -> 0 | AQ12: =IF($D$2="$ K",Calc!Z13,Calc!Z13/1000) -> 0 | AR12: =IF(Calc!BL13=0,0,IF($D$2="$ M",Calc!CT13/1000,0)) -> 0 | AS12: =IF($D$2="$ K",Calc!AA13,Calc!AA13/1000) -> 0 | AT12: =IF(Calc!BN13=0,0,IF($D$2="$ M",Calc!CU13/1000,0)) -> 0 | AU12: =IF($D$2="$ K",Calc!AB13,Calc!AB13/1000) -> 0 | AV12: =IF(Calc!BP13=0,0,IF($D$2="$ M",Calc!CV13/1000,0)) -> 0 | AW12: =IF($D$2="$ K",Calc!AC13,Calc!AC13/1000) -> 0 | AX12: =IF(Calc!BR13=0,0,IF($D$2="$ M",Calc!CW13/1000,0)) -> 0 | AY12: =IF($D$2="$ K",Calc!AD13,Calc!AD13/1000) -> 0 | AZ12: =IF(Calc!BT13=0,0,IF($D$2="$ M",Calc!CX13/1000,0)) -> 0 | BA12: =IF($D$2="$ K",Calc!AE13,Calc!AE13/1000) -> 0 | BB12: =IF(Calc!BV13=0,0,IF($D$2="$ M",Calc!CY13/1000,0)) -> 0 | BC12: =IF($D$2="$ K",Calc!AF13,Calc!AF13/1000) -> 0 | BD12: =IF(Calc!BX13=0,0,IF($D$2="$ M",Calc!CZ13/1000,0)) -> 0 | BE12: =IF($D$2="$ K",Calc!AG13,Calc!AG13/1000) -> 0 | BF12: =IF(Calc!BZ13=0,0,IF($D$2="$ M",Calc!DA13/1000,0)) -> 0 | BG12: =IF($D$2="$ K",Calc!AH13,Calc!AH13/1000) -> 0 | BH12: =IF(Calc!CB13=0,0,IF($D$2="$ M",Calc!DB13/1000,0)) -> 0 | BI12: =IF($D$2="$ K",Calc!AI13,Calc!AI13/1000) -> 0 | BJ12: =IF(Calc!BS13=0,0,IF($D$2="$ M",Calc!DC13/1000,0)) -> 0 | BK12: =IF($D$2="$ K",Calc!AJ13,Calc!AJ13/1000) -> 0 | BM12: =IF(Calc!BT13=0,0,IF($D$2="$ M",Calc!DD13/1000,0)) -> 0 | BP12: =IF($D$2="$ K",Calc!AM13,Calc!AM13/1000) -> 0
